Workbook

Sheet 规则表
A1: 规则参数
A2: 股东资本 | B2: 1000000
A3: 贷款倍数 | B3: 3
A4: 管理费 | B4: 10000 | D4: 使用说明：1.规则表绿色代表表格引用数据，表格公式计算结果会根据绿色区域填入的规则实时更改，白色区域不可更改 2.灰色代表有公式，尽量不要乱动 3.黄色同样有公式，但如有需要可以根据实际情况更改 4.白色和橙色代表需要手动填入的数据 5.注意！！！维护费、折旧、销售收入、激励、工资这些数据仅为参考值，可用于协助做方案，实际操作时需根据实际情况更改 6.如需使用12小时制，需自行修改激励或辞退福利 7.涨薪行为默认下一年年初辞退，不再多给工资，且辞退福利需要自己计算 8.该表格需要使用WPS2019以后的版本或excel365版本打开，否则会出现部分报错情况
A5: 税率 | B5: 0.25
A6: 1季短贷 | B6: 0.03
A7: 4季短贷 | B7: 0.1
A8: 2年长贷 | B8: 0.03
A9: 贴现 | B9: 利率
A10: 0 | B10: 0
A11: 1 | B11: 0.02
A12: 2 | B12: 0.04
A13: 3 | B13: 0.06
A14: 4 | B14: 0.08
A16: 线型名称 | B16: 购买价格（元） | C16: 安装周期（季） | D16: 生产周期（季） | E16: 产量 | F16: 转产周期（季） | G16: 转产价格（元） | H16: 残值（元） | I16: 维修费用（元） | J16: 普通工 | K16: 高级工 | L16: 碳排放量 | M16: 折旧年限 | N16: 普通效率（%） | O16: 高级效率（%） | P16: 8小时总产量 | Q16: 12小时总产量 | R16: 单条线工 资（季） | S16: 单条线生 产费用 | T16: 单条线总激励 | U16: 每次8小时消耗费用 | V16: 每次12小时消耗费用 | W16: 单条线涨薪总费用 | X16: 每次线涨薪费用
A17: 传统线 | B17: 100000 | C17: 0 | D17: 2 | E17: 50 | F17: 0 | G17: 20000 | H17: 10000 | I17: 10000 | J17: 2 | K17: 1 | L17: 0 | M17: 4 | N17: 100 | O17: 100 | P17: =INT(E17*(1+J17*N17/400+K17*O17/100)) -> 125 | Q17: =INT(E17*(1+J17*N17/400+K17*O17/100)*$L$32) -> 150 | R17: =(J17*$L$23+K17*$L$24)*3 -> 9000 | S17: =J17*P17*$M$23+K17*P17*$M$24 -> 12500 | T17: =(N17-$O$23)*$M$27*J17+(O17-$O$24)*$M$27*K17 -> 12000 | U17: =(J17+K17)*$M$27*$M$31 -> 600 | V17: =(J17+K17)*$M$27*$M$32 -> 15000 | W17: =ROUNDUP((N17-$O$23)*$M$28*J17+(O17-$O$24)*$M$28*K17,0) -> 2040 | X17: =ROUNDUP($M$31*$M$28*J17+$M$31*$M$28*K17,0) -> 102
A18: 自动线 | B18: 160000 | C18: 1 | D18: 1 | E18: 35 | F18: 0 | G18: 10000 | H18: 10000 | I18: 10000 | J18: 1 | K18: 1 | L18: 0 | M18: 4 | N18: 100 | O18: 100 | P18: =INT(E18*(1+J18*N18/400+K18*O18/100)) -> 78 | Q18: =INT(E18*(1+J18*N18/400+K18*O18/100)*$L$32) -> 94 | R18: =(J18*$L$23+K18*$L$24)*3 -> 7500 | S18: =J18*P18*$M$23+K18*P18*$M$24 -> 5850 | T18: =(N18-$O$23)*$M$27*J18+(O18-$O$24)*$M$27*K18 -> 8000 | U18: =(J18+K18)*$M$27*$M$31 -> 400 | V18: =(J18+K18)*$M$27*$M$32 -> 10000 | W18: =ROUNDUP((N18-$O$23)*$M$28*J18+(O18-$O$24)*$M$28*K18,0) -> 1360 | X18: =ROUNDUP($M$31*$M$28*J18+$M$31*$M$28*K18,0) -> 68
A19: 智能线 | B19: 250000 | C19: 2 | D19: 1 | E19: 30 | F19: 0 | G19: 0 | H19: 50000 | I19: 10000 | J19: 1 | K19: 2 | L19: 0 | M19: 4 | N19: 100 | O19: 100 | P19: =INT(E19*(1+J19*N19/400+K19*O19/100)) -> 97 | Q19: =INT(E19*(1+J19*N19/400+K19*O19/100)*$L$32) -> 117 | R19: =(J19*$L$23+K19*$L$24)*3 -> 13500 | S19: =J19*P19*$M$23+K19*P19*$M$24 -> 12125 | T19: =(N19-$O$23)*$M$27*J19+(O19-$O$24)*$M$27*K19 -> 12000 | U19: =(J19+K19)*$M$27*$M$31 -> 600 | V19: =(J19+K19)*$M$27*$M$32 -> 15000 | W19: =ROUNDUP((N19-$O$23)*$M$28*J19+(O19-$O$24)*$M$28*K19,0) -> 2040 | X19: =ROUNDUP($M$31*$M$28*J19+$M$31*$M$28*K19,0) -> 102
A22: 产品编号 | B22: 产品成本 | C22: R1 | D22: R2 | E22: R3 | F22: R4 | G22: R5 | H22: 材料总费用 | J22: 名称 | K22: 编码 | L22: 初始期望工资（元） | M22: 计件 | N22: 每季度数量 | O22: 效率（%） | U22: 12小时制
A23: =现金流量表!H54 -> P1 | B23: 1800 | C23: 2 | D23: 2 | E23: 1 | F23: 0 | G23: 0 | H23: =C23*$C$30+D23*$D$30+E23*$E$30+F23*$F$30+G23*$G$30 -> 500 | J23: 初级工 | K23: GR1 | L23: 500 | M23: 25 | N23: 20 | O23: 60 | U23: 单个成本 | V23: 成本利润率
A24: =现金流量表!H55 -> P2 | B24: 3400 | C24: 2 | D24: 3 | E24: 2 | F24: 2 | G24: 0 | H24: =C24*$C$30+D24*$D$30+E24*$E$30+F24*$F$30+G24*$G$30 -> 900 | J24: 高级工 | K24: GR2 | L24: 2000 | M24: 50 | N24: 10 | O24: 60 | S24: 利润 | T24: 4150 | U24: =(V17-U17)/(Q17-P17) -> 576 | V24: =T24/U24 -> 7.2048611
A25: =现金流量表!H56 -> P3 | B25: 5800 | C25: 5 | D25: 3 | E25: 3 | F25: 4 | G25: 0 | H25: =C25*$C$30+D25*$D$30+E25*$E$30+F25*$F$30+G25*$G$30 -> 1500 | U25: =(V18-U18)/(Q18-P18) -> 600 | V25: =T25/U25 -> 0
A26: =现金流量表!H57 -> P4 | B26: 8600 | C26: 6 | D26: 7 | E26: 5 | F26: 5 | H26: =C26*$C$30+D26*$D$30+E26*$E$30+F26*$F$30+G26*$G$30 -> 2300 | J26: 激励名称 | K26: 编码 | L26: 提升效率比例（%） | M26: 每1%需要费用 | U26: =(V19-U19)/(Q19-P19) -> 720 | V26: =T26/U26 -> 0
A27: =现金流量表!H58 -> 0 | B27: 6000 | H27: =C27*$C$30+D27*$D$30+E27*$E$30+F27*$F$30+G27*$G$30 -> 0 | J27: 奖金激励 | K27: JL1 | L27: 100 | M27: =ROUNDUP(10000/L27,0) -> 100
B28: 送货周期 | C28: 1 | D28: 1 | E28: 1 | F28: 2 | G28: 1 | J28: 涨薪激励 | K28: JL2 | L28: 600 | M28: =ROUNDUP(10000/L28,0) -> 17 | R28: =B17+R17+S17+T17+P17*H23 -> 196000 | S28: =R28/P17 -> 1568
B29: 账期 | C29: 0 | D29: 0 | E29: 0 | F29: 0 | G29: 0
B30: 材料价格 | C30: 100 | D30: 100 | E30: 100 | F30: 100 | G30: 0 | J30: 班次名称 | K30: 班次编码 | L30: 产量加成（倍） | M30: 效率损失（%）
J31: 8小时制 | K31: BC1 | L31: 1 | M31: 2 | Q31: 正单与补单利润差
J32: 12小时制 | K32: BC2 | L32: 1.2 | M32: 50
A35: 8小时 | B35: =A17 -> 传统线 | C35: =A18 -> 自动线 | D35: =A19 -> 智能线
A36: =A23 -> P1 | B36: =(H23*$P$17+$S$17+$U$17+$R$17*2)/$P$17 -> 748.8 | C36: =(H23*$P$18+$S$18+$U$18+$R$18)/$P$18 -> 676.28205 | D36: =(H23*$P$19+$S$19+$U$19+$R$19)/$P$19 -> 770.36082
A37: =A24 -> P2 | B37: =(H24*$P$17+$S$17+$U$17+$R$17*2)/$P$17 -> 1148.8 | C37: =(H24*$P$18+$S$18+$U$18+$R$18)/$P$18 -> 1076.2821 | D37: =(H24*$P$19+$S$19+$U$19+$R$19)/$P$19 -> 1170.3608
A38: =A25 -> P3 | B38: =(H25*$P$17+$S$17+$U$17+$R$17*2)/$P$17 -> 1748.8 | C38: =(H25*$P$18+$S$18+$U$18+$R$18)/$P$18 -> 1676.2821 | D38: =(H25*$P$19+$S$19+$U$19+$R$19)/$P$19 -> 1770.3608
A39: =A26 -> P4 | B39: =(H26*$P$17+$S$17+$U$17+$R$17*2)/$P$17 -> 2548.8 | C39: =(H26*$P$18+$S$18+$U$18+$R$18)/$P$18 -> 2476.2821 | D39: =(H26*$P$19+$S$19+$U$19+$R$19)/$P$19 -> 2570.3608
A40: =A27 -> 0 | B40: =(H27*$P$17+$S$17+$U$17+$R$17*2)/$P$17 -> 248.8 | C40: =(H27*$P$18+$S$18+$U$18+$R$18)/$P$18 -> 176.28205 | D40: =(H27*$P$19+$S$19+$U$19+$R$19)/$P$19 -> 270.36082
A43: 12小时 | B43: =B35 -> 传统线 | C43: =C35 -> 自动线 | D43: =D35 -> 智能线
A44: =A36 -> P1 | B44: =($Q$17*H23+$R$17+$S$17+$V$17)/$Q$17 -> 743.33333 | C44: =($Q$18*H23+$R$18+$S$18+$V$18)/$Q$18 -> 748.40426 | D44: =($Q$19*H23+$R$19+$S$19+$V$19)/$Q$19 -> 847.22222 | K44: =18*94 -> 1692
A45: =A37 -> P2 | B45: =($Q$17*H24+$R$17+$S$17+$V$17)/$Q$17 -> 1143.3333 | C45: =($Q$18*H24+$R$18+$S$18+$V$18)/$Q$18 -> 1148.4043 | D45: =($Q$19*H24+$R$19+$S$19+$V$19)/$Q$19 -> 1247.2222
A46: =A38 -> P3 | B46: =($Q$17*H25+$R$17+$S$17+$V$17)/$Q$17 -> 1743.3333 | C46: =($Q$18*H25+$R$18+$S$18+$V$18)/$Q$18 -> 1748.4043 | D46: =($Q$19*H25+$R$19+$S$19+$V$19)/$Q$19 -> 1847.2222
A47: =A39 -> P4 | B47: =($Q$17*H26+$R$17+$S$17+$V$17)/$Q$17 -> 2543.3333 | C47: =($Q$18*H26+$R$18+$S$18+$V$18)/$Q$18 -> 2548.4043 | D47: =($Q$19*H26+$R$19+$S$19+$V$19)/$Q$19 -> 2647.2222
A48: =A40 -> 0 | B48: =($Q$17*H27+$R$17+$S$17+$V$17)/$Q$17 -> 243.33333 | C48: =($Q$18*H27+$R$18+$S$18+$V$18)/$Q$18 -> 248.40426 | D48: =($Q$19*H27+$R$19+$S$19+$V$19)/$Q$19 -> 347.22222

Sheet 订单贴现表
C1: 第一年 | G1: 第二年 | K1: 第三年 | O1: 第四年
C2: 第一季 | D2: 第二季 | E2: 第三季 | F2: 第四季 | G2: 第一季 | H2: 第二季 | I2: 第三季 | J2: 第四季 | K2: 第一季 | L2: 第二季 | M2: 第三季 | N2: 第四季 | O2: 第一季 | P2: 第二季 | Q2: 第三季 | R2: 第四季
A3: 需填 | B3: 0期
B4: 1期
B5: 2期
B6: 3期
B7: 4期
A8: 期初 | B8: 已收 | C8: =N(OFFSET(C8,-5,0))+N(OFFSET(C8,-4,-1))+N(OFFSET(C8,-3,-2))+IFERROR(N(OFFSET(C8,-2,-3)),0)+IFERROR(N(OFFSET(C8,-1,-4)),0)+C3 -> 0 | D8: =C9+D3-现金流量表!C50 -> 0 | E8: =D9+E3-现金流量表!D50 -> 0 | F8: =E9+F3-现金流量表!E51 -> 0 | G8: =F9+G3-现金流量表!F51 -> 0 | H8: =G9+H3-现金流量表!O51 -> 0 | I8: =H9+I3-现金流量表!P51 -> 0 | J8: =I9+J3-现金流量表!Q51 -> 0 | K8: =J9+K3-现金流量表!R51 -> 0 | L8: =K9+L3-现金流量表!AA51 -> 0 | M8: =L9+M3-现金流量表!AB51 -> 0 | N8: =M9+N3-现金流量表!AC51 -> 0 | O8: =N9+O3-现金流量表!AD51 -> 0 | P8: =O9+P3-现金流量表!AK51 -> 0 | Q8: =P9+Q3-现金流量表!AL51 -> 0 | R8: =Q9+R3-现金流量表!AM51 -> 0
B9: 1期 | C9: =N(OFFSET(C9,-5,0))+N(OFFSET(C9,-4,-1))+N(OFFSET(C9,-3,-2))+IFERROR(N(OFFSET(C9,-2,-3)),0)+C4 -> 0 | D9: =C10+D4-现金流量表!C51 -> 0 | E9: =D10+E4-现金流量表!D51 -> 0 | F9: =E10+F4-现金流量表!E52 -> 0 | G9: =F10+G4-现金流量表!F52 -> 0 | H9: =G10+H4-现金流量表!O52 -> 0 | I9: =H10+I4-现金流量表!P52 -> 0 | J9: =I10+J4-现金流量表!Q52 -> 0 | K9: =J10+K4-现金流量表!R52 -> 0 | L9: =K10+L4-现金流量表!AA52 -> 0 | M9: =L10+M4-现金流量表!AB52 -> 0 | N9: =M10+N4-现金流量表!AC52 -> 0 | O9: =N10+O4-现金流量表!AD52 -> 0 | P9: =O10+P4-现金流量表!AK52 -> 0 | Q9: =P10+Q4-现金流量表!AL52 -> 0 | R9: =Q10+R4-现金流量表!AM52 -> 0
B10: 2期 | C10: =N(OFFSET(C10,-5,0))+N(OFFSET(C10,-4,-1))+N(OFFSET(C10,-3,-2))+C5 -> 0 | D10: =C11+D5-现金流量表!C52 -> 0 | E10: =D11+E5-现金流量表!D52 -> 0 | F10: =E11+F5-现金流量表!E53 -> 0 | G10: =F11+G5-现金流量表!F53 -> 0 | H10: =G11+H5-现金流量表!O53 -> 0 | I10: =H11+I5-现金流量表!P53 -> 0 | J10: =I11+J5-现金流量表!Q53 -> 0 | K10: =J11+K5-现金流量表!R53 -> 0 | L10: =K11+L5-现金流量表!AA53 -> 0 | M10: =L11+M5-现金流量表!AB53 -> 0 | N10: =M11+N5-现金流量表!AC53 -> 0 | O10: =N11+O5-现金流量表!AD53 -> 0 | P10: =O11+P5-现金流量表!AK53 -> 0 | Q10: =P11+Q5-现金流量表!AL53 -> 0 | R10: =Q11+R5-现金流量表!AM53 -> 0
B11: 3期 | C11: =N(OFFSET(C11,-5,0))+N(OFFSET(C11,-4,-1))+C6 -> 0 | D11: =C12+D6-现金流量表!C53 -> 0 | E11: =E6+D12-现金流量表!D53 -> 0 | F11: =E12+F6-现金流量表!E54 -> 0 | G11: =F12+G6-现金流量表!F54 -> 0 | H11: =G12+H6-现金流量表!O54 -> 0 | I11: =H12+I6-现金流量表!P54 -> 0 | J11: =I12+J6-现金流量表!Q54 -> 0 | K11: =J12+K6-现金流量表!R54 -> 0 | L11: =K12+L6-现金流量表!AA54 -> 0 | M11: =L12+M6-现金流量表!AB54 -> 0 | N11: =M12+N6-现金流量表!AC54 -> 0 | O11: =N12+O6-现金流量表!AD54 -> 0 | P11: =O12+P6-现金流量表!AK54 -> 0 | Q11: =P12+Q6-现金流量表!AL54 -> 0 | R11: =Q12+R6-现金流量表!AM54 -> 0
B12: 4期 | C12: =N(OFFSET(C12,-5,0))+C7 -> 0 | D12: =D7-现金流量表!C54 -> 0 | E12: =E7-现金流量表!D54 -> 0 | F12: =F7 -> 0 | G12: =G7 -> 0 | H12: =H7 -> 0 | I12: =I7 -> 0 | J12: =J7 -> 0 | K12: =K7 -> 0 | L12: =L7 -> 0 | M12: =M7 -> 0 | ... R12: =R7 -> 0
A13: 实时贴现值 | B13: 已收 | C13: =C8-现金流量表!C50 -> 0 | D13: =D8-现金流量表!D50 -> 0 | E13: =E8-现金流量表!E50 -> 0 | F13: =F8-现金流量表!F50 -> 0 | G13: =G8-现金流量表!O50 -> 0 | H13: =H8-现金流量表!P50 -> 0 | I13: =I8-现金流量表!Q50 -> 0 | J13: =J8-现金流量表!R50 -> 0 | K13: =K8-现金流量表!AA50 -> 0 | L13: =L8-现金流量表!AB50 -> 0 | M13: =M8-现金流量表!AC50 -> 0 | N13: =N8-现金流量表!AD50 -> 0 | O13: =O8-现金流量表!AK50 -> 0 | P13: =P8-现金流量表!AL50 -> 0 | Q13: =Q8-现金流量表!AM50 -> 0 | R13: =R8-现金流量表!AN50 -> 0
B14: 1期 | C14: =C9-现金流量表!C51 -> 0 | D14: =D9-现金流量表!D51 -> 0 | E14: =E9-现金流量表!E51 -> 0 | F14: =F9-现金流量表!F51 -> 0 | G14: =G9-现金流量表!O51 -> 0 | H14: =H9-现金流量表!P51 -> 0 | I14: =I9-现金流量表!Q51 -> 0 | J14: =J9-现金流量表!R51 -> 0 | K14: =K9-现金流量表!AA51 -> 0 | L14: =L9-现金流量表!AB51 -> 0 | M14: =M9-现金流量表!AC51 -> 0 | N14: =N9-现金流量表!AD51 -> 0 | O14: =O9-现金流量表!AK51 -> 0 | P14: =P9-现金流量表!AL51 -> 0 | Q14: =Q9-现金流量表!AM51 -> 0 | R14: =R9-现金流量表!AN51 -> 0
B15: 2期 | C15: =C10-现金流量表!C52 -> 0 | D15: =D10-现金流量表!D52 -> 0 | E15: =E10-现金流量表!E52 -> 0 | F15: =F10-现金流量表!F52 -> 0 | G15: =G10-现金流量表!O52 -> 0 | H15: =H10-现金流量表!P52 -> 0 | I15: =I10-现金流量表!Q52 -> 0 | J15: =J10-现金流量表!R52 -> 0 | K15: =K10-现金流量表!AA52 -> 0 | L15: =L10-现金流量表!AB52 -> 0 | M15: =M10-现金流量表!AC52 -> 0 | N15: =N10-现金流量表!AD52 -> 0 | O15: =O10-现金流量表!AK52 -> 0 | P15: =P10-现金流量表!AL52 -> 0 | Q15: =Q10-现金流量表!AM52 -> 0 | R15: =R10-现金流量表!AN52 -> 0
B16: 3期 | C16: =C11-现金流量表!C53 -> 0 | D16: =D11-现金流量表!D53 -> 0 | E16: =E11-现金流量表!E53 -> 0 | F16: =F11-现金流量表!F53 -> 0 | G16: =G11-现金流量表!O53 -> 0 | H16: =H11-现金流量表!P53 -> 0 | I16: =I11-现金流量表!Q53 -> 0 | J16: =J11-现金流量表!R53 -> 0 | K16: =K11-现金流量表!AA53 -> 0 | L16: =L11-现金流量表!AB53 -> 0 | M16: =M11-现金流量表!AC53 -> 0 | N16: =N11-现金流量表!AD53 -> 0 | O16: =O11-现金流量表!AK53 -> 0 | P16: =P11-现金流量表!AL53 -> 0 | Q16: =Q11-现金流量表!AM53 -> 0 | R16: =R11-现金流量表!AN53 -> 0
B17: 4期 | C17: =C12-现金流量表!C54 -> 0 | D17: =D12-现金流量表!D54 -> 0 | E17: =E12-现金流量表!E54 -> 0 | F17: =F12-现金流量表!F54 -> 0 | G17: =G12-现金流量表!O54 -> 0 | H17: =H12-现金流量表!P54 -> 0 | I17: =I12-现金流量表!Q54 -> 0 | J17: =J12-现金流量表!R54 -> 0 | K17: =K12-现金流量表!AA54 -> 0 | L17: =L12-现金流量表!AB54 -> 0 | M17: =M12-现金流量表!AC54 -> 0 | N17: =N12-现金流量表!AD54 -> 0 | O17: =O12-现金流量表!AK54 -> 0 | P17: =P12-现金流量表!AL54 -> 0 | Q17: =Q12-现金流量表!AM54 -> 0 | R17: =R12-现金流量表!AN54 -> 0
A18: 当季贴息 | C18: {=SUMPRODUCT(现金流量表!C50:C54,规则表!$B$10:$B$14)} -> 0 | D18: {=SUMPRODUCT(现金流量表!D50:D54,规则表!$B$10:$B$14)} -> 0 | E18: {=SUMPRODUCT(现金流量表!E50:E54,规则表!$B$10:$B$14)} -> 0 | F18: {=SUMPRODUCT(现金流量表!F50:F54,规则表!$B$10:$B$14)} -> 0 | G18: {=SUMPRODUCT(现金流量表!O50:O54,规则表!$B$10:$B$14)} -> 0 | H18: {=SUMPRODUCT(现金流量表!P50:P54,规则表!$B$10:$B$14)} -> 0 | I18: {=SUMPRODUCT(现金流量表!Q50:Q54,规则表!$B$10:$B$14)} -> 0 | J18: {=SUMPRODUCT(现金流量表!R50:R54,规则表!$B$10:$B$14)} -> 0 | K18: {=SUMPRODUCT(现金流量表!AA50:AA54,规则表!$B$10:$B$14)} -> 0 | L18: {=SUMPRODUCT(现金流量表!AB50:AB54,规则表!$B$10:$B$14)} -> 0 | M18: {=SUMPRODUCT(现金流量表!AC50:AC54,规则表!$B$10:$B$14)} -> 0 | N18: {=SUMPRODUCT(现金流量表!AD50:AD54,规则表!$B$10:$B$14)} -> 0 | O18: {=SUMPRODUCT(现金流量表!AK50:AK54,规则表!$B$10:$B$14)} -> 0 | P18: {=SUMPRODUCT(现金流量表!AL50:AL54,规则表!$B$10:$B$14)} -> 0 | Q18: {=SUMPRODUCT(现金流量表!AM50:AM54,规则表!$B$10:$B$14)} -> 0 | R18: {=SUMPRODUCT(现金流量表!AN50:AN54,规则表!$B$10:$B$14)} -> 0

Sheet 现金流量表
B1: 第一年 | C1: 第一季 | D1: 第二季 | E1: 第三季 | F1: 第四季 | G1: 上年所得税 | N1: 第二年 | O1: 第一季 | P1: 第二季 | Q1: 第三季 | R1: 第四季 | S1: 上年所得税 | T1: =J14 -> 0 | Z1: 第三年 | AA1: 第一季 | AB1: 第二季 | AC1: 第三季 | AD1: 第四季 | AE1: 上年所得税 | AF1: =V14 -> 6445499 | AJ1: 第四年 | AK1: 第一季 | AL1: 第二季 | AM1: 第三季 | AN1: 第四季 | AO1: 上年所得税 | AP1: =AH14 -> 0
B2: 现金盘点 | C2: =规则表!$B$2 -> 1000000 | D2: =C46 -> 2379997 | E2: =D46 -> 2159997 | F2: =E46 -> -966003 | G2: 综合费用表 | I2: 利润表 | N2: 现金盘点 | O2: =F46-T1 -> -1086003 | P2: =O46 -> 11531547 | Q2: =P46 -> 11411547 | R2: =Q46 -> 26570547 | S2: 综合费用表 | U2: 利润表 | Z2: 现金盘点 | AA2: =R46-AF1 -> 20005048 | AB2: =AA46 -> 19050643 | AC2: =AB46 -> 18930643 | AD2: =AC46 -> 18810643 | AE2: 综合费用表 | AG2: 利润表 | AJ2: 现金盘点 | AK2: =AD46-AP1 -> 18690643 | AL2: =AK46 -> 18570643 | AM2: =AL46 -> 18450643 | AN2: =AM46 -> 18330643 | AO2: 综合费用表 | AQ2: 利润表
B3: 损失 | G3: 项目 | H3: 值 | I3: 项目 | J3: 值 | N3: 损失 | S3: 项目 | T3: 值 | U3: 项目 | V3: 值 | Z3: 损失 | AE3: 项目 | AF3: 值 | AG3: 项目 | AH3: 值 | AJ3: 损失 | AO3: 项目 | AP3: 值 | AQ3: 项目 | AR3: 值
B4: 折旧 | C4: =生产建设!I53 -> 0 | D4: =生产建设!J53 -> 0 | E4: =生产建设!K53 -> 0 | F4: =生产建设!L53 -> 0 | G4: 管理费 | H4: =SUM(C15:F15) -> 120000 | I4: 销售收入 | J4: =SUM(C16:F17) -> 0 | K4: 销售收入、直接成本仅为做方案提供参考，如需精确，需自行填入 | N4: 折旧 | O4: =生产建设!M53 -> 0 | P4: =生产建设!N53 -> 0 | Q4: =生产建设!O53 -> 0 | R4: =生产建设!P53 -> 0 | S4: 管理费 | T4: =SUM(O15:R15) -> 120000 | U4: 销售收入 | V4: =SUM(O16:R17)+SUM(O22:R22) -> 36570000 | Z4: 折旧 | AA4: =生产建设!Q53 -> 0 | AB4: =生产建设!R53 -> 0 | AC4: =生产建设!S53 -> 0 | AD4: =生产建设!T53 -> 0 | AE4: 管理费 | AF4: =SUM(AA15:AD15) -> 120000 | AG4: 销售收入 | AJ4: 折旧 | AK4: =生产建设!U53 -> 0 | AL4: =生产建设!V53 -> 0 | AM4: =生产建设!W53 -> 0 | AN4: =生产建设!X53 -> 0 | AO4: 管理费 | AP4: =SUM(AK15:AN15) -> 120000 | AQ4: 销售收入
B5: 现金盘点 | C5: =C2-C3 -> 1000000 | D5: =D2-D3 -> 2379997 | E5: =E2-E3 -> 2159997 | F5: =F2-F3 -> -966003 | G5: 广告费 | H5: =SUM(C43:F43) -> 0 | I5: 直接成本 | J5: =E26+F26+D31+E31+D36+E36 -> 3180000 | N5: 现金盘点 | O5: =O2-O3 -> -1086003 | P5: =P2-P3 -> 11531547 | Q5: =Q2-Q3 -> 11411547 | R5: =R2-R3 -> 26570547 | S5: 广告费 | T5: =SUM(O43:R43) -> 0 | U5: 直接成本 | V5: =SUM(O26:R26)+SUM(O31:Q31)+SUM(O36:Q36)+F31+F36 -> 6360000 | Z5: 现金盘点 | AA5: =AA2-AA3 -> 20005048 | AB5: =AB2-AB3 -> 19050643 | AC5: =AC2-AC3 -> 18930643 | AD5: =AD2-AD3 -> 18810643 | AE5: 广告费 | AF5: =SUM(AA43:AD43) -> 0 | AG5: 直接成本 | AJ5: 现金盘点 | AK5: =AK2-AK3 -> 18690643 | AL5: =AL2-AL3 -> 18570643 | AM5: =AM2-AM3 -> 18450643 | AN5: =AN2-AN3 -> 18330643 | AO5: 广告费 | AP5: =SUM(AK43:AN43) -> 0 | AQ5: 直接成本
B6: 财务总监 | G6: 维修费 | H6: =SUM(C37:F37) -> 0 | I6: 毛利 | J6: =J4-J5 -> -3180000 | N6: 财务总监 | S6: 维修费 | T6: =SUM(O37:R37) -> 0 | U6: 毛利 | V6: =V4-V5 -> 30210000 | Z6: 财务总监 | AE6: 维修费 | AF6: =SUM(AA37:AD37) -> 0 | AG6: 毛利 | AH6: =AH4-AH5 -> 0 | AJ6: 财务总监 | AO6: 维修费 | AP6: =SUM(AK37:AN37) -> 0 | AQ6: 毛利 | AR6: =AR4-AR5 -> 0
B7: 短贷还款 | D7: =C12 -> 0 | E7: =D12 -> 0 | F7: =E12 -> 0 | G7: 转产费 | H7: =SUM(C35:F35) -> 0 | I7: 综合费用 | J7: =H20 -> 816003 | N7: 短贷还款 | O7: =F12+C13 -> 3000000 | P7: =O12+D13 -> 0 | Q7: =P12+E13 -> 0 | R7: =Q12+F13 -> 0 | S7: 转产费 | T7: =SUM(O35:R35) -> 0 | U7: 综合费用 | V7: =T20 -> 132000 | Z7: 短贷还款 | AA7: =R12+O13 -> 758550 | AB7: =AA12+P13 -> 0 | AC7: =AB12+Q13 -> 0 | AD7: =AC12+R13 -> 0 | AE7: 转产费 | AF7: =SUM(AA35:AD35) -> 0 | AG7: 综合费用 | AH7: =AF20 -> 120000 | AJ7: 短贷还款 | AK7: =AD12+AA13 -> 0 | AL7: =AK12+AB13 -> 0 | AM7: =AL12+AC13 -> 0 | AN7: =AM12+AD13 -> 0 | AO7: 转产费 | AP7: =SUM(AK35:AN35) -> 0 | AQ7: 综合费用 | AR7: =AP20 -> 120000
B8: 短贷利息 | D8: =C12*规则表!$B$6 -> 0 | E8: =D12*规则表!$B$6 -> 0 | F8: =E12*规则表!$B$6 -> 0 | G8: 市场开拓 | H8: =SUM(C41:F41) -> 240000 | I8: 折旧前利润 | J8: =J6-J7 -> -3996003 | N8: 短贷利息 | O8: =F12*规则表!$B$6+C13*规则表!$B$7 -> 300000 | P8: =O12*规则表!$B$6+D13*规则表!$B$7 -> 0 | Q8: =P12*规则表!$B$6+E13*规则表!$B$7 -> 0 | R8: =Q12*规则表!$B$6+F13*规则表!$B$7 -> 0 | S8: 市场开拓 | T8: =SUM(O41:R41) -> 0 | U8: 折旧前利润 | V8: =V6-V7 -> 30078000 | Z8: 短贷利息 | AA8: =R12*规则表!$B$6+O13*规则表!$B$7 -> 75855 | AB8: =AA12*规则表!B6+P13*规则表!B7 -> 0 | AC8: =AB12*规则表!B6+Q13*规则表!B7 -> 0 | AD8: =AC12*规则表!B6+R13*规则表!B7 -> 0 | AE8: 市场开拓 | AF8: =SUM(AA41:AD41) -> 0 | AG8: 折旧前利润 | AH8: =AH6-AH7 -> -120000 | AJ8: 短贷利息 | AK8: =AD12*规则表!B6+AA13*规则表!B7 -> 0 | AL8: =AK12*规则表!B6+AB13*规则表!B7 -> 0 | AM8: =AL12*规则表!B6+AC13*规则表!B7 -> 0 | AN8: =AM12*规则表!B6+AD13*规则表!B7 -> 0 | AO8: 市场开拓 | AP8: =SUM(AK41:AN41) -> 0 | AQ8: 折旧前利润 | AR8: =AR6-AR7 -> -120000
B9: 长贷还款 | G9: 产品资质 | H9: =SUM(C40:F40) -> 210000 | I9: 折旧 | J9: =SUM(C4:F4) -> 0 | N9: 长贷还款 | S9: 产品资质 | T9: =SUM(O40:R40) -> 0 | U9: 折旧 | V9: =SUM(O4:R4) -> 0 | Z9: 长贷还款 | AE9: 产品资质 | AF9: =SUM(AA40:AD40) -> 0 | AG9: 折旧 | AH9: =SUM(AA4:AD4) -> 0 | AJ9: 长贷还款 | AO9: 产品资质 | AP9: =SUM(AK40:AN40) -> 0 | AQ9: 折旧 | AR9: =SUM(AK4:AN4) -> 0
B10: 长贷利息 | G10: ISO 认证 | H10: =SUM(C42:F42) -> 240003 | I10: 付息前利润 | J10: =J8-J9 -> -3996003 | N10: 长贷利息 | S10: ISO 认证 | T10: =SUM(O42:R42) -> 0 | U10: 付息前利润 | V10: =V8-V9 -> 30078000 | Z10: 长贷利息 | AE10: ISO 认证 | AF10: =SUM(AA42:AD42) -> 0 | AG10: 付息前利润 | AH10: =AH8-AH9 -> -120000 | AJ10: 长贷利息 | AO10: ISO 认证 | AP10: =SUM(AK42:AN42) -> 0 | AQ10: 付息前利润 | AR10: =AR8-AR9 -> -120000
B11: 贷款额度 | C11: =规则表!$B$2*规则表!$B$3-SUM(C12:C14) -> 0 | D11: =C11+D7+D9-SUM(D12:D14) -> 0 | E11: =D11+E7+E9-SUM(E12:E14) -> 0 | F11: =E11+F7+F9-SUM(F12:F14) -> 0 | G11: 信息费 | H11: =SUM(C20:F20) -> 0 | I11: 财务费用 | J11: =SUM(C8:F8)+SUM(C10:F10)+SUM(C18:F18) -> 0 | N11: 贷款额度 | O11: =J19*规则表!$B$3+O7+O9-SUM(O12:O14)-SUM(C13:F13)-F12-SUM(C14:F14) -> -9746559 | P11: =O11+P7+P9-SUM(P12:P14) -> -9746559 | Q11: =P11+Q7+Q9-SUM(Q12:Q14) -> -9746559 | R11: =Q11+R7+R9-SUM(R12:R14) -> -9746559 | S11: 信息费 | T11: =SUM(O20:R20) -> 0 | U11: 财务费用 | V11: =SUM(O8:R8)+SUM(O10:R10)+SUM(O18:R18) -> 300000 | Z11: 贷款额度 | AA11: =V19*规则表!B3+AA7+AA9-SUM(AA12:AA14)-SUM(O13:R13)-R12-SUM(O14:R14) -> 61009494 | AB11: =AA11+AB7+AB9-SUM(AB12:AB14) -> 61009494 | AC11: =AB11+AC7+AC9-SUM(AC12:AC14) -> 61009494 | AD11: =AC11+AD7+AD9-SUM(AD12:AD14) -> 61009494 | AE11: 信息费 | AF11: =SUM(AA20:AD20) -> 0 | AG11: 财务费用 | AH11: =SUM(AA8:AD8)+SUM(AA10:AD10)+SUM(AA18:AD18) -> 75855 | AJ11: 贷款额度 | AK11: =AH19*规则表!B3+AK7+AK9-SUM(AK12:AK14)-SUM(AA13:AD13)-AD12-SUM(AA14:AD14) -> 60421929 | AL11: =AK11+AL7+AL9-SUM(AL12:AL14) -> 60421929 | AM11: =AL11+AM7+AM9-SUM(AM12:AM14) -> 60421929 | AN11: =AM11+AN7+AN9-SUM(AN12:AN14) -> 60421929 | AO11: 信息费 | AP11: =SUM(AK20:AN20) -> 0 | AQ11: 财务费用 | AR11: =SUM(AK8:AN8)+SUM(AK10:AN10)+SUM(AK18:AN18) -> 0
B12: 1季短贷 | G12: 产品设计 | H12: =SUM(C33:F33) -> 0 | I12: 营业外损失 | K12: 营业外损失用于填写卖原料的成本 | N12: 1季短贷 | S12: 产品设计 | T12: =SUM(O33:R33) -> 0 | U12: 营业外收支 | Z12: 1季短贷 | AE12: 产品设计 | AF12: =SUM(AA33:AD33) -> 0 | AG12: 营业外收支 | AJ12: 1季短贷 | AO12: 产品设计 | AP12: =SUM(AK33:AN33) -> 0 | AQ12: 营业外收支
B13: 4季短贷 | C13: 3000000 | G13: 辞退福利 | H13: =SUM(C28:F28) -> 0 | I13: 税前利润 | J13: =J10-J11-J12 -> -3996003 | N13: 4季短贷 | O13: 758550 | S13: 辞退福利 | T13: =SUM(O28:R28) -> 0 | U13: 税前利润 | V13: =V10-V11-V12 -> 29778000 | Z13: 4季短贷 | AE13: 辞退福利 | AF13: =SUM(AA28:AD28) -> 0 | AG13: 税前利润 | AH13: =AH10-AH11-AH12 -> -195855 | AJ13: 4季短贷 | AO13: 辞退福利 | AP13: =SUM(AK28:AN28) -> 0 | AQ13: 税前利润 | AR13: =AR10-AR11-AR12 -> -120000
B14: 2年长贷 | G14: 培训费 | H14: =SUM(C24:F24) -> 0 | I14: 所得税 | J14: =ROUND(IF(J17>0,IF(J13>0,J13/4,0),IF(J13+J17>0,(J13+J17)/4,0)),0) -> 0 | N14: 2年长贷 | S14: 培训费 | T14: =SUM(O24:R24) -> 0 | U14: 所得税 | V14: =ROUND(IF(V17>0,IF(V13>0,V13/4,0),IF(V13+V17>0,(V13+V17)/4,0)),0) -> 6445499 | Z14: 2年长贷 | AE14: 培训费 | AF14: =SUM(AA24:AD24) -> 0 | AG14: 所得税 | AH14: =ROUND(IF(AH17>0,IF(AH13>0,AH13/4,0),IF(AH13+AH17>0,(AH13+AH17)/4,0)),0) -> 0 | AJ14: 2年长贷 | AO14: 培训费 | AP14: =SUM(AK24:AN24) -> 0 | AQ14: 所得税 | AR14: =ROUND(IF(AR17>0,IF(AR13>0,AR13/4,0),IF(AR13+AR17>0,(AR13+AR17)/4,0)),0) -> 0
B15: 管理费用 | C15: =规则表!$B$4*3 -> 30000 | D15: =规则表!$B$4*3 -> 30000 | E15: =规则表!$B$4*3 -> 30000 | F15: =规则表!$B$4*3 -> 30000 | G15: 激励费 | H15: =SUM(C25:F25) -> 6000 | I15: 净利润 | J15: =J13-J14 -> -3996003 | N15: 管理费用 | O15: =规则表!$B$4*3 -> 30000 | P15: =规则表!$B$4*3 -> 30000 | Q15: =规则表!$B$4*3 -> 30000 | R15: =规则表!$B$4*3 -> 30000 | S15: 激励费 | T15: =SUM(O25:R25) -> 12000 | U15: 净利润 | V15: =V13-V14 -> 23332501 | Z15: 管理费用 | AA15: =规则表!$B$4*3 -> 30000 | AB15: =规则表!$B$4*3 -> 30000 | AC15: =规则表!$B$4*3 -> 30000 | AD15: =规则表!$B$4*3 -> 30000 | AE15: 激励费 | AF15: =SUM(AA25:AD25) -> 0 | AG15: 净利润 | AH15: =AH13-AH14 -> -195855 | AJ15: 管理费用 | AK15: =规则表!$B$4*3 -> 30000 | AL15: =规则表!$B$4*3 -> 30000 | AM15: =规则表!$B$4*3 -> 30000 | AN15: =规则表!$B$4*3 -> 30000 | AO15: 激励费 | AP15: =SUM(AK25:AN25) -> 0 | AQ15: 净利润 | AR15: =AR13-AR14 -> -120000
B16: 应收款到账 | C16: =订单贴现表!C8 -> 0 | D16: =订单贴现表!D8 -> 0 | E16: =订单贴现表!E8 -> 0 | F16: =订单贴现表!F8 -> 0 | G16: 空闲人力费 | H16: =SUM(C27:F27) -> 0 | I16: 股东资本 | J16: =规则表!$B$2 -> 1000000 | N16: 应收款到账 | O16: =订单贴现表!G8 -> 0 | P16: =订单贴现表!H8 -> 0 | Q16: =订单贴现表!I8 -> 0 | R16: =订单贴现表!J8 -> 0 | S16: 空闲人力费 | T16: =SUM(O27:R27) -> 0 | U16: 股东资本 | V16: =规则表!$B$2 -> 1000000 | Z16: 应收款到账 | AA16: =订单贴现表!K8 -> 0 | AB16: =订单贴现表!L8 -> 0 | AC16: =订单贴现表!M8 -> 0 | AD16: =订单贴现表!N8 -> 0 | AE16: 空闲人力费 | AF16: =SUM(AA27:AD27) -> 0 | AG16: 股东资本 | AH16: =规则表!B2 -> 1000000 | AJ16: 应收款到账 | AK16: =订单贴现表!O8 -> 0 | AL16: =订单贴现表!P8 -> 0 | AM16: =订单贴现表!Q8 -> 0 | AN16: =订单贴现表!R8 -> 0 | AO16: 空闲人力费 | AP16: =SUM(AK27:AN27) -> 0 | AQ16: 股东资本 | AR16: =规则表!B2 -> 1000000
B17: 贴现 | E17: {=SUMPRODUCT(材料表!F34:F38,$H$27:$H$31)} -> 0 | F17: {=SUMPRODUCT(材料表!G34:G38,$H$27:$H$31)} -> 0 | G17: 特性研发 | H17: =SUM(C34:F34) -> 0 | I17: 利润留存 | J17: 0 | N17: 贴现 | O17: =材料表!H34*$U$27+材料表!H35*$U$28+材料表!H36*$U$29+材料表!H37*$U$30+材料表!H38*$U$31 -> 18285000 | P17: =材料表!I34*$U$27+材料表!I35*$U$28+材料表!I36*$U$29+材料表!I37*$U$30+材料表!I38*$U$31 -> 0 | Q17: =材料表!J34*$U$27+材料表!J35*$U$28+材料表!J36*$U$29+材料表!J37*$U$30+材料表!J38*$U$31 -> 18285000 | R17: =材料表!K34*$U$27+材料表!K35*$U$28+材料表!K36*$U$29+材料表!K37*$U$30+材料表!K38*$U$31 -> 0 | S17: 特性研发 | T17: =SUM(O34:R34) -> 0 | U17: 利润留存 | V17: =J18 -> -3996003 | Z17: 贴现 | AE17: 特性研发 | AF17: =SUM(AA34:AD34) -> 0 | AG17: 利润留存 | AH17: =V17+V15 -> 19336498 | AJ17: 贴现 | AO17: 特性研发 | AP17: =SUM(AK34:AN34) -> 0 | AQ17: 利润留存 | AR17: =AH17+AH15 -> 19140643
B18: 贴息 | G18: 损失 | H18: =SUM(C3:F3) -> 0 | I18: 年度净利 | J18: =J15 -> -3996003 | N18: 贴息 | S18: 损失 | T18: =SUM(O3:R3)+SUM(O44:R44) -> 0 | U18: 年度净利 | V18: =V15 -> 23332501 | Z18: 贴息 | AE18: 损失 | AF18: =SUM(AA3:AD3) -> 0 | AG18: 年度净利 | AH18: =AH15 -> -195855 | AJ18: 贴息 | AO18: 损失 | AP18: =SUM(AK3:AN3) -> 0 | AQ18: 年度净利 | AR18: =AR15 -> -120000
B19: 应付款 | G19: 违约金 | H19: =SUM(C44:F44) -> 0 | I19: 权益合计 | J19: =SUM(J16:J18) -> -2996003 | N19: 应付款 | S19: 违约金 | T19: =SUM(O44:R44) -> 0 | U19: 权益合计 | V19: =SUM(V16:V18) -> 20336498 | Z19: 应付款 | AE19: 违约金 | AF19: =SUM(AA44:AD44) -> 0 | AG19: 权益合计 | AH19: =SUM(AH16:AH18) -> 20140643 | AJ19: 应付款 | AO19: 违约金 | AP19: =SUM(AK44:AN44) -> 0 | AQ19: 权益合计 | AR19: =SUM(AR16:AR18) -> 20020643
B20: 信息费 | G20: 合计 | H20: =SUM(H4:H19) -> 816003 | N20: g | S20: 合计 | T20: =SUM(T4:T18) -> 132000 | Z20: 信息费 | AE20: 合计 | AF20: =SUM(AF4:AF19) -> 120000 | AJ20: 信息费 | AO20: 合计 | AP20: =SUM(AP4:AP19) -> 120000
B21: 碳中和 | I21: 资金余额 | J21: =O2 -> -1086003 | N21: 碳中和 | Z21: 碳中和 | AJ21: 碳中和
B22: 拆线收入 | C22: {=SUMPRODUCT(生产建设!I64:I66,规则表!$H$17:$H$19)} -> 0 | D22: {=SUMPRODUCT(生产建设!J64:J66,规则表!$H$17:$H$19)} -> 0 | E22: {=SUMPRODUCT(生产建设!K64:K66,规则表!$H$17:$H$19)} -> 0 | F22: {=SUMPRODUCT(生产建设!L64:L66,规则表!$H$17:$H$19)} -> 0 | N22: 拆线收入 | O22: {=SUMPRODUCT(生产建设!M64:M66,规则表!$H$17:$H$19)} -> 0 | P22: {=SUMPRODUCT(生产建设!N64:N66,规则表!$H$17:$H$19)} -> 0 | Q22: {=SUMPRODUCT(生产建设!O64:O66,规则表!$H$17:$H$19)} -> 0 | R22: {=SUMPRODUCT(生产建设!P64:P66,规则表!$H$17:$H$19)} -> 0 | Z22: 拆线收入 | AA22: {=SUMPRODUCT(生产建设!Q64:Q66,规则表!$H$17:$H$19)} -> 0 | AB22: {=SUMPRODUCT(生产建设!R64:R66,规则表!$H$17:$H$19)} -> 0 | AC22: {=SUMPRODUCT(生产建设!S64:S66,规则表!$H$17:$H$19)} -> 0 | AD22: {=SUMPRODUCT(生产建设!T64:T66,规则表!$H$17:$H$19)} -> 0 | AJ22: 拆线费用 | AK22: {=SUMPRODUCT(生产建设!U64:U66,规则表!$H$17:$H$19)} -> 0 | AL22: {=SUMPRODUCT(生产建设!V64:V66,规则表!$H$17:$H$19)} -> 0 | AM22: {=SUMPRODUCT(生产建设!W64:W66,规则表!$H$17:$H$19)} -> 0 | AN22: {=SUMPRODUCT(生产建设!X64:X66,规则表!$H$17:$H$19)} -> 0
B23: 人力总监 | N23: 人力总监 | Z23: 人力总监 | AJ23: 人力总监
B24: 工人培训 | N24: 工人培训 | Z24: 工人培训 | AJ24: 工人培训
B25: 工人激励 | D25: =生产建设!J58 -> 0 | E25: =生产建设!K58 -> 6000 | F25: =生产建设!L58 -> 0 | G25: 产品 | H25: 1.2 | K25: 1.3 | N25: 工人激励 | O25: =生产建设!M58 -> 6000 | P25: =生产建设!N58 -> 0 | Q25: =生产建设!O58 -> 6000 | R25: =生产建设!P58 -> 0 | S25: 产品 | T25: 2.1 | Z25: 工人激励 | AA25: =生产建设!Q58 -> 0 | AB25: =生产建设!R58 -> 0 | AC25: =生产建设!S58 -> 0 | AD25: =生产建设!T58 -> 0 | AJ25: 工人激励 | AK25: =生产建设!U58 -> 0 | AL25: =生产建设!V58 -> 0 | AM25: =生产建设!W58 -> 0 | AN25: =生产建设!X58 -> 0
B26: 工人工资 | C26: =生产建设!I54 -> 0 | D26: =生产建设!J54 -> 90000 | E26: =生产建设!K54 -> 90000 | F26: =生产建设!L54 -> 90000 | H26: 最低价 | I26: 均价 | J26: 最高价 | K26: 最低价 | L26: 均价 | M26: 最高价 | N26: 工人工资 | O26: =生产建设!M54 -> 90000 | P26: =生产建设!N54 -> 90000 | Q26: =生产建设!O54 -> 90000 | R26: =生产建设!P54 -> 90000 | T26: 最低价 | U26: 均价 | V26: 最高价 | Z26: 工人工资 | AA26: =生产建设!Q54 -> 90000 | AB26: =生产建设!R54 -> 90000 | AC26: =生产建设!S54 -> 90000 | AD26: =生产建设!T54 -> 90000 | AJ26: 工人工资 | AK26: =生产建设!U54 -> 90000 | AL26: =生产建设!V54 -> 90000 | AM26: =生产建设!W54 -> 90000 | AN26: =生产建设!X54 -> 90000
B27: 空闲人力费 | G27: =H54 -> P1 | H27: {=INT(MIN(_xlfn._xlws.FILTER(原始订单表!$M:$M,(原始订单表!$A:$A=1)*(原始订单表!$B:$B=2)*(原始订单表!$E:$E=G27),0)))} -> 4800 | I27: {=INT(AVERAGE(_xlfn._xlws.FILTER(原始订单表!$M:$M,(原始订单表!$A:$A=1)*(原始订单表!$B:$B=2)*(原始订单表!$E:$E=G27),0)))} -> 4848 | J27: {=INT(MAX(_xlfn._xlws.FILTER(原始订单表!$M:$M,(原始订单表!$A:$A=1)*(原始订单表!$B:$B=2)*(原始订单表!$E:$E=G27),0)))} -> 4896 | K27: {=INT(MIN(_xlfn._xlws.FILTER(原始订单表!$M:$M,(原始订单表!$A:$A=1)*(原始订单表!$B:$B=3)*(原始订单表!$E:$E=G27),0)))} -> 4032 | L27: {=INT(AVERAGE(_xlfn._xlws.FILTER(原始订单表!$M:$M,(原始订单表!$A:$A=1)*(原始订单表!$B:$B=3)*(原始订单表!$E:$E=G27),0)))} -> 4080 | M27: {=INT(MAX(_xlfn._xlws.FILTER(原始订单表!$M:$M,(原始订单表!$A:$A=1)*(原始订单表!$B:$B=3)*(原始订单表!$E:$E=G27),0)))} -> 4128 | N27: 空闲人力费 | S27: =G27 -> P1 | T27: {=INT(MIN(_xlfn._xlws.FILTER(原始订单表!$M:$M,(原始订单表!$A:$A=2)*(原始订单表!$B:$B=1)*(原始订单表!$E:$E=S27),0)))} -> 4416 | U27: {=INT(AVERAGE(_xlfn._xlws.FILTER(原始订单表!$M:$M,(原始订单表!$A:$A=2)*(原始订单表!$B:$B=1)*(原始订单表!$E:$E=S27),0)))} -> 4909 | V27: {=INT(MAX(_xlfn._xlws.FILTER(原始订单表!$M:$M,(原始订单表!$A:$A=2)*(原始订单表!$B:$B=1)*(原始订单表!$E:$E=S27),0)))} -> 5624 | W27: 2.2 | Z27: 空闲人力费 | AJ27: 空闲人力费
B28: 辞退福利 | G28: =H55 -> P2 | H28: {=INT(MIN(_xlfn._xlws.FILTER(原始订单表!$M:$M,(原始订单表!$A:$A=1)*(原始订单表!$B:$B=2)*(原始订单表!$E:$E=G28),0)))} -> 7938 | I28: {=INT(AVERAGE(_xlfn._xlws.FILTER(原始订单表!$M:$M,(原始订单表!$A:$A=1)*(原始订单表!$B:$B=2)*(原始订单表!$E:$E=G28),0)))} -> 7953 | J28: {=INT(MAX(_xlfn._xlws.FILTER(原始订单表!$M:$M,(原始订单表!$A:$A=1)*(原始订单表!$B:$B=2)*(原始订单表!$E:$E=G28),0)))} -> 7968 | K28: {=INT(MIN(_xlfn._xlws.FILTER(原始订单表!$M:$M,(原始订单表!$A:$A=1)*(原始订单表!$B:$B=3)*(原始订单表!$E:$E=G28),0)))} -> 7200 | L28: {=INT(AVERAGE(_xlfn._xlws.FILTER(原始订单表!$M:$M,(原始订单表!$A:$A=1)*(原始订单表!$B:$B=3)*(原始订单表!$E:$E=G28),0)))} -> 7348 | M28: {=INT(MAX(_xlfn._xlws.FILTER(原始订单表!$M:$M,(原始订单表!$A:$A=1)*(原始订单表!$B:$B=3)*(原始订单表!$E:$E=G28),0)))} -> 7497 | N28: 辞退福利 | S28: =G28 -> P2 | T28: {=INT(MIN(_xlfn._xlws.FILTER(原始订单表!$M:$M,(原始订单表!$A:$A=2)*(原始订单表!$B:$B=1)*(原始订单表!$E:$E=S28),0)))} -> 6816 | U28: {=INT(AVERAGE(_xlfn._xlws.FILTER(原始订单表!M:M,(原始订单表!A:A=2)*(原始订单表!B:B=1)*(原始订单表!E:E=S28),0)))} -> 7622 | V28: {=INT(MAX(_xlfn._xlws.FILTER(原始订单表!$M:$M,(原始订单表!$A:$A=2)*(原始订单表!$B:$B=1)*(原始订单表!$E:$E=S28),0)))} -> 8640 | W28: 最低价 | X28: 均价 | Y28: 最高价 | Z28: 辞退福利 | AJ28: 辞退福利
B29: 预算 | C29: =SUM(C24:C28) -> 0 | D29: =SUM(D24:D28) -> 90000 | E29: =SUM(E24:E28) -> 96000 | F29: =SUM(F24:F28) -> 90000 | G29: =H56 -> P3 | H29: {=INT(MIN(_xlfn._xlws.FILTER(原始订单表!$M:$M,(原始订单表!$A:$A=1)*(原始订单表!$B:$B=2)*(原始订单表!$E:$E=G29),0)))} -> 0 | I29: {=INT(AVERAGE(_xlfn._xlws.FILTER(原始订单表!$M:$M,(原始订单表!$A:$A=1)*(原始订单表!$B:$B=2)*(原始订单表!$E:$E=G29),0)))} -> 0 | J29: {=INT(MAX(_xlfn._xlws.FILTER(原始订单表!$M:$M,(原始订单表!$A:$A=1)*(原始订单表!$B:$B=2)*(原始订单表!$E:$E=G29),0)))} -> 0 | K29: {=INT(MIN(_xlfn._xlws.FILTER(原始订单表!$M:$M,(原始订单表!$A:$A=1)*(原始订单表!$B:$B=3)*(原始订单表!$E:$E=G29),0)))} -> 0 | L29: {=INT(AVERAGE(_xlfn._xlws.FILTER(原始订单表!$M:$M,(原始订单表!$A:$A=1)*(原始订单表!$B:$B=3)*(原始订单表!$E:$E=G29),0)))} -> 0 | M29: {=INT(MAX(_xlfn._xlws.FILTER(原始订单表!$M:$M,(原始订单表!$A:$A=1)*(原始订单表!$B:$B=3)*(原始订单表!$E:$E=G29),0)))} -> 0 | N29: 预算 | O29: =SUM(O24:O28) -> 96000 | P29: =SUM(P24:P28) -> 90000 | Q29: =SUM(Q24:Q28) -> 96000 | R29: =SUM(R24:R28) -> 90000 | S29: =G29 -> P3 | T29: {=INT(MIN(_xlfn._xlws.FILTER(原始订单表!$M:$M,(原始订单表!$A:$A=2)*(原始订单表!$B:$B=1)*(原始订单表!$E:$E=S29),0)))} -> 9792 | U29: {=INT(AVERAGE(_xlfn._xlws.FILTER(原始订单表!$M:$M,(原始订单表!$A:$A=2)*(原始订单表!$B:$B=1)*(原始订单表!$E:$E=S29),0)))} -> 10880 | V29: {=INT(MAX(_xlfn._xlws.FILTER(原始订单表!$M:$M,(原始订单表!$A:$A=2)*(原始订单表!$B:$B=1)*(原始订单表!$E:$E=S29),0)))} -> 12070 | W29: {=INT(MIN(_xlfn._xlws.FILTER(原始订单表!$M:$M,(原始订单表!$A:$A=2)*(原始订单表!$B:$B=2)*(原始订单表!$E:$E=S27),0)))} -> 0 | X29: {=INT(AVERAGE(_xlfn._xlws.FILTER(原始订单表!$M:$M,(原始订单表!$A:$A=2)*(原始订单表!$B:$B=2)*(原始订单表!$E:$E=S27),0)))} -> 0 | Y29: {=INT(MAX(_xlfn._xlws.FILTER(原始订单表!$M:$M,(原始订单表!$A:$A=2)*(原始订单表!$B:$B=2)*(原始订单表!$E:$E=S27),0)))} -> 0 | Z29: 预算 | AA29: =SUM(AA24:AA28) -> 90000 | AB29: =SUM(AB24:AB28) -> 90000 | AC29: =SUM(AC24:AC28) -> 90000 | AD29: =SUM(AD24:AD28) -> 90000 | AJ29: 预算 | AK29: =SUM(AK24:AK28) -> 90000 | AL29: =SUM(AL24:AL28) -> 90000 | AM29: =SUM(AM24:AM28) -> 90000 | AN29: =SUM(AN24:AN28) -> 90000
B30: 生产总监 | G30: =H57 -> P4 | H30: {=INT(MIN(_xlfn._xlws.FILTER(原始订单表!$M:$M,(原始订单表!$A:$A=1)*(原始订单表!$B:$B=2)*(原始订单表!$E:$E=G30),0)))} -> 0 | I30: {=INT(AVERAGE(_xlfn._xlws.FILTER(原始订单表!$M:$M,(原始订单表!$A:$A=1)*(原始订单表!$B:$B=2)*(原始订单表!$E:$E=G30),0)))} -> 0 | J30: {=INT(MAX(_xlfn._xlws.FILTER(原始订单表!$M:$M,(原始订单表!$A:$A=1)*(原始订单表!$B:$B=2)*(原始订单表!$E:$E=G30),0)))} -> 0 | K30: {=INT(MIN(_xlfn._xlws.FILTER(原始订单表!$M:$M,(原始订单表!$A:$A=1)*(原始订单表!$B:$B=3)*(原始订单表!$E:$E=G30),0)))} -> 0 | L30: {=INT(AVERAGE(_xlfn._xlws.FILTER(原始订单表!$M:$M,(原始订单表!$A:$A=1)*(原始订单表!$B:$B=3)*(原始订单表!$E:$E=G30),0)))} -> 0 | M30: {=INT(MAX(_xlfn._xlws.FILTER(原始订单表!$M:$M,(原始订单表!$A:$A=1)*(原始订单表!$B:$B=3)*(原始订单表!$E:$E=G30),0)))} -> 0 | N30: 生产总监 | S30: =G30 -> P4 | T30: {=INT(MIN(_xlfn._xlws.FILTER(原始订单表!$M:$M,(原始订单表!$A:$A=2)*(原始订单表!$B:$B=1)*(原始订单表!$E:$E=S30),0)))} -> 13780 | U30: {=INT(AVERAGE(_xlfn._xlws.FILTER(原始订单表!$M:$M,(原始订单表!$A:$A=2)*(原始订单表!$B:$B=1)*(原始订单表!$E:$E=S30),0)))} -> 14628 | V30: {=INT(MAX(_xlfn._xlws.FILTER(原始订单表!$M:$M,(原始订单表!$A:$A=2)*(原始订单表!$B:$B=1)*(原始订单表!$E:$E=S30),0)))} -> 15019 | W30: {=INT(MIN(_xlfn._xlws.FILTER(原始订单表!$M:$M,(原始订单表!$A:$A=2)*(原始订单表!$B:$B=2)*(原始订单表!$E:$E=S28),0)))} -> 6818 | X30: {=INT(AVERAGE(_xlfn._xlws.FILTER(原始订单表!$M:$M,(原始订单表!$A:$A=2)*(原始订单表!$B:$B=2)*(原始订单表!$E:$E=S28),0)))} -> 6818 | Y30: {=INT(MAX(_xlfn._xlws.FILTER(原始订单表!$M:$M,(原始订单表!$A:$A=2)*(原始订单表!$B:$B=2)*(原始订单表!$E:$E=S28),0)))} -> 6818 | Z30: 生产总监 | AJ30: 生产总监
B31: 原料成本 | C31: =材料表!D25 -> 0 | D31: =材料表!E25 -> 0 | E31: =材料表!F25 -> 2875000 | F31: =材料表!G25 -> 0 | G31: =H58 -> 0 | H31: {=INT(MIN(_xlfn._xlws.FILTER(原始订单表!$M:$M,(原始订单表!$A:$A=1)*(原始订单表!$B:$B=2)*(原始订单表!$E:$E=G31),0)))} -> 4608 | I31: {=INT(AVERAGE(_xlfn._xlws.FILTER(原始订单表!$M:$M,(原始订单表!$A:$A=1)*(原始订单表!$B:$B=2)*(原始订单表!$E:$E=G31),0)))} -> 4608 | J31: {=INT(MAX(_xlfn._xlws.FILTER(原始订单表!$M:$M,(原始订单表!$A:$A=1)*(原始订单表!$B:$B=2)*(原始订单表!$E:$E=G31),0)))} -> 4608 | K31: {=INT(MIN(_xlfn._xlws.FILTER(原始订单表!$M:$M,(原始订单表!$A:$A=1)*(原始订单表!$B:$B=3)*(原始订单表!$E:$E=G31),0)))} -> 0 | L31: {=INT(AVERAGE(_xlfn._xlws.FILTER(原始订单表!$M:$M,(原始订单表!$A:$A=1)*(原始订单表!$B:$B=3)*(原始订单表!$E:$E=G31),0)))} -> 0 | M31: {=INT(MAX(_xlfn._xlws.FILTER(原始订单表!$M:$M,(原始订单表!$A:$A=1)*(原始订单表!$B:$B=3)*(原始订单表!$E:$E=G31),0)))} -> 0 | N31: 原料成本 | O31: =材料表!H25 -> 2875000 | P31: =材料表!I25 -> 0 | Q31: =材料表!J25 -> 2875000 | R31: =材料表!K25 -> 0 | S31: =G31 -> 0 | T31: {=INT(MIN(_xlfn._xlws.FILTER(原始订单表!$M:$M,(原始订单表!$A:$A=2)*(原始订单表!$B:$B=1)*(原始订单表!$E:$E=S31),0)))} -> 0 | U31: {=INT(AVERAGE(_xlfn._xlws.FILTER(原始订单表!$M:$M,(原始订单表!$A:$A=2)*(原始订单表!$B:$B=1)*(原始订单表!$E:$E=S31),0)))} -> 0 | V31: {=INT(MAX(_xlfn._xlws.FILTER(原始订单表!$M:$M,(原始订单表!$A:$A=2)*(原始订单表!$B:$B=1)*(原始订单表!$E:$E=S31),0)))} -> 0 | W31: {=INT(MIN(_xlfn._xlws.FILTER(原始订单表!$M:$M,(原始订单表!$A:$A=2)*(原始订单表!$B:$B=2)*(原始订单表!$E:$E=S29),0)))} -> 9257 | X31: {=INT(AVERAGE(_xlfn._xlws.FILTER(原始订单表!$M:$M,(原始订单表!$A:$A=2)*(原始订单表!$B:$B=2)*(原始订单表!$E:$E=S29),0)))} -> 9450 | Y31: {=INT(MAX(_xlfn._xlws.FILTER(原始订单表!$M:$M,(原始订单表!$A:$A=2)*(原始订单表!$B:$B=2)*(原始订单表!$E:$E=S29),0)))} -> 9644 | Z31: 原料成本 | AA31: =材料表!L25 -> 0 | AB31: =材料表!M25 -> 0 | AC31: =材料表!N25 -> 0 | AD31: =材料表!O25 -> 0 | AJ31: 原料成本 | AK31: =材料表!P25 -> 0 | AL31: =材料表!Q25 -> 0 | AM31: =材料表!R25 -> 0 | AN31: =材料表!S25 -> 0
B32: 机器设备 | C32: =生产建设!I51 -> 1000000 | D32: =生产建设!J51 -> 0 | E32: =生产建设!K51 -> 0 | F32: =生产建设!L51 -> 0 | N32: 机器设备 | O32: =生产建设!M51 -> 0 | P32: =生产建设!N51 -> 0 | Q32: =生产建设!O51 -> 0 | R32: =生产建设!P51 -> 0 | W32: {=INT(MIN(_xlfn._xlws.FILTER(原始订单表!$M:$M,(原始订单表!$A:$A=2)*(原始订单表!$B:$B=2)*(原始订单表!$E:$E=S30),0)))} -> 12740 | X32: {=INT(AVERAGE(_xlfn._xlws.FILTER(原始订单表!$M:$M,(原始订单表!$A:$A=2)*(原始订单表!$B:$B=2)*(原始订单表!$E:$E=S30),0)))} -> 12901 | Y32: {=INT(MAX(_xlfn._xlws.FILTER(原始订单表!$M:$M,(原始订单表!$A:$A=2)*(原始订单表!$B:$B=2)*(原始订单表!$E:$E=S30),0)))} -> 13063 | Z32: 机器设备 | AA32: =生产建设!Q51 -> 0 | AB32: =生产建设!R51 -> 0 | AC32: =生产建设!S51 -> 0 | AD32: =生产建设!T51 -> 0 | AJ32: 机器设备 | AK32: =生产建设!U52 -> 0 | AL32: =生产建设!V52 -> 0 | AM32: =生产建设!W52 -> 0 | AN32: =生产建设!X52 -> 0
B33: 产品设计 | N33: 产品设计 | W33: {=INT(MIN(_xlfn._xlws.FILTER(原始订单表!$M:$M,(原始订单表!$A:$A=2)*(原始订单表!$B:$B=2)*(原始订单表!$E:$E=S31),0)))} -> 0 | X33: {=INT(AVERAGE(_xlfn._xlws.FILTER(原始订单表!$M:$M,(原始订单表!$A:$A=2)*(原始订单表!$B:$B=2)*(原始订单表!$E:$E=S31),0)))} -> 0 | Y33: {=INT(MAX(_xlfn._xlws.FILTER(原始订单表!$M:$M,(原始订单表!$A:$A=2)*(原始订单表!$B:$B=2)*(原始订单表!$E:$E=S31),0)))} -> 0 | Z33: 产品设计 | AJ33: 产品设计
B34: 特性研发 | N34: 特性研发 | Z34: 特性研发 | AJ34: 特性研发
B35: 转产 | C35: =生产建设!I56 -> 0 | D35: =生产建设!J56 -> 0 | E35: =生产建设!K56 -> 0 | F35: =生产建设!L56 -> 0 | H35: （计算的是成本） | I35: =规则表!B35 -> 传统线 | J35: =规则表!C35 -> 自动线 | K35: =规则表!D35 -> 智能线 | N35: 转产 | O35: =生产建设!M56 -> 0 | P35: =生产建设!N56 -> 0 | Q35: =生产建设!O56 -> 0 | R35: =生产建设!P56 -> 0 | Z35: 转产 | AA35: =生产建设!Q56 -> 0 | AB35: =生产建设!R56 -> 0 | AC35: =生产建设!S56 -> 0 | AD35: =生产建设!T56 -> 0 | AJ35: 转产 | AK35: =生产建设!U56 -> 0 | AL35: =生产建设!V56 -> 0 | AM35: =生产建设!W56 -> 0 | AN35: =生产建设!X56 -> 0
B36: 生产费用 | D36: =材料表!E26 -> 0 | E36: =材料表!F26 -> 125000 | F36: =材料表!G26 -> 0 | H36: =规则表!A36 -> P1 | I36: =规则表!B36 -> 748.8 | J36: =规则表!C36 -> 676.28205 | K36: =规则表!D36 -> 770.36082 | N36: 生产费用 | O36: =材料表!H26 -> 125000 | P36: =材料表!I26 -> 0 | Q36: =材料表!J26 -> 125000 | R36: =材料表!K26 -> 0 | Z36: 生产费用 | AA36: =材料表!L26 -> 0 | AB36: =材料表!M26 -> 0 | AC36: =材料表!N26 -> 0 | AD36: =材料表!O26 -> 0 | AJ36: 生产费用 | AK36: =材料表!P26 -> 0 | AL36: =材料表!Q26 -> 0 | AM36: =材料表!R26 -> 0 | AN36: =材料表!S26 -> 0
B37: 维护费 | H37: =规则表!A37 -> P2 | I37: =规则表!B37 -> 1148.8 | J37: =规则表!C37 -> 1076.2821 | K37: =规则表!D37 -> 1170.3608 | N37: 维护费 | O37: =生产建设!M52 -> 0 | P37: =生产建设!N52 -> 0 | Q37: =生产建设!O52 -> 0 | R37: =生产建设!P52 -> 0 | T37: （计算的是成本） | U37: =U17 -> 利润留存 | V37: =U18 -> 年度净利 | W37: =U19 -> 权益合计 | Z37: 维护费 | AJ37: 维护费
B38: 预算 | C38: =SUM(C31:C36) -> 1000000 | D38: =SUM(D31:D36) -> 0 | E38: =SUM(E31:E36) -> 3000000 | F38: =SUM(F31:F36) -> 0 | H38: =规则表!A38 -> P3 | I38: =规则表!B38 -> 1748.8 | J38: =规则表!C38 -> 1676.2821 | K38: =规则表!D38 -> 1770.3608 | N38: 预算 | O38: =SUM(O31:O36) -> 3000000 | P38: =SUM(P31:P36) -> 0 | Q38: =SUM(Q31:Q36) -> 3000000 | R38: =SUM(R31:R36) -> 0 | T38: =H36 -> P1 | U38: =I36 -> 748.8 | V38: =J36 -> 676.28205 | W38: =K36 -> 770.36082 | Z38: 预算 | AA38: =SUM(AA31:AA36) -> 0 | AB38: =SUM(AB31:AB36) -> 0 | AC38: =SUM(AC31:AC36) -> 0 | AD38: =SUM(AD31:AD36) -> 0 | AJ38: 预算 | AK38: =SUM(AK31:AK36) -> 0 | AL38: =SUM(AL31:AL36) -> 0 | AM38: =SUM(AM31:AM36) -> 0 | AN38: =SUM(AN31:AN36) -> 0
B39: 营销总监 | H39: =规则表!A39 -> P4 | I39: =规则表!B39 -> 2548.8 | J39: =规则表!C39 -> 2476.2821 | K39: =规则表!D39 -> 2570.3608 | N39: 营销总监 | T39: =H37 -> P2 | U39: =I37 -> 1148.8 | V39: =J37 -> 1076.2821 | W39: =K37 -> 1170.3608 | Z39: 营销总监 | AJ39: 营销总监
B40: 产品资质 | C40: {=SUM(IF($K$54:$K$58<=1,$I$54:$I$58,0))} -> 210000 | D40: {=SUM(IF($K$54:$K$58=2,$I$54:$I$58,0))} -> 0 | E40: {=SUM(IF($K$54:$K$58=3,$I$54:$I$58,0))} -> 0 | F40: {=SUM(IF($K$54:$K$58=4,$I$54:$I$58,0))} -> 0 | H40: =规则表!A40 -> 0 | I40: =规则表!B40 -> 248.8 | J40: =规则表!C40 -> 176.28205 | K40: =规则表!D40 -> 270.36082 | N40: 产品资质 | O40: {=SUM(IF($K$54:$K$58=5,$I$54:$I$58,0))} -> 0 | P40: {=SUM(IF($K$54:$K$58=6,$I$54:$I$58,0))} -> 0 | Q40: {=SUM(IF($K$54:$K$58=7,$I$54:$I$58,0))} -> 0 | R40: {=SUM(IF($K$54:$K$58=8,$I$54:$I$58,0))} -> 0 | T40: =H38 -> P3 | U40: =I38 -> 1748.8 | V40: =J38 -> 1676.2821 | W40: =K38 -> 1770.3608 | Z40: 产品资质 | AA40: {=SUM(IF($K$54:$K$58=9,$I$54:$I$58,0))} -> 0 | AB40: {=SUM(IF($K$54:$K$58=10,$I$54:$I$58,0))} -> 0 | AC40: {=SUM(IF($K$54:$K$58=11,$I$54:$I$58,0))} -> 0 | AD40: {=SUM(IF($K$54:$K$58=12,$I$54:$I$58,0))} -> 0 | AJ40: 产品资质 | AK40: {=SUM(IF($K$54:$K$58=13,$I$54:$I$58,0))} -> 0 | AL40: {=SUM(IF($K$54:$K$58=14,$I$54:$I$58,0))} -> 0 | AM40: {=SUM(IF($K$54:$K$58=15,$I$54:$I$58,0))} -> 0 | AN40: {=SUM(IF($K$54:$K$58=16,$I$54:$I$58,0))} -> 0
B41: 市场开拓 | C41: {=SUM(IF($K$61:$K$65<=1,$I$61:$I$65,0))} -> 140000 | D41: {=SUM(IF($K$61:$K$65=2,$I$61:$I$65,0))} -> 100000 | E41: {=SUM(IF($K$61:$K$65=3,$I$61:$I$65,0))} -> 0 | F41: {=SUM(IF($K$61:$K$65=4,$I$61:$I$65,0))} -> 0 | N41: 市场开拓 | O41: {=SUM(IF($K$61:$K$65=5,$I$61:$I$65,0))} -> 0 | P41: {=SUM(IF($K$61:$K$65=6,$I$61:$I$65,0))} -> 0 | Q41: {=SUM(IF($K$61:$K$65=7,$I$61:$I$65,0))} -> 0 | R41: {=SUM(IF($K$61:$K$65=8,$I$61:$I$65,0))} -> 0 | T41: =H39 -> P4 | U41: =I39 -> 2548.8 | V41: =J39 -> 2476.2821 | W41: =K39 -> 2570.3608 | Z41: 市场开拓 | AA41: {=SUM(IF($K$54:$K$58=9,$I$54:$I$58,0))} -> 0 | AB41: {=SUM(IF($K$54:$K$58=10,$I$54:$I$58,0))} -> 0 | AC41: {=SUM(IF($K$54:$K$58=11,$I$54:$I$58,0))} -> 0 | AD41: {=SUM(IF($K$54:$K$58=12,$I$54:$I$58,0))} -> 0 | AJ41: 市场开拓 | AK41: {=SUM(IF($K$54:$K$58=13,$I$54:$I$58,0))} -> 0 | AL41: {=SUM(IF($K$54:$K$58=14,$I$54:$I$58,0))} -> 0 | AM41: {=SUM(IF($K$54:$K$58=15,$I$54:$I$58,0))} -> 0 | AN41: {=SUM(IF($K$54:$K$58=16,$I$54:$I$58,0))} -> 0
B42: ISO认证 | C42: {=SUM(IF($K$68:$K$72<=1,$I$68:$I$72,0))} -> 240003 | D42: {=SUM(IF($K$68:$K$72=2,$I$68:$I$72,0))} -> 0 | E42: {=SUM(IF($K$68:$K$72=3,$I$68:$I$72,0))} -> 0 | F42: {=SUM(IF($K$68:$K$72=4,$I$68:$I$72,0))} -> 0 | H42: =规则表!A43 -> 12小时 | I42: =规则表!B43 -> 传统线 | J42: =规则表!C43 -> 自动线 | K42: =规则表!D43 -> 智能线 | N42: ISO认证 | O42: {=SUM(IF($K$68:$K$72=5,$I$68:$I$72,0))} -> 0 | P42: {=SUM(IF($K$68:$K$72=6,$I$68:$I$72,0))} -> 0 | Q42: {=SUM(IF($K$68:$K$72=7,$I$68:$I$72,0))} -> 0 | R42: {=SUM(IF($K$68:$K$72=8,$I$68:$I$72,0))} -> 0 | T42: =H40 -> 0 | U42: =I40 -> 248.8 | V42: =J40 -> 176.28205 | W42: =K40 -> 270.36082 | Z42: ISO认证 | AA42: {=SUM(IF($K$68:$K$72=9,$I$68:$I$72,0))} -> 0 | AB42: {=SUM(IF($K$68:$K$72=10,$I$68:$I$72,0))} -> 0 | AC42: {=SUM(IF($K$68:$K$72=11,$I$68:$I$72,0))} -> 0 | AD42: {=SUM(IF($K$68:$K$72=12,$I$68:$I$72,0))} -> 0 | AJ42: ISO认证 | AK42: {=SUM(IF($K$68:$K$72=13,$I$68:$I$72,0))} -> 0 | AL42: {=SUM(IF($K$68:$K$72=14,$I$68:$I$72,0))} -> 0 | AM42: {=SUM(IF($K$68:$K$72=15,$I$68:$I$72,0))} -> 0 | AN42: {=SUM(IF($K$68:$K$72=16,$I$68:$I$72,0))} -> 0
B43: 广告投放 | H43: =规则表!A44 -> P1 | I43: =规则表!B44 -> 743.33333 | J43: =规则表!C44 -> 748.40426 | K43: =规则表!D44 -> 847.22222 | N43: 广告投放 | Z43: 广告投放 | AJ43: 广告投放
B44: 违约金 | H44: =规则表!A45 -> P2 | I44: =规则表!B45 -> 1143.3333 | J44: =规则表!C45 -> 1148.4043 | K44: =规则表!D45 -> 1247.2222 | N44: 违约金 | Z44: 违约金 | AJ44: 违约金
B45: 预算 | C45: =SUM(C40:C43) -> 590003 | D45: =SUM(D40:D43) -> 100000 | E45: =SUM(E40:E43) -> 0 | F45: =SUM(F40:F43) -> 0 | H45: =规则表!A46 -> P3 | I45: =规则表!B46 -> 1743.3333 | J45: =规则表!C46 -> 1748.4043 | K45: =规则表!D46 -> 1847.2222 | N45: 预算 | O45: =SUM(O40:O43) -> 0 | P45: =SUM(P40:P43) -> 0 | Q45: =SUM(Q40:Q43) -> 0 | R45: =SUM(R40:R43) -> 0 | Z45: 预算 | AA45: =SUM(AA40:AA43) -> 0 | AB45: =SUM(AB40:AB43) -> 0 | AC45: =SUM(AC40:AC43) -> 0 | AD45: =SUM(AD40:AD43) -> 0 | AJ45: 预算 | AK45: =SUM(AK40:AK43) -> 0 | AL45: =SUM(AL40:AL43) -> 0 | AM45: =SUM(AM40:AM43) -> 0 | AN45: =SUM(AN40:AN43) -> 0
B46: 现金盘点 | C46: =C5-C7-C8-C9-C10+C12+C13+C14-C15+C16+C17-C18-C19-C20-C29-C38-C45-C44-C37-C21+C22 -> 2379997 | D46: =D5-D7-D8-D9-D10+D12+D13+D14-D15+D16+D17-D18-D19-D20-D29-D38-D45-D44-D37-D21+D22 -> 2159997 | E46: =E5-E7-E8-E9-E10+E12+E13+E14-E15+E16+E17-E18-E19-E20-E29-E38-E45-E44-E37-E21+E22 -> -966003 | F46: =F5-F7-F8-F9-F10+F12+F13+F14-F15+F16+F17-F18-F19-F20-F29-F38-F45-F44-F37-F21+F22 -> -1086003 | H46: =规则表!A47 -> P4 | I46: =规则表!B47 -> 2543.3333 | J46: =规则表!C47 -> 2548.4043 | K46: =规则表!D47 -> 2647.2222 | N46: 现金盘点 | O46: =O5-O7-O8-O9-O10+O12+O13+O14-O15+O16+O17-O18-O19-O20-O29-O38-O45-O44-O37+O22-O21 -> 11531547 | P46: =P5-P7-P8-P9-P10+P12+P13+P14-P15+P16+P17-P18-P19-P20-P29-P38-P45-P44-P37+P22-P21 -> 11411547 | Q46: =Q5-Q7-Q8-Q9-Q10+Q12+Q13+Q14-Q15+Q16+Q17-Q18-Q19-Q20-Q29-Q38-Q45-Q44-Q37+Q22-Q21 -> 26570547 | R46: =R5-R7-R8-R9-R10+R12+R13+R14-R15+R16+R17-R18-R19-R20-R29-R38-R45-R44-R37+R22-R21 -> 26450547 | Z46: 现金盘点 | AA46: =AA5-AA7-AA8-AA9-AA10+AA12+AA13+AA14-AA15+AA16+AA17-AA18-AA19-AA20-AA29-AA38-AA45-AA44-AA37+AA22-AA21 -> 19050643 | AB46: =AB5-AB7-AB8-AB9-AB10+AB12+AB13+AB14-AB15+AB16+AB17-AB18-AB19-AB20-AB29-AB38-AB45-AB44-AB37+AB22-AB21 -> 18930643 | AC46: =AC5-AC7-AC8-AC9-AC10+AC12+AC13+AC14-AC15+AC16+AC17-AC18-AC19-AC20-AC29-AC38-AC45-AC44-AC37+AC22-AC21 -> 18810643 | AD46: =AD5-AD7-AD8-AD9-AD10+AD12+AD13+AD14-AD15+AD16+AD17-AD18-AD19-AD20-AD29-AD38-AD45-AD44-AD37+AD22-AD21 -> 18690643 | AJ46: 现金盘点 | AK46: =AK5-AK7-AK8-AK9-AK10+AK12+AK13+AK14-AK15+AK16+AK17-AK18-AK19-AK20-AK29-AK38-AK45-AK44-AK37+AK22-AK21 -> 18570643 | AL46: =AL5-AL7-AL8-AL9-AL10+AL12+AL13+AL14-AL15+AL16+AL17-AL18-AL19-AL20-AL29-AL38-AL45-AL44-AL37+AL22-AL21 -> 18450643 | AM46: =AM5-AM7-AM8-AM9-AM10+AM12+AM13+AM14-AM15+AM16+AM17-AM18-AM19-AM20-AM29-AM38-AM45-AM44-AM37+AM22-AM21 -> 18330643 | AN46: =AN5-AN7-AN8-AN9-AN10+AN12+AN13+AN14-AN15+AN16+AN17-AN18-AN19-AN20-AN29-AN38-AN45-AN44-AN37+AN22-AN21 -> 18210643
H47: =规则表!A48 -> 0 | I47: =规则表!B48 -> 243.33333 | J47: =规则表!C48 -> 248.40426 | K47: =规则表!D48 -> 347.22222 | O47: 第二年投广告
A49: 需要金额 | M49: 需要金额 | Y49: 需要金额 | AI49: 需要金额
A50: 贴现方案 | B50: 0 | C50: =IF(订单贴现表!C8<C49,订单贴现表!C8,C49) -> 0 | D50: =IF(订单贴现表!D8<D49,订单贴现表!D8,D49) -> 0 | E50: =IF(订单贴现表!E8<E49,订单贴现表!E8,E49) -> 0 | F50: =IF(订单贴现表!F8<F49,订单贴现表!F8,F49) -> 0 | M50: 贴现方案 | N50: 0 | O50: =IF(订单贴现表!G8<O49,订单贴现表!G8,O49) -> 0 | P50: =IF(订单贴现表!H8<P49,订单贴现表!H8,P49) -> 0 | Q50: =IF(订单贴现表!I8<Q49,订单贴现表!I8,Q49) -> 0 | R50: =IF(订单贴现表!J8<R49,订单贴现表!J8,R49) -> 0 | Y50: 贴现方案 | Z50: 0 | AA50: =IF(订单贴现表!K8<AA49,订单贴现表!K8,AA49) -> 0 | AB50: =IF(订单贴现表!L8<AB49,订单贴现表!L8,AB49) -> 0 | AC50: =IF(订单贴现表!M8<AC49,订单贴现表!M8,AC49) -> 0 | AD50: =IF(订单贴现表!N8<AD49,订单贴现表!N8,AD49) -> 0 | AI50: 贴现方案 | AJ50: 0 | AK50: =IF(订单贴现表!O8<AK49,订单贴现表!O8,AK49) -> 0 | AL50: =IF(订单贴现表!P8<AL49,订单贴现表!P8,AL49) -> 0 | AM50: =IF(订单贴现表!Q8<AM49,订单贴现表!Q8,AM49) -> 0 | AN50: =IF(订单贴现表!R8<AN49,订单贴现表!R8,AN49) -> 0
B51: 1 | C51: {=ROUNDUP(_xlfn.IFS(C49<订单贴现表!C8,0,C49<C50+订单贴现表!C9*(1-VLOOKUP(--SUBSTITUTE(订单贴现表!$B$9,"期",""),规则表!$A$10:$B$14,2,FALSE)),(C49-C50)/(1-VLOOKUP(--SUBSTITUTE(订单贴现表!$B$9,"期",""),规则表!$A$10:$B$14,2,FALSE)),TRUE,订单贴现表!C9),0)} -> 0 | D51: {=_xlfn.IFS(D49<订单贴现表!D8,0,D49<D50+订单贴现表!D9*(1-VLOOKUP(--SUBSTITUTE(订单贴现表!$B$9,"期",""),规则表!$A$10:$B$14,2,FALSE)),(D49-D50)/(1-VLOOKUP(--SUBSTITUTE(订单贴现表!$B$9,"期",""),规则表!$A$10:$B$14,2,FALSE)),TRUE,订单贴现表!D9)} -> 0 | E51: {=_xlfn.IFS(E49<订单贴现表!E8,0,E49<E50+订单贴现表!E9*(1-VLOOKUP(--SUBSTITUTE(订单贴现表!$B$9,"期",""),规则表!$A$10:$B$14,2,FALSE)),(E49-E50)/(1-VLOOKUP(--SUBSTITUTE(订单贴现表!$B$9,"期",""),规则表!$A$10:$B$14,2,FALSE)),TRUE,订单贴现表!E9)} -> 0 | F51: {=_xlfn.IFS(F49<订单贴现表!F8,0,F49<F50+订单贴现表!F9*(1-VLOOKUP(--SUBSTITUTE(订单贴现表!$B$9,"期",""),规则表!$A$10:$B$14,2,FALSE)),(F49-F50)/(1-VLOOKUP(--SUBSTITUTE(订单贴现表!$B$9,"期",""),规则表!$A$10:$B$14,2,FALSE)),TRUE,订单贴现表!F9)} -> 0 | N51: 1 | O51: {=_xlfn.IFS(O49<订单贴现表!G8,0,O49<O50+订单贴现表!G9*(1-VLOOKUP(--SUBSTITUTE(订单贴现表!$B$9,"期",""),规则表!$A$10:$B$14,2,FALSE)),(O49-O50)/(1-VLOOKUP(--SUBSTITUTE(订单贴现表!$B$9,"期",""),规则表!$A$10:$B$14,2,FALSE)),TRUE,订单贴现表!G9)} -> 0 | P51: {=_xlfn.IFS(P49<订单贴现表!H8,0,P49<P50+订单贴现表!H9*(1-VLOOKUP(--SUBSTITUTE(订单贴现表!$B$9,"期",""),规则表!$A$10:$B$14,2,FALSE)),(P49-P50)/(1-VLOOKUP(--SUBSTITUTE(订单贴现表!$B$9,"期",""),规则表!$A$10:$B$14,2,FALSE)),TRUE,订单贴现表!H9)} -> 0 | Q51: {=_xlfn.IFS(Q49<订单贴现表!I8,0,Q49<Q50+订单贴现表!I9*(1-VLOOKUP(--SUBSTITUTE(订单贴现表!$B$9,"期",""),规则表!$A$10:$B$14,2,FALSE)),(Q49-Q50)/(1-VLOOKUP(--SUBSTITUTE(订单贴现表!$B$9,"期",""),规则表!$A$10:$B$14,2,FALSE)),TRUE,订单贴现表!I9)} -> 0 | R51: {=_xlfn.IFS(R49<订单贴现表!J8,0,R49<R50+订单贴现表!J9*(1-VLOOKUP(--SUBSTITUTE(订单贴现表!$B$9,"期",""),规则表!$A$10:$B$14,2,FALSE)),(R49-R50)/(1-VLOOKUP(--SUBSTITUTE(订单贴现表!$B$9,"期",""),规则表!$A$10:$B$14,2,FALSE)),TRUE,订单贴现表!J9)} -> 0 | Z51: 1 | AA51: {=_xlfn.IFS(AA49<订单贴现表!K8,0,AA49<AA50+订单贴现表!K9*(1-VLOOKUP(--SUBSTITUTE(订单贴现表!$B$9,"期",""),规则表!$A$10:$B$14,2,FALSE)),(AA49-AA50)/(1-VLOOKUP(--SUBSTITUTE(订单贴现表!$B$9,"期",""),规则表!$A$10:$B$14,2,FALSE)),TRUE,订单贴现表!K9)} -> 0 | AB51: {=_xlfn.IFS(AB49<订单贴现表!L8,0,AB49<AB50+订单贴现表!L9*(1-VLOOKUP(--SUBSTITUTE(订单贴现表!$B$9,"期",""),规则表!$A$10:$B$14,2,FALSE)),(AB49-AB50)/(1-VLOOKUP(--SUBSTITUTE(订单贴现表!$B$9,"期",""),规则表!$A$10:$B$14,2,FALSE)),TRUE,订单贴现表!L9)} -> 0 | AC51: {=_xlfn.IFS(AC49<订单贴现表!M8,0,AC49<AC50+订单贴现表!M9*(1-VLOOKUP(--SUBSTITUTE(订单贴现表!$B$9,"期",""),规则表!$A$10:$B$14,2,FALSE)),(AC49-AC50)/(1-VLOOKUP(--SUBSTITUTE(订单贴现表!$B$9,"期",""),规则表!$A$10:$B$14,2,FALSE)),TRUE,订单贴现表!M9)} -> 0 | AD51: {=_xlfn.IFS(AD49<订单贴现表!N8,0,AD49<AD50+订单贴现表!N9*(1-VLOOKUP(--SUBSTITUTE(订单贴现表!$B$9,"期",""),规则表!$A$10:$B$14,2,FALSE)),(AD49-AD50)/(1-VLOOKUP(--SUBSTITUTE(订单贴现表!$B$9,"期",""),规则表!$A$10:$B$14,2,FALSE)),TRUE,订单贴现表!N9)} -> 0 | AJ51: 1 | AK51: {=_xlfn.IFS(AK49<订单贴现表!O8,0,AK49<AK50+订单贴现表!O9*(1-VLOOKUP(--SUBSTITUTE(订单贴现表!$B$9,"期",""),规则表!$A$10:$B$14,2,FALSE)),(AK49-AK50)/(1-VLOOKUP(--SUBSTITUTE(订单贴现表!$B$9,"期",""),规则表!$A$10:$B$14,2,FALSE)),TRUE,订单贴现表!O9)} -> 0 | AL51: {=_xlfn.IFS(AL49<订单贴现表!P8,0,AL49<AL50+订单贴现表!P9*(1-VLOOKUP(--SUBSTITUTE(订单贴现表!$B$9,"期",""),规则表!$A$10:$B$14,2,FALSE)),(AL49-AL50)/(1-VLOOKUP(--SUBSTITUTE(订单贴现表!$B$9,"期",""),规则表!$A$10:$B$14,2,FALSE)),TRUE,订单贴现表!P9)} -> 0 | AM51: {=_xlfn.IFS(AM49<订单贴现表!Q8,0,AM49<AM50+订单贴现表!Q9*(1-VLOOKUP(--SUBSTITUTE(订单贴现表!$B$9,"期",""),规则表!$A$10:$B$14,2,FALSE)),(AM49-AM50)/(1-VLOOKUP(--SUBSTITUTE(订单贴现表!$B$9,"期",""),规则表!$A$10:$B$14,2,FALSE)),TRUE,订单贴现表!Q9)} -> 0 | AN51: {=_xlfn.IFS(AN49<订单贴现表!R8,0,AN49<AN50+订单贴现表!R9*(1-VLOOKUP(--SUBSTITUTE(订单贴现表!$B$9,"期",""),规则表!$A$10:$B$14,2,FALSE)),(AN49-AN50)/(1-VLOOKUP(--SUBSTITUTE(订单贴现表!$B$9,"期",""),规则表!$A$10:$B$14,2,FALSE)),TRUE,订单贴现表!R9)} -> 0
B52: 2 | C52: {=ROUNDUP(_xlfn.IFS(C49<=C50+C51*(1-VLOOKUP(--SUBSTITUTE(订单贴现表!$B$9,"期",""),规则表!$A$10:$B$14,2,FALSE)),0,C49<C50+C51*(1-VLOOKUP(--SUBSTITUTE(订单贴现表!$B$9,"期",""),规则表!$A$10:$B$14,2,FALSE))+订单贴现表!C10*(1-VLOOKUP(--SUBSTITUTE(订单贴现表!$B$10,"期",""),规则表!$A$10:$B$14,2,FALSE)),(C49-C50-C51*(1-VLOOKUP(--SUBSTITUTE(订单贴现表!$B$9,"期",""),规则表!$A$10:$B$14,2,FALSE)))/(1-VLOOKUP(--SUBSTITUTE(订单贴现表!$B$10,"期",""),规则表!$A$10:$B$14,2,FALSE)),TRUE,订单贴现表!C10),0)} -> 0 | D52: {=_xlfn.IFS(D49<=D50+D51*(1-VLOOKUP(--SUBSTITUTE(订单贴现表!$B$9,"期",""),规则表!$A$10:$B$14,2,FALSE)),0,D49<D50+D51*(1-VLOOKUP(--SUBSTITUTE(订单贴现表!$B$9,"期",""),规则表!$A$10:$B$14,2,FALSE))+订单贴现表!D10*(1-VLOOKUP(--SUBSTITUTE(订单贴现表!$B$10,"期",""),规则表!$A$10:$B$14,2,FALSE)),(D49-D50-D51*(1-VLOOKUP(--SUBSTITUTE(订单贴现表!$B$9,"期",""),规则表!$A$10:$B$14,2,FALSE)))/(1-VLOOKUP(--SUBSTITUTE(订单贴现表!$B$10,"期",""),规则表!$A$10:$B$14,2,FALSE)),TRUE,订单贴现表!D10)} -> 0 | E52: {=_xlfn.IFS(E49<=E50+E51*(1-VLOOKUP(--SUBSTITUTE(订单贴现表!$B$9,"期",""),规则表!$A$10:$B$14,2,FALSE)),0,E49<E50+E51*(1-VLOOKUP(--SUBSTITUTE(订单贴现表!$B$9,"期",""),规则表!$A$10:$B$14,2,FALSE))+订单贴现表!E10*(1-VLOOKUP(--SUBSTITUTE(订单贴现表!$B$10,"期",""),规则表!$A$10:$B$14,2,FALSE)),(E49-E50-E51*(1-VLOOKUP(--SUBSTITUTE(订单贴现表!$B$9,"期",""),规则表!$A$10:$B$14,2,FALSE)))/(1-VLOOKUP(--SUBSTITUTE(订单贴现表!$B$10,"期",""),规则表!$A$10:$B$14,2,FALSE)),TRUE,订单贴现表!E10)} -> 0 | F52: {=_xlfn.IFS(F49<=F50+F51*(1-VLOOKUP(--SUBSTITUTE(订单贴现表!$B$9,"期",""),规则表!$A$10:$B$14,2,FALSE)),0,F49<F50+F51*(1-VLOOKUP(--SUBSTITUTE(订单贴现表!$B$9,"期",""),规则表!$A$10:$B$14,2,FALSE))+订单贴现表!F10*(1-VLOOKUP(--SUBSTITUTE(订单贴现表!$B$10,"期",""),规则表!$A$10:$B$14,2,FALSE)),(F49-F50-F51*(1-VLOOKUP(--SUBSTITUTE(订单贴现表!$B$9,"期",""),规则表!$A$10:$B$14,2,FALSE)))/(1-VLOOKUP(--SUBSTITUTE(订单贴现表!$B$10,"期",""),规则表!$A$10:$B$14,2,FALSE)),TRUE,订单贴现表!F10)} -> 0 | N52: 2 | O52: {=_xlfn.IFS(O49<=O50+O51*(1-VLOOKUP(--SUBSTITUTE(订单贴现表!$B$9,"期",""),规则表!$A$10:$B$14,2,FALSE)),0,O49<O50+O51*(1-VLOOKUP(--SUBSTITUTE(订单贴现表!$B$9,"期",""),规则表!$A$10:$B$14,2,FALSE))+订单贴现表!G10*(1-VLOOKUP(--SUBSTITUTE(订单贴现表!$B$10,"期",""),规则表!$A$10:$B$14,2,FALSE)),(O49-O50-O51*(1-VLOOKUP(--SUBSTITUTE(订单贴现表!$B$9,"期",""),规则表!$A$10:$B$14,2,FALSE)))/(1-VLOOKUP(--SUBSTITUTE(订单贴现表!$B$10,"期",""),规则表!$A$10:$B$14,2,FALSE)),TRUE,订单贴现表!G10)} -> 0 | P52: {=_xlfn.IFS(P49<=P50+P51*(1-VLOOKUP(--SUBSTITUTE(订单贴现表!$B$9,"期",""),规则表!$A$10:$B$14,2,FALSE)),0,P49<P50+P51*(1-VLOOKUP(--SUBSTITUTE(订单贴现表!$B$9,"期",""),规则表!$A$10:$B$14,2,FALSE))+订单贴现表!H10*(1-VLOOKUP(--SUBSTITUTE(订单贴现表!$B$10,"期",""),规则表!$A$10:$B$14,2,FALSE)),(P49-P50-P51*(1-VLOOKUP(--SUBSTITUTE(订单贴现表!$B$9,"期",""),规则表!$A$10:$B$14,2,FALSE)))/(1-VLOOKUP(--SUBSTITUTE(订单贴现表!$B$10,"期",""),规则表!$A$10:$B$14,2,FALSE)),TRUE,订单贴现表!H10)} -> 0 | Q52: {=_xlfn.IFS(Q49<=Q50+Q51*(1-VLOOKUP(--SUBSTITUTE(订单贴现表!$B$9,"期",""),规则表!$A$10:$B$14,2,FALSE)),0,Q49<Q50+Q51*(1-VLOOKUP(--SUBSTITUTE(订单贴现表!$B$9,"期",""),规则表!$A$10:$B$14,2,FALSE))+订单贴现表!I10*(1-VLOOKUP(--SUBSTITUTE(订单贴现表!$B$10,"期",""),规则表!$A$10:$B$14,2,FALSE)),(Q49-Q50-Q51*(1-VLOOKUP(--SUBSTITUTE(订单贴现表!$B$9,"期",""),规则表!$A$10:$B$14,2,FALSE)))/(1-VLOOKUP(--SUBSTITUTE(订单贴现表!$B$10,"期",""),规则表!$A$10:$B$14,2,FALSE)),TRUE,订单贴现表!I10)} -> 0 | R52: {=_xlfn.IFS(R49<=R50+R51*(1-VLOOKUP(--SUBSTITUTE(订单贴现表!$B$9,"期",""),规则表!$A$10:$B$14,2,FALSE)),0,R49<R50+R51*(1-VLOOKUP(--SUBSTITUTE(订单贴现表!$B$9,"期",""),规则表!$A$10:$B$14,2,FALSE))+订单贴现表!J10*(1-VLOOKUP(--SUBSTITUTE(订单贴现表!$B$10,"期",""),规则表!$A$10:$B$14,2,FALSE)),(R49-R50-R51*(1-VLOOKUP(--SUBSTITUTE(订单贴现表!$B$9,"期",""),规则表!$A$10:$B$14,2,FALSE)))/(1-VLOOKUP(--SUBSTITUTE(订单贴现表!$B$10,"期",""),规则表!$A$10:$B$14,2,FALSE)),TRUE,订单贴现表!J10)} -> 0 | Z52: 2 | AA52: {=_xlfn.IFS(AA49<=AA50+AA51*(1-VLOOKUP(--SUBSTITUTE(订单贴现表!$B$9,"期",""),规则表!$A$10:$B$14,2,FALSE)),0,AA49<AA50+AA51*(1-VLOOKUP(--SUBSTITUTE(订单贴现表!$B$9,"期",""),规则表!$A$10:$B$14,2,FALSE))+订单贴现表!K10*(1-VLOOKUP(--SUBSTITUTE(订单贴现表!$B$10,"期",""),规则表!$A$10:$B$14,2,FALSE)),(AA49-AA50-AA51*(1-VLOOKUP(--SUBSTITUTE(订单贴现表!$B$9,"期",""),规则表!$A$10:$B$14,2,FALSE)))/(1-VLOOKUP(--SUBSTITUTE(订单贴现表!$B$10,"期",""),规则表!$A$10:$B$14,2,FALSE)),TRUE,订单贴现表!K10)} -> 0 | AB52: {=_xlfn.IFS(AB49<=AB50+AB51*(1-VLOOKUP(--SUBSTITUTE(订单贴现表!$B$9,"期",""),规则表!$A$10:$B$14,2,FALSE)),0,AB49<AB50+AB51*(1-VLOOKUP(--SUBSTITUTE(订单贴现表!$B$9,"期",""),规则表!$A$10:$B$14,2,FALSE))+订单贴现表!L10*(1-VLOOKUP(--SUBSTITUTE(订单贴现表!$B$10,"期",""),规则表!$A$10:$B$14,2,FALSE)),(AB49-AB50-AB51*(1-VLOOKUP(--SUBSTITUTE(订单贴现表!$B$9,"期",""),规则表!$A$10:$B$14,2,FALSE)))/(1-VLOOKUP(--SUBSTITUTE(订单贴现表!$B$10,"期",""),规则表!$A$10:$B$14,2,FALSE)),TRUE,订单贴现表!L10)} -> 0 | AC52: {=_xlfn.IFS(AC49<=AC50+AC51*(1-VLOOKUP(--SUBSTITUTE(订单贴现表!$B$9,"期",""),规则表!$A$10:$B$14,2,FALSE)),0,AC49<AC50+AC51*(1-VLOOKUP(--SUBSTITUTE(订单贴现表!$B$9,"期",""),规则表!$A$10:$B$14,2,FALSE))+订单贴现表!M10*(1-VLOOKUP(--SUBSTITUTE(订单贴现表!$B$10,"期",""),规则表!$A$10:$B$14,2,FALSE)),(AC49-AC50-AC51*(1-VLOOKUP(--SUBSTITUTE(订单贴现表!$B$9,"期",""),规则表!$A$10:$B$14,2,FALSE)))/(1-VLOOKUP(--SUBSTITUTE(订单贴现表!$B$10,"期",""),规则表!$A$10:$B$14,2,FALSE)),TRUE,订单贴现表!M10)} -> 0 | AD52: {=_xlfn.IFS(AD49<=AD50+AD51*(1-VLOOKUP(--SUBSTITUTE(订单贴现表!$B$9,"期",""),规则表!$A$10:$B$14,2,FALSE)),0,AD49<AD50+AD51*(1-VLOOKUP(--SUBSTITUTE(订单贴现表!$B$9,"期",""),规则表!$A$10:$B$14,2,FALSE))+订单贴现表!N10*(1-VLOOKUP(--SUBSTITUTE(订单贴现表!$B$10,"期",""),规则表!$A$10:$B$14,2,FALSE)),(AD49-AD50-AD51*(1-VLOOKUP(--SUBSTITUTE(订单贴现表!$B$9,"期",""),规则表!$A$10:$B$14,2,FALSE)))/(1-VLOOKUP(--SUBSTITUTE(订单贴现表!$B$10,"期",""),规则表!$A$10:$B$14,2,FALSE)),TRUE,订单贴现表!N10)} -> 0 | AJ52: 2 | AK52: {=_xlfn.IFS(AK49<=AK50+AK51*(1-VLOOKUP(--SUBSTITUTE(订单贴现表!$B$9,"期",""),规则表!$A$10:$B$14,2,FALSE)),0,AK49<AK50+AK51*(1-VLOOKUP(--SUBSTITUTE(订单贴现表!$B$9,"期",""),规则表!$A$10:$B$14,2,FALSE))+订单贴现表!O10*(1-VLOOKUP(--SUBSTITUTE(订单贴现表!$B$10,"期",""),规则表!$A$10:$B$14,2,FALSE)),(AK49-AK50-AK51*(1-VLOOKUP(--SUBSTITUTE(订单贴现表!$B$9,"期",""),规则表!$A$10:$B$14,2,FALSE)))/(1-VLOOKUP(--SUBSTITUTE(订单贴现表!$B$10,"期",""),规则表!$A$10:$B$14,2,FALSE)),TRUE,订单贴现表!O10)} -> 0 | AL52: {=_xlfn.IFS(AL49<=AL50+AL51*(1-VLOOKUP(--SUBSTITUTE(订单贴现表!$B$9,"期",""),规则表!$A$10:$B$14,2,FALSE)),0,AL49<AL50+AL51*(1-VLOOKUP(--SUBSTITUTE(订单贴现表!$B$9,"期",""),规则表!$A$10:$B$14,2,FALSE))+订单贴现表!P10*(1-VLOOKUP(--SUBSTITUTE(订单贴现表!$B$10,"期",""),规则表!$A$10:$B$14,2,FALSE)),(AL49-AL50-AL51*(1-VLOOKUP(--SUBSTITUTE(订单贴现表!$B$9,"期",""),规则表!$A$10:$B$14,2,FALSE)))/(1-VLOOKUP(--SUBSTITUTE(订单贴现表!$B$10,"期",""),规则表!$A$10:$B$14,2,FALSE)),TRUE,订单贴现表!P10)} -> 0 | AM52: {=_xlfn.IFS(AM49<=AM50+AM51*(1-VLOOKUP(--SUBSTITUTE(订单贴现表!$B$9,"期",""),规则表!$A$10:$B$14,2,FALSE)),0,AM49<AM50+AM51*(1-VLOOKUP(--SUBSTITUTE(订单贴现表!$B$9,"期",""),规则表!$A$10:$B$14,2,FALSE))+订单贴现表!Q10*(1-VLOOKUP(--SUBSTITUTE(订单贴现表!$B$10,"期",""),规则表!$A$10:$B$14,2,FALSE)),(AM49-AM50-AM51*(1-VLOOKUP(--SUBSTITUTE(订单贴现表!$B$9,"期",""),规则表!$A$10:$B$14,2,FALSE)))/(1-VLOOKUP(--SUBSTITUTE(订单贴现表!$B$10,"期",""),规则表!$A$10:$B$14,2,FALSE)),TRUE,订单贴现表!Q10)} -> 0 | AN52: {=_xlfn.IFS(AN49<=AN50+AN51*(1-VLOOKUP(--SUBSTITUTE(订单贴现表!$B$9,"期",""),规则表!$A$10:$B$14,2,FALSE)),0,AN49<AN50+AN51*(1-VLOOKUP(--SUBSTITUTE(订单贴现表!$B$9,"期",""),规则表!$A$10:$B$14,2,FALSE))+订单贴现表!R10*(1-VLOOKUP(--SUBSTITUTE(订单贴现表!$B$10,"期",""),规则表!$A$10:$B$14,2,FALSE)),(AN49-AN50-AN51*(1-VLOOKUP(--SUBSTITUTE(订单贴现表!$B$9,"期",""),规则表!$A$10:$B$14,2,FALSE)))/(1-VLOOKUP(--SUBSTITUTE(订单贴现表!$B$10,"期",""),规则表!$A$10:$B$14,2,FALSE)),TRUE,订单贴现表!R10)} -> 0
B53: 3 | C53: {=ROUNDUP(_xlfn.IFS(C49<=C50+C51*(1-VLOOKUP(--SUBSTITUTE(订单贴现表!$B$9,"期",""),规则表!$A$10:$B$14,2,FALSE))+C52*(1-VLOOKUP(--SUBSTITUTE(订单贴现表!$B$10,"期",""),规则表!$A$10:$B$14,2,FALSE)),0,C49<C50+C51*(1-VLOOKUP(--SUBSTITUTE(订单贴现表!$B$9,"期",""),规则表!$A$10:$B$14,2,FALSE))+C52*(1-VLOOKUP(--SUBSTITUTE(订单贴现表!$B$10,"期",""),规则表!$A$10:$B$14,2,FALSE))+订单贴现表!C11*(1-VLOOKUP(--SUBSTITUTE(订单贴现表!$B$11,"期",""),规则表!$A$10:$B$14,2,FALSE)),(C49-C50-C51*(1-VLOOKUP(--SUBSTITUTE(订单贴现表!$B$9,"期",""),规则表!$A$10:$B$14,2,FALSE))-C52*(1-VLOOKUP(--SUBSTITUTE(订单贴现表!$B$10,"期",""),规则表!$A$10:$B$14,2,FALSE)))/(1-VLOOKUP(--SUBSTITUTE(订单贴现表!$B$11,"期",""),规则表!$A$10:$B$14,2,FALSE)),TRUE,订单贴现表!C11),0)} -> 0 | D53: {=_xlfn.IFS(D49<=D50+D51*(1-VLOOKUP(--SUBSTITUTE(订单贴现表!$B$9,"期",""),规则表!$A$10:$B$14,2,FALSE))+D52*(1-VLOOKUP(--SUBSTITUTE(订单贴现表!$B$10,"期",""),规则表!$A$10:$B$14,2,FALSE)),0,D49<D50+D51*(1-VLOOKUP(--SUBSTITUTE(订单贴现表!$B$9,"期",""),规则表!$A$10:$B$14,2,FALSE))+D52*(1-VLOOKUP(--SUBSTITUTE(订单贴现表!$B$10,"期",""),规则表!$A$10:$B$14,2,FALSE))+订单贴现表!D11*(1-VLOOKUP(--SUBSTITUTE(订单贴现表!$B$11,"期",""),规则表!$A$10:$B$14,2,FALSE)),(D49-D50-D51*(1-VLOOKUP(--SUBSTITUTE(订单贴现表!$B$9,"期",""),规则表!$A$10:$B$14,2,FALSE))-D52*(1-VLOOKUP(--SUBSTITUTE(订单贴现表!$B$10,"期",""),规则表!$A$10:$B$14,2,FALSE)))/(1-VLOOKUP(--SUBSTITUTE(订单贴现表!$B$11,"期",""),规则表!$A$10:$B$14,2,FALSE)),TRUE,订单贴现表!D11)} -> 0 | E53: {=_xlfn.IFS(E49<=E50+E51*(1-VLOOKUP(--SUBSTITUTE(订单贴现表!$B$9,"期",""),规则表!$A$10:$B$14,2,FALSE))+E52*(1-VLOOKUP(--SUBSTITUTE(订单贴现表!$B$10,"期",""),规则表!$A$10:$B$14,2,FALSE)),0,E49<E50+E51*(1-VLOOKUP(--SUBSTITUTE(订单贴现表!$B$9,"期",""),规则表!$A$10:$B$14,2,FALSE))+E52*(1-VLOOKUP(--SUBSTITUTE(订单贴现表!$B$10,"期",""),规则表!$A$10:$B$14,2,FALSE))+订单贴现表!E11*(1-VLOOKUP(--SUBSTITUTE(订单贴现表!$B$11,"期",""),规则表!$A$10:$B$14,2,FALSE)),(E49-E50-E51*(1-VLOOKUP(--SUBSTITUTE(订单贴现表!$B$9,"期",""),规则表!$A$10:$B$14,2,FALSE))-E52*(1-VLOOKUP(--SUBSTITUTE(订单贴现表!$B$10,"期",""),规则表!$A$10:$B$14,2,FALSE)))/(1-VLOOKUP(--SUBSTITUTE(订单贴现表!$B$11,"期",""),规则表!$A$10:$B$14,2,FALSE)),TRUE,订单贴现表!E11)} -> 0 | F53: {=_xlfn.IFS(F49<=F50+F51*(1-VLOOKUP(--SUBSTITUTE(订单贴现表!$B$9,"期",""),规则表!$A$10:$B$14,2,FALSE))+F52*(1-VLOOKUP(--SUBSTITUTE(订单贴现表!$B$10,"期",""),规则表!$A$10:$B$14,2,FALSE)),0,F49<F50+F51*(1-VLOOKUP(--SUBSTITUTE(订单贴现表!$B$9,"期",""),规则表!$A$10:$B$14,2,FALSE))+F52*(1-VLOOKUP(--SUBSTITUTE(订单贴现表!$B$10,"期",""),规则表!$A$10:$B$14,2,FALSE))+订单贴现表!F11*(1-VLOOKUP(--SUBSTITUTE(订单贴现表!$B$11,"期",""),规则表!$A$10:$B$14,2,FALSE)),(F49-F50-F51*(1-VLOOKUP(--SUBSTITUTE(订单贴现表!$B$9,"期",""),规则表!$A$10:$B$14,2,FALSE))-F52*(1-VLOOKUP(--SUBSTITUTE(订单贴现表!$B$10,"期",""),规则表!$A$10:$B$14,2,FALSE)))/(1-VLOOKUP(--SUBSTITUTE(订单贴现表!$B$11,"期",""),规则表!$A$10:$B$14,2,FALSE)),TRUE,订单贴现表!F11)} -> 0 | H53: {=_xlfn.TOCOL(_xlfn.TAKE(_xlfn.UNIQUE(原始订单表!E1:E1000),COUNTA(_xlfn.UNIQUE(原始订单表!E1:E1000)+1)),1)} -> 产品 | I53: 消耗金钱 (元) | J53: 消耗时间 (季) | K53: 最晚要开季度 | N53: 3 | O53: {=_xlfn.IFS(O49<=O50+O51*(1-VLOOKUP(--SUBSTITUTE(订单贴现表!$B$9,"期",""),规则表!$A$10:$B$14,2,FALSE))+O52*(1-VLOOKUP(--SUBSTITUTE(订单贴现表!$B$10,"期",""),规则表!$A$10:$B$14,2,FALSE)),0,O49<O50+O51*(1-VLOOKUP(--SUBSTITUTE(订单贴现表!$B$9,"期",""),规则表!$A$10:$B$14,2,FALSE))+O52*(1-VLOOKUP(--SUBSTITUTE(订单贴现表!$B$10,"期",""),规则表!$A$10:$B$14,2,FALSE))+订单贴现表!G11*(1-VLOOKUP(--SUBSTITUTE(订单贴现表!$B$11,"期",""),规则表!$A$10:$B$14,2,FALSE)),(O49-O50-O51*(1-VLOOKUP(--SUBSTITUTE(订单贴现表!$B$9,"期",""),规则表!$A$10:$B$14,2,FALSE))-O52*(1-VLOOKUP(--SUBSTITUTE(订单贴现表!$B$10,"期",""),规则表!$A$10:$B$14,2,FALSE)))/(1-VLOOKUP(--SUBSTITUTE(订单贴现表!$B$11,"期",""),规则表!$A$10:$B$14,2,FALSE)),TRUE,订单贴现表!G11)} -> 0 | P53: {=_xlfn.IFS(P49<=P50+P51*(1-VLOOKUP(--SUBSTITUTE(订单贴现表!$B$9,"期",""),规则表!$A$10:$B$14,2,FALSE))+P52*(1-VLOOKUP(--SUBSTITUTE(订单贴现表!$B$10,"期",""),规则表!$A$10:$B$14,2,FALSE)),0,P49<P50+P51*(1-VLOOKUP(--SUBSTITUTE(订单贴现表!$B$9,"期",""),规则表!$A$10:$B$14,2,FALSE))+P52*(1-VLOOKUP(--SUBSTITUTE(订单贴现表!$B$10,"期",""),规则表!$A$10:$B$14,2,FALSE))+订单贴现表!H11*(1-VLOOKUP(--SUBSTITUTE(订单贴现表!$B$11,"期",""),规则表!$A$10:$B$14,2,FALSE)),(P49-P50-P51*(1-VLOOKUP(--SUBSTITUTE(订单贴现表!$B$9,"期",""),规则表!$A$10:$B$14,2,FALSE))-P52*(1-VLOOKUP(--SUBSTITUTE(订单贴现表!$B$10,"期",""),规则表!$A$10:$B$14,2,FALSE)))/(1-VLOOKUP(--SUBSTITUTE(订单贴现表!$B$11,"期",""),规则表!$A$10:$B$14,2,FALSE)),TRUE,订单贴现表!H11)} -> 0 | Q53: {=_xlfn.IFS(Q49<=Q50+Q51*(1-VLOOKUP(--SUBSTITUTE(订单贴现表!$B$9,"期",""),规则表!$A$10:$B$14,2,FALSE))+Q52*(1-VLOOKUP(--SUBSTITUTE(订单贴现表!$B$10,"期",""),规则表!$A$10:$B$14,2,FALSE)),0,Q49<Q50+Q51*(1-VLOOKUP(--SUBSTITUTE(订单贴现表!$B$9,"期",""),规则表!$A$10:$B$14,2,FALSE))+Q52*(1-VLOOKUP(--SUBSTITUTE(订单贴现表!$B$10,"期",""),规则表!$A$10:$B$14,2,FALSE))+订单贴现表!I11*(1-VLOOKUP(--SUBSTITUTE(订单贴现表!$B$11,"期",""),规则表!$A$10:$B$14,2,FALSE)),(Q49-Q50-Q51*(1-VLOOKUP(--SUBSTITUTE(订单贴现表!$B$9,"期",""),规则表!$A$10:$B$14,2,FALSE))-Q52*(1-VLOOKUP(--SUBSTITUTE(订单贴现表!$B$10,"期",""),规则表!$A$10:$B$14,2,FALSE)))/(1-VLOOKUP(--SUBSTITUTE(订单贴现表!$B$11,"期",""),规则表!$A$10:$B$14,2,FALSE)),TRUE,订单贴现表!I11)} -> 0 | R53: {=_xlfn.IFS(R49<=R50+R51*(1-VLOOKUP(--SUBSTITUTE(订单贴现表!$B$9,"期",""),规则表!$A$10:$B$14,2,FALSE))+R52*(1-VLOOKUP(--SUBSTITUTE(订单贴现表!$B$10,"期",""),规则表!$A$10:$B$14,2,FALSE)),0,R49<R50+R51*(1-VLOOKUP(--SUBSTITUTE(订单贴现表!$B$9,"期",""),规则表!$A$10:$B$14,2,FALSE))+R52*(1-VLOOKUP(--SUBSTITUTE(订单贴现表!$B$10,"期",""),规则表!$A$10:$B$14,2,FALSE))+订单贴现表!J11*(1-VLOOKUP(--SUBSTITUTE(订单贴现表!$B$11,"期",""),规则表!$A$10:$B$14,2,FALSE)),(R49-R50-R51*(1-VLOOKUP(--SUBSTITUTE(订单贴现表!$B$9,"期",""),规则表!$A$10:$B$14,2,FALSE))-R52*(1-VLOOKUP(--SUBSTITUTE(订单贴现表!$B$10,"期",""),规则表!$A$10:$B$14,2,FALSE)))/(1-VLOOKUP(--SUBSTITUTE(订单贴现表!$B$11,"期",""),规则表!$A$10:$B$14,2,FALSE)),TRUE,订单贴现表!J11)} -> 0 | Z53: 3 | AA53: {=_xlfn.IFS(AA49<=AA50+AA51*(1-VLOOKUP(--SUBSTITUTE(订单贴现表!$B$9,"期",""),规则表!$A$10:$B$14,2,FALSE))+AA52*(1-VLOOKUP(--SUBSTITUTE(订单贴现表!$B$10,"期",""),规则表!$A$10:$B$14,2,FALSE)),0,AA49<AA50+AA51*(1-VLOOKUP(--SUBSTITUTE(订单贴现表!$B$9,"期",""),规则表!$A$10:$B$14,2,FALSE))+AA52*(1-VLOOKUP(--SUBSTITUTE(订单贴现表!$B$10,"期",""),规则表!$A$10:$B$14,2,FALSE))+订单贴现表!K11*(1-VLOOKUP(--SUBSTITUTE(订单贴现表!$B$11,"期",""),规则表!$A$10:$B$14,2,FALSE)),(AA49-AA50-AA51*(1-VLOOKUP(--SUBSTITUTE(订单贴现表!$B$9,"期",""),规则表!$A$10:$B$14,2,FALSE))-AA52*(1-VLOOKUP(--SUBSTITUTE(订单贴现表!$B$10,"期",""),规则表!$A$10:$B$14,2,FALSE)))/(1-VLOOKUP(--SUBSTITUTE(订单贴现表!$B$11,"期",""),规则表!$A$10:$B$14,2,FALSE)),TRUE,订单贴现表!K11)} -> 0 | AB53: {=_xlfn.IFS(AB49<=AB50+AB51*(1-VLOOKUP(--SUBSTITUTE(订单贴现表!$B$9,"期",""),规则表!$A$10:$B$14,2,FALSE))+AB52*(1-VLOOKUP(--SUBSTITUTE(订单贴现表!$B$10,"期",""),规则表!$A$10:$B$14,2,FALSE)),0,AB49<AB50+AB51*(1-VLOOKUP(--SUBSTITUTE(订单贴现表!$B$9,"期",""),规则表!$A$10:$B$14,2,FALSE))+AB52*(1-VLOOKUP(--SUBSTITUTE(订单贴现表!$B$10,"期",""),规则表!$A$10:$B$14,2,FALSE))+订单贴现表!L11*(1-VLOOKUP(--SUBSTITUTE(订单贴现表!$B$11,"期",""),规则表!$A$10:$B$14,2,FALSE)),(AB49-AB50-AB51*(1-VLOOKUP(--SUBSTITUTE(订单贴现表!$B$9,"期",""),规则表!$A$10:$B$14,2,FALSE))-AB52*(1-VLOOKUP(--SUBSTITUTE(订单贴现表!$B$10,"期",""),规则表!$A$10:$B$14,2,FALSE)))/(1-VLOOKUP(--SUBSTITUTE(订单贴现表!$B$11,"期",""),规则表!$A$10:$B$14,2,FALSE)),TRUE,订单贴现表!L11)} -> 0 | AC53: {=_xlfn.IFS(AC49<=AC50+AC51*(1-VLOOKUP(--SUBSTITUTE(订单贴现表!$B$9,"期",""),规则表!$A$10:$B$14,2,FALSE))+AC52*(1-VLOOKUP(--SUBSTITUTE(订单贴现表!$B$10,"期",""),规则表!$A$10:$B$14,2,FALSE)),0,AC49<AC50+AC51*(1-VLOOKUP(--SUBSTITUTE(订单贴现表!$B$9,"期",""),规则表!$A$10:$B$14,2,FALSE))+AC52*(1-VLOOKUP(--SUBSTITUTE(订单贴现表!$B$10,"期",""),规则表!$A$10:$B$14,2,FALSE))+订单贴现表!M11*(1-VLOOKUP(--SUBSTITUTE(订单贴现表!$B$11,"期",""),规则表!$A$10:$B$14,2,FALSE)),(AC49-AC50-AC51*(1-VLOOKUP(--SUBSTITUTE(订单贴现表!$B$9,"期",""),规则表!$A$10:$B$14,2,FALSE))-AC52*(1-VLOOKUP(--SUBSTITUTE(订单贴现表!$B$10,"期",""),规则表!$A$10:$B$14,2,FALSE)))/(1-VLOOKUP(--SUBSTITUTE(订单贴现表!$B$11,"期",""),规则表!$A$10:$B$14,2,FALSE)),TRUE,订单贴现表!M11)} -> 0 | AD53: {=_xlfn.IFS(AD49<=AD50+AD51*(1-VLOOKUP(--SUBSTITUTE(订单贴现表!$B$9,"期",""),规则表!$A$10:$B$14,2,FALSE))+AD52*(1-VLOOKUP(--SUBSTITUTE(订单贴现表!$B$10,"期",""),规则表!$A$10:$B$14,2,FALSE)),0,AD49<AD50+AD51*(1-VLOOKUP(--SUBSTITUTE(订单贴现表!$B$9,"期",""),规则表!$A$10:$B$14,2,FALSE))+AD52*(1-VLOOKUP(--SUBSTITUTE(订单贴现表!$B$10,"期",""),规则表!$A$10:$B$14,2,FALSE))+订单贴现表!N11*(1-VLOOKUP(--SUBSTITUTE(订单贴现表!$B$11,"期",""),规则表!$A$10:$B$14,2,FALSE)),(AD49-AD50-AD51*(1-VLOOKUP(--SUBSTITUTE(订单贴现表!$B$9,"期",""),规则表!$A$10:$B$14,2,FALSE))-AD52*(1-VLOOKUP(--SUBSTITUTE(订单贴现表!$B$10,"期",""),规则表!$A$10:$B$14,2,FALSE)))/(1-VLOOKUP(--SUBSTITUTE(订单贴现表!$B$11,"期",""),规则表!$A$10:$B$14,2,FALSE)),TRUE,订单贴现表!N11)} -> 0 | AJ53: 3 | AK53: {=_xlfn.IFS(AK49<=AK50+AK51*(1-VLOOKUP(--SUBSTITUTE(订单贴现表!$B$9,"期",""),规则表!$A$10:$B$14,2,FALSE))+AK52*(1-VLOOKUP(--SUBSTITUTE(订单贴现表!$B$10,"期",""),规则表!$A$10:$B$14,2,FALSE)),0,AK49<AK50+AK51*(1-VLOOKUP(--SUBSTITUTE(订单贴现表!$B$9,"期",""),规则表!$A$10:$B$14,2,FALSE))+AK52*(1-VLOOKUP(--SUBSTITUTE(订单贴现表!$B$10,"期",""),规则表!$A$10:$B$14,2,FALSE))+订单贴现表!O11*(1-VLOOKUP(--SUBSTITUTE(订单贴现表!$B$11,"期",""),规则表!$A$10:$B$14,2,FALSE)),(AK49-AK50-AK51*(1-VLOOKUP(--SUBSTITUTE(订单贴现表!$B$9,"期",""),规则表!$A$10:$B$14,2,FALSE))-AK52*(1-VLOOKUP(--SUBSTITUTE(订单贴现表!$B$10,"期",""),规则表!$A$10:$B$14,2,FALSE)))/(1-VLOOKUP(--SUBSTITUTE(订单贴现表!$B$11,"期",""),规则表!$A$10:$B$14,2,FALSE)),TRUE,订单贴现表!O11)} -> 0 | AL53: {=_xlfn.IFS(AL49<=AL50+AL51*(1-VLOOKUP(--SUBSTITUTE(订单贴现表!$B$9,"期",""),规则表!$A$10:$B$14,2,FALSE))+AL52*(1-VLOOKUP(--SUBSTITUTE(订单贴现表!$B$10,"期",""),规则表!$A$10:$B$14,2,FALSE)),0,AL49<AL50+AL51*(1-VLOOKUP(--SUBSTITUTE(订单贴现表!$B$9,"期",""),规则表!$A$10:$B$14,2,FALSE))+AL52*(1-VLOOKUP(--SUBSTITUTE(订单贴现表!$B$10,"期",""),规则表!$A$10:$B$14,2,FALSE))+订单贴现表!P11*(1-VLOOKUP(--SUBSTITUTE(订单贴现表!$B$11,"期",""),规则表!$A$10:$B$14,2,FALSE)),(AL49-AL50-AL51*(1-VLOOKUP(--SUBSTITUTE(订单贴现表!$B$9,"期",""),规则表!$A$10:$B$14,2,FALSE))-AL52*(1-VLOOKUP(--SUBSTITUTE(订单贴现表!$B$10,"期",""),规则表!$A$10:$B$14,2,FALSE)))/(1-VLOOKUP(--SUBSTITUTE(订单贴现表!$B$11,"期",""),规则表!$A$10:$B$14,2,FALSE)),TRUE,订单贴现表!P11)} -> 0 | AM53: {=_xlfn.IFS(AM49<=AM50+AM51*(1-VLOOKUP(--SUBSTITUTE(订单贴现表!$B$9,"期",""),规则表!$A$10:$B$14,2,FALSE))+AM52*(1-VLOOKUP(--SUBSTITUTE(订单贴现表!$B$10,"期",""),规则表!$A$10:$B$14,2,FALSE)),0,AM49<AM50+AM51*(1-VLOOKUP(--SUBSTITUTE(订单贴现表!$B$9,"期",""),规则表!$A$10:$B$14,2,FALSE))+AM52*(1-VLOOKUP(--SUBSTITUTE(订单贴现表!$B$10,"期",""),规则表!$A$10:$B$14,2,FALSE))+订单贴现表!Q11*(1-VLOOKUP(--SUBSTITUTE(订单贴现表!$B$11,"期",""),规则表!$A$10:$B$14,2,FALSE)),(AM49-AM50-AM51*(1-VLOOKUP(--SUBSTITUTE(订单贴现表!$B$9,"期",""),规则表!$A$10:$B$14,2,FALSE))-AM52*(1-VLOOKUP(--SUBSTITUTE(订单贴现表!$B$10,"期",""),规则表!$A$10:$B$14,2,FALSE)))/(1-VLOOKUP(--SUBSTITUTE(订单贴现表!$B$11,"期",""),规则表!$A$10:$B$14,2,FALSE)),TRUE,订单贴现表!Q11)} -> 0 | AN53: {=_xlfn.IFS(AN49<=AN50+AN51*(1-VLOOKUP(--SUBSTITUTE(订单贴现表!$B$9,"期",""),规则表!$A$10:$B$14,2,FALSE))+AN52*(1-VLOOKUP(--SUBSTITUTE(订单贴现表!$B$10,"期",""),规则表!$A$10:$B$14,2,FALSE)),0,AN49<AN50+AN51*(1-VLOOKUP(--SUBSTITUTE(订单贴现表!$B$9,"期",""),规则表!$A$10:$B$14,2,FALSE))+AN52*(1-VLOOKUP(--SUBSTITUTE(订单贴现表!$B$10,"期",""),规则表!$A$10:$B$14,2,FALSE))+订单贴现表!R11*(1-VLOOKUP(--SUBSTITUTE(订单贴现表!$B$11,"期",""),规则表!$A$10:$B$14,2,FALSE)),(AN49-AN50-AN51*(1-VLOOKUP(--SUBSTITUTE(订单贴现表!$B$9,"期",""),规则表!$A$10:$B$14,2,FALSE))-AN52*(1-VLOOKUP(--SUBSTITUTE(订单贴现表!$B$10,"期",""),规则表!$A$10:$B$14,2,FALSE)))/(1-VLOOKUP(--SUBSTITUTE(订单贴现表!$B$11,"期",""),规则表!$A$10:$B$14,2,FALSE)),TRUE,订单贴现表!R11)} -> 0
B54: 4 | C54: {=ROUNDUP(_xlfn.IFS(C49<=C50+C51*(1-VLOOKUP(--SUBSTITUTE(订单贴现表!$B$4,"期",""),规则表!$A$10:$B$14,2,FALSE))+C52*(1-VLOOKUP(--SUBSTITUTE(订单贴现表!$B$5,"期",""),规则表!$A$10:$B$14,2,FALSE))+C53*(1-VLOOKUP(--SUBSTITUTE(订单贴现表!$B$6,"期",""),规则表!$A$10:$B$14,2,FALSE)),0,C49<C50+C51*(1-VLOOKUP(--SUBSTITUTE(订单贴现表!$B$4,"期",""),规则表!$A$10:$B$14,2,FALSE))+C52*(1-VLOOKUP(--SUBSTITUTE(订单贴现表!$B$5,"期",""),规则表!$A$10:$B$14,2,FALSE))+C53*(1-VLOOKUP(--SUBSTITUTE(订单贴现表!$B$6,"期",""),规则表!$A$10:$B$14,2,FALSE))+订单贴现表!C7*(1-VLOOKUP(--SUBSTITUTE(订单贴现表!$B$7,"期",""),规则表!$A$10:$B$14,2,FALSE)),(C49-C50-C51*(1-VLOOKUP(--SUBSTITUTE(订单贴现表!$B$4,"期",""),规则表!$A$10:$B$14,2,FALSE))-C52*(1-VLOOKUP(--SUBSTITUTE(订单贴现表!$B$5,"期",""),规则表!$A$10:$B$14,2,FALSE))-C53*(1-VLOOKUP(--SUBSTITUTE(订单贴现表!$B$6,"期",""),规则表!$A$10:$B$14,2,FALSE)))/(1-VLOOKUP(--SUBSTITUTE(订单贴现表!$B$7,"期",""),规则表!$A$10:$B$14,2,FALSE)),TRUE,订单贴现表!C7),0)} -> 0 | D54: {=_xlfn.IFS(D49<=D50+D51*(1-VLOOKUP(--SUBSTITUTE(订单贴现表!$B$4,"期",""),规则表!$A$10:$B$14,2,FALSE))+D52*(1-VLOOKUP(--SUBSTITUTE(订单贴现表!$B$5,"期",""),规则表!$A$10:$B$14,2,FALSE))+D53*(1-VLOOKUP(--SUBSTITUTE(订单贴现表!$B$6,"期",""),规则表!$A$10:$B$14,2,FALSE)),0,D49<D50+D51*(1-VLOOKUP(--SUBSTITUTE(订单贴现表!$B$4,"期",""),规则表!$A$10:$B$14,2,FALSE))+D52*(1-VLOOKUP(--SUBSTITUTE(订单贴现表!$B$5,"期",""),规则表!$A$10:$B$14,2,FALSE))+D53*(1-VLOOKUP(--SUBSTITUTE(订单贴现表!$B$6,"期",""),规则表!$A$10:$B$14,2,FALSE))+订单贴现表!D7*(1-VLOOKUP(--SUBSTITUTE(订单贴现表!$B$7,"期",""),规则表!$A$10:$B$14,2,FALSE)),(D49-D50-D51*(1-VLOOKUP(--SUBSTITUTE(订单贴现表!$B$4,"期",""),规则表!$A$10:$B$14,2,FALSE))-D52*(1-VLOOKUP(--SUBSTITUTE(订单贴现表!$B$5,"期",""),规则表!$A$10:$B$14,2,FALSE))-D53*(1-VLOOKUP(--SUBSTITUTE(订单贴现表!$B$6,"期",""),规则表!$A$10:$B$14,2,FALSE)))/(1-VLOOKUP(--SUBSTITUTE(订单贴现表!$B$7,"期",""),规则表!$A$10:$B$14,2,FALSE)),TRUE,订单贴现表!D7)} -> 0 | E54: {=_xlfn.IFS(E49<=E50+E51*(1-VLOOKUP(--SUBSTITUTE(订单贴现表!$B$9,"期",""),规则表!$A$10:$B$14,2,FALSE))+E52*(1-VLOOKUP(--SUBSTITUTE(订单贴现表!$B$10,"期",""),规则表!$A$10:$B$14,2,FALSE))+E53*(1-VLOOKUP(--SUBSTITUTE(订单贴现表!$B$11,"期",""),规则表!$A$10:$B$14,2,FALSE)),0,E49<E50+E51*(1-VLOOKUP(--SUBSTITUTE(订单贴现表!$B$9,"期",""),规则表!$A$10:$B$14,2,FALSE))+E52*(1-VLOOKUP(--SUBSTITUTE(订单贴现表!$B$10,"期",""),规则表!$A$10:$B$14,2,FALSE))+E53*(1-VLOOKUP(--SUBSTITUTE(订单贴现表!$B$11,"期",""),规则表!$A$10:$B$14,2,FALSE))+订单贴现表!E12*(1-VLOOKUP(--SUBSTITUTE(订单贴现表!$B$12,"期",""),规则表!$A$10:$B$14,2,FALSE)),(E49-E50-E51*(1-VLOOKUP(--SUBSTITUTE(订单贴现表!$B$9,"期",""),规则表!$A$10:$B$14,2,FALSE))-E52*(1-VLOOKUP(--SUBSTITUTE(订单贴现表!$B$10,"期",""),规则表!$A$10:$B$14,2,FALSE))-E53*(1-VLOOKUP(--SUBSTITUTE(订单贴现表!$B$11,"期",""),规则表!$A$10:$B$14,2,FALSE)))/(1-VLOOKUP(--SUBSTITUTE(订单贴现表!$B$12,"期",""),规则表!$A$10:$B$14,2,FALSE)),TRUE,订单贴现表!E12)} -> 0 | F54: {=_xlfn.IFS(F49<=F50+F51*(1-VLOOKUP(--SUBSTITUTE(订单贴现表!$B$9,"期",""),规则表!$A$10:$B$14,2,FALSE))+F52*(1-VLOOKUP(--SUBSTITUTE(订单贴现表!$B$10,"期",""),规则表!$A$10:$B$14,2,FALSE))+F53*(1-VLOOKUP(--SUBSTITUTE(订单贴现表!$B$11,"期",""),规则表!$A$10:$B$14,2,FALSE)),0,F49<F50+F51*(1-VLOOKUP(--SUBSTITUTE(订单贴现表!$B$9,"期",""),规则表!$A$10:$B$14,2,FALSE))+F52*(1-VLOOKUP(--SUBSTITUTE(订单贴现表!$B$10,"期",""),规则表!$A$10:$B$14,2,FALSE))+F53*(1-VLOOKUP(--SUBSTITUTE(订单贴现表!$B$11,"期",""),规则表!$A$10:$B$14,2,FALSE))+订单贴现表!F12*(1-VLOOKUP(--SUBSTITUTE(订单贴现表!$B$12,"期",""),规则表!$A$10:$B$14,2,FALSE)),(F49-F50-F51*(1-VLOOKUP(--SUBSTITUTE(订单贴现表!$B$9,"期",""),规则表!$A$10:$B$14,2,FALSE))-F52*(1-VLOOKUP(--SUBSTITUTE(订单贴现表!$B$10,"期",""),规则表!$A$10:$B$14,2,FALSE))-F53*(1-VLOOKUP(--SUBSTITUTE(订单贴现表!$B$11,"期",""),规则表!$A$10:$B$14,2,FALSE)))/(1-VLOOKUP(--SUBSTITUTE(订单贴现表!$B$12,"期",""),规则表!$A$10:$B$14,2,FALSE)),TRUE,订单贴现表!F12)} -> 0 | H54: P1 | I54: 20000 | J54: 1 | K54: =IFERROR(_xlfn.MINIFS(原始订单表!L:L,原始订单表!E:E,H54)-VLOOKUP(H54,$H$53:$J$70,3,FALSE),0) -> 1 | N54: 4 | O54: {=_xlfn.IFS(O49<=O50+O51*(1-VLOOKUP(--SUBSTITUTE(订单贴现表!$B$4,"期",""),规则表!$A$10:$B$14,2,FALSE))+O52*(1-VLOOKUP(--SUBSTITUTE(订单贴现表!$B$5,"期",""),规则表!$A$10:$B$14,2,FALSE))+O53*(1-VLOOKUP(--SUBSTITUTE(订单贴现表!$B$6,"期",""),规则表!$A$10:$B$14,2,FALSE)),0,O49<O50+O51*(1-VLOOKUP(--SUBSTITUTE(订单贴现表!$B$4,"期",""),规则表!$A$10:$B$14,2,FALSE))+O52*(1-VLOOKUP(--SUBSTITUTE(订单贴现表!$B$5,"期",""),规则表!$A$10:$B$14,2,FALSE))+O53*(1-VLOOKUP(--SUBSTITUTE(订单贴现表!$B$6,"期",""),规则表!$A$10:$B$14,2,FALSE))+订单贴现表!G7*(1-VLOOKUP(--SUBSTITUTE(订单贴现表!$B$7,"期",""),规则表!$A$10:$B$14,2,FALSE)),(O49-O50-O51*(1-VLOOKUP(--SUBSTITUTE(订单贴现表!$B$4,"期",""),规则表!$A$10:$B$14,2,FALSE))-O52*(1-VLOOKUP(--SUBSTITUTE(订单贴现表!$B$5,"期",""),规则表!$A$10:$B$14,2,FALSE))-O53*(1-VLOOKUP(--SUBSTITUTE(订单贴现表!$B$6,"期",""),规则表!$A$10:$B$14,2,FALSE)))/(1-VLOOKUP(--SUBSTITUTE(订单贴现表!$B$7,"期",""),规则表!$A$10:$B$14,2,FALSE)),TRUE,订单贴现表!G7)} -> 0 | P54: {=_xlfn.IFS(P49<=P50+P51*(1-VLOOKUP(--SUBSTITUTE(订单贴现表!$B$4,"期",""),规则表!$A$10:$B$14,2,FALSE))+P52*(1-VLOOKUP(--SUBSTITUTE(订单贴现表!$B$5,"期",""),规则表!$A$10:$B$14,2,FALSE))+P53*(1-VLOOKUP(--SUBSTITUTE(订单贴现表!$B$6,"期",""),规则表!$A$10:$B$14,2,FALSE)),0,P49<P50+P51*(1-VLOOKUP(--SUBSTITUTE(订单贴现表!$B$4,"期",""),规则表!$A$10:$B$14,2,FALSE))+P52*(1-VLOOKUP(--SUBSTITUTE(订单贴现表!$B$5,"期",""),规则表!$A$10:$B$14,2,FALSE))+P53*(1-VLOOKUP(--SUBSTITUTE(订单贴现表!$B$6,"期",""),规则表!$A$10:$B$14,2,FALSE))+订单贴现表!H7*(1-VLOOKUP(--SUBSTITUTE(订单贴现表!$B$7,"期",""),规则表!$A$10:$B$14,2,FALSE)),(P49-P50-P51*(1-VLOOKUP(--SUBSTITUTE(订单贴现表!$B$4,"期",""),规则表!$A$10:$B$14,2,FALSE))-P52*(1-VLOOKUP(--SUBSTITUTE(订单贴现表!$B$5,"期",""),规则表!$A$10:$B$14,2,FALSE))-P53*(1-VLOOKUP(--SUBSTITUTE(订单贴现表!$B$6,"期",""),规则表!$A$10:$B$14,2,FALSE)))/(1-VLOOKUP(--SUBSTITUTE(订单贴现表!$B$7,"期",""),规则表!$A$10:$B$14,2,FALSE)),TRUE,订单贴现表!H7)} -> 0 | Q54: {=_xlfn.IFS(Q49<=Q50+Q51*(1-VLOOKUP(--SUBSTITUTE(订单贴现表!$B$4,"期",""),规则表!$A$10:$B$14,2,FALSE))+Q52*(1-VLOOKUP(--SUBSTITUTE(订单贴现表!$B$5,"期",""),规则表!$A$10:$B$14,2,FALSE))+Q53*(1-VLOOKUP(--SUBSTITUTE(订单贴现表!$B$6,"期",""),规则表!$A$10:$B$14,2,FALSE)),0,Q49<Q50+Q51*(1-VLOOKUP(--SUBSTITUTE(订单贴现表!$B$4,"期",""),规则表!$A$10:$B$14,2,FALSE))+Q52*(1-VLOOKUP(--SUBSTITUTE(订单贴现表!$B$5,"期",""),规则表!$A$10:$B$14,2,FALSE))+Q53*(1-VLOOKUP(--SUBSTITUTE(订单贴现表!$B$6,"期",""),规则表!$A$10:$B$14,2,FALSE))+订单贴现表!I7*(1-VLOOKUP(--SUBSTITUTE(订单贴现表!$B$7,"期",""),规则表!$A$10:$B$14,2,FALSE)),(Q49-Q50-Q51*(1-VLOOKUP(--SUBSTITUTE(订单贴现表!$B$4,"期",""),规则表!$A$10:$B$14,2,FALSE))-Q52*(1-VLOOKUP(--SUBSTITUTE(订单贴现表!$B$5,"期",""),规则表!$A$10:$B$14,2,FALSE))-Q53*(1-VLOOKUP(--SUBSTITUTE(订单贴现表!$B$6,"期",""),规则表!$A$10:$B$14,2,FALSE)))/(1-VLOOKUP(--SUBSTITUTE(订单贴现表!$B$7,"期",""),规则表!$A$10:$B$14,2,FALSE)),TRUE,订单贴现表!I7)} -> 0 | R54: {=_xlfn.IFS(R49<=R50+R51*(1-VLOOKUP(--SUBSTITUTE(订单贴现表!$B$4,"期",""),规则表!$A$10:$B$14,2,FALSE))+R52*(1-VLOOKUP(--SUBSTITUTE(订单贴现表!$B$5,"期",""),规则表!$A$10:$B$14,2,FALSE))+R53*(1-VLOOKUP(--SUBSTITUTE(订单贴现表!$B$6,"期",""),规则表!$A$10:$B$14,2,FALSE)),0,R49<R50+R51*(1-VLOOKUP(--SUBSTITUTE(订单贴现表!$B$4,"期",""),规则表!$A$10:$B$14,2,FALSE))+R52*(1-VLOOKUP(--SUBSTITUTE(订单贴现表!$B$5,"期",""),规则表!$A$10:$B$14,2,FALSE))+R53*(1-VLOOKUP(--SUBSTITUTE(订单贴现表!$B$6,"期",""),规则表!$A$10:$B$14,2,FALSE))+订单贴现表!J7*(1-VLOOKUP(--SUBSTITUTE(订单贴现表!$B$7,"期",""),规则表!$A$10:$B$14,2,FALSE)),(R49-R50-R51*(1-VLOOKUP(--SUBSTITUTE(订单贴现表!$B$4,"期",""),规则表!$A$10:$B$14,2,FALSE))-R52*(1-VLOOKUP(--SUBSTITUTE(订单贴现表!$B$5,"期",""),规则表!$A$10:$B$14,2,FALSE))-R53*(1-VLOOKUP(--SUBSTITUTE(订单贴现表!$B$6,"期",""),规则表!$A$10:$B$14,2,FALSE)))/(1-VLOOKUP(--SUBSTITUTE(订单贴现表!$B$7,"期",""),规则表!$A$10:$B$14,2,FALSE)),TRUE,订单贴现表!J7)} -> 0 | Z54: 4 | AA54: {=_xlfn.IFS(AA49<=AA50+AA51*(1-VLOOKUP(--SUBSTITUTE(订单贴现表!$B$4,"期",""),规则表!$A$10:$B$14,2,FALSE))+AA52*(1-VLOOKUP(--SUBSTITUTE(订单贴现表!$B$5,"期",""),规则表!$A$10:$B$14,2,FALSE))+AA53*(1-VLOOKUP(--SUBSTITUTE(订单贴现表!$B$6,"期",""),规则表!$A$10:$B$14,2,FALSE)),0,AA49<AA50+AA51*(1-VLOOKUP(--SUBSTITUTE(订单贴现表!$B$4,"期",""),规则表!$A$10:$B$14,2,FALSE))+AA52*(1-VLOOKUP(--SUBSTITUTE(订单贴现表!$B$5,"期",""),规则表!$A$10:$B$14,2,FALSE))+AA53*(1-VLOOKUP(--SUBSTITUTE(订单贴现表!$B$6,"期",""),规则表!$A$10:$B$14,2,FALSE))+订单贴现表!K7*(1-VLOOKUP(--SUBSTITUTE(订单贴现表!$B$7,"期",""),规则表!$A$10:$B$14,2,FALSE)),(AA49-AA50-AA51*(1-VLOOKUP(--SUBSTITUTE(订单贴现表!$B$4,"期",""),规则表!$A$10:$B$14,2,FALSE))-AA52*(1-VLOOKUP(--SUBSTITUTE(订单贴现表!$B$5,"期",""),规则表!$A$10:$B$14,2,FALSE))-AA53*(1-VLOOKUP(--SUBSTITUTE(订单贴现表!$B$6,"期",""),规则表!$A$10:$B$14,2,FALSE)))/(1-VLOOKUP(--SUBSTITUTE(订单贴现表!$B$7,"期",""),规则表!$A$10:$B$14,2,FALSE)),TRUE,订单贴现表!K7)} -> 0 | AB54: {=_xlfn.IFS(AB49<=AB50+AB51*(1-VLOOKUP(--SUBSTITUTE(订单贴现表!$B$4,"期",""),规则表!$A$10:$B$14,2,FALSE))+AB52*(1-VLOOKUP(--SUBSTITUTE(订单贴现表!$B$5,"期",""),规则表!$A$10:$B$14,2,FALSE))+AB53*(1-VLOOKUP(--SUBSTITUTE(订单贴现表!$B$6,"期",""),规则表!$A$10:$B$14,2,FALSE)),0,AB49<AB50+AB51*(1-VLOOKUP(--SUBSTITUTE(订单贴现表!$B$4,"期",""),规则表!$A$10:$B$14,2,FALSE))+AB52*(1-VLOOKUP(--SUBSTITUTE(订单贴现表!$B$5,"期",""),规则表!$A$10:$B$14,2,FALSE))+AB53*(1-VLOOKUP(--SUBSTITUTE(订单贴现表!$B$6,"期",""),规则表!$A$10:$B$14,2,FALSE))+订单贴现表!L7*(1-VLOOKUP(--SUBSTITUTE(订单贴现表!$B$7,"期",""),规则表!$A$10:$B$14,2,FALSE)),(AB49-AB50-AB51*(1-VLOOKUP(--SUBSTITUTE(订单贴现表!$B$4,"期",""),规则表!$A$10:$B$14,2,FALSE))-AB52*(1-VLOOKUP(--SUBSTITUTE(订单贴现表!$B$5,"期",""),规则表!$A$10:$B$14,2,FALSE))-AB53*(1-VLOOKUP(--SUBSTITUTE(订单贴现表!$B$6,"期",""),规则表!$A$10:$B$14,2,FALSE)))/(1-VLOOKUP(--SUBSTITUTE(订单贴现表!$B$7,"期",""),规则表!$A$10:$B$14,2,FALSE)),TRUE,订单贴现表!L7)} -> 0 | AC54: {=_xlfn.IFS(AC49<=AC50+AC51*(1-VLOOKUP(--SUBSTITUTE(订单贴现表!$B$4,"期",""),规则表!$A$10:$B$14,2,FALSE))+AC52*(1-VLOOKUP(--SUBSTITUTE(订单贴现表!$B$5,"期",""),规则表!$A$10:$B$14,2,FALSE))+AC53*(1-VLOOKUP(--SUBSTITUTE(订单贴现表!$B$6,"期",""),规则表!$A$10:$B$14,2,FALSE)),0,AC49<AC50+AC51*(1-VLOOKUP(--SUBSTITUTE(订单贴现表!$B$4,"期",""),规则表!$A$10:$B$14,2,FALSE))+AC52*(1-VLOOKUP(--SUBSTITUTE(订单贴现表!$B$5,"期",""),规则表!$A$10:$B$14,2,FALSE))+AC53*(1-VLOOKUP(--SUBSTITUTE(订单贴现表!$B$6,"期",""),规则表!$A$10:$B$14,2,FALSE))+订单贴现表!M7*(1-VLOOKUP(--SUBSTITUTE(订单贴现表!$B$7,"期",""),规则表!$A$10:$B$14,2,FALSE)),(AC49-AC50-AC51*(1-VLOOKUP(--SUBSTITUTE(订单贴现表!$B$4,"期",""),规则表!$A$10:$B$14,2,FALSE))-AC52*(1-VLOOKUP(--SUBSTITUTE(订单贴现表!$B$5,"期",""),规则表!$A$10:$B$14,2,FALSE))-AC53*(1-VLOOKUP(--SUBSTITUTE(订单贴现表!$B$6,"期",""),规则表!$A$10:$B$14,2,FALSE)))/(1-VLOOKUP(--SUBSTITUTE(订单贴现表!$B$7,"期",""),规则表!$A$10:$B$14,2,FALSE)),TRUE,订单贴现表!M7)} -> 0 | AD54: {=_xlfn.IFS(AD49<=AD50+AD51*(1-VLOOKUP(--SUBSTITUTE(订单贴现表!$B$4,"期",""),规则表!$A$10:$B$14,2,FALSE))+AD52*(1-VLOOKUP(--SUBSTITUTE(订单贴现表!$B$5,"期",""),规则表!$A$10:$B$14,2,FALSE))+AD53*(1-VLOOKUP(--SUBSTITUTE(订单贴现表!$B$6,"期",""),规则表!$A$10:$B$14,2,FALSE)),0,AD49<AD50+AD51*(1-VLOOKUP(--SUBSTITUTE(订单贴现表!$B$4,"期",""),规则表!$A$10:$B$14,2,FALSE))+AD52*(1-VLOOKUP(--SUBSTITUTE(订单贴现表!$B$5,"期",""),规则表!$A$10:$B$14,2,FALSE))+AD53*(1-VLOOKUP(--SUBSTITUTE(订单贴现表!$B$6,"期",""),规则表!$A$10:$B$14,2,FALSE))+订单贴现表!N7*(1-VLOOKUP(--SUBSTITUTE(订单贴现表!$B$7,"期",""),规则表!$A$10:$B$14,2,FALSE)),(AD49-AD50-AD51*(1-VLOOKUP(--SUBSTITUTE(订单贴现表!$B$4,"期",""),规则表!$A$10:$B$14,2,FALSE))-AD52*(1-VLOOKUP(--SUBSTITUTE(订单贴现表!$B$5,"期",""),规则表!$A$10:$B$14,2,FALSE))-AD53*(1-VLOOKUP(--SUBSTITUTE(订单贴现表!$B$6,"期",""),规则表!$A$10:$B$14,2,FALSE)))/(1-VLOOKUP(--SUBSTITUTE(订单贴现表!$B$7,"期",""),规则表!$A$10:$B$14,2,FALSE)),TRUE,订单贴现表!N7)} -> 0 | AJ54: 4 | AK54: {=_xlfn.IFS(AK49<=AK50+AK51*(1-VLOOKUP(--SUBSTITUTE(订单贴现表!$B$4,"期",""),规则表!$A$10:$B$14,2,FALSE))+AK52*(1-VLOOKUP(--SUBSTITUTE(订单贴现表!$B$5,"期",""),规则表!$A$10:$B$14,2,FALSE))+AK53*(1-VLOOKUP(--SUBSTITUTE(订单贴现表!$B$6,"期",""),规则表!$A$10:$B$14,2,FALSE)),0,AK49<AK50+AK51*(1-VLOOKUP(--SUBSTITUTE(订单贴现表!$B$4,"期",""),规则表!$A$10:$B$14,2,FALSE))+AK52*(1-VLOOKUP(--SUBSTITUTE(订单贴现表!$B$5,"期",""),规则表!$A$10:$B$14,2,FALSE))+AK53*(1-VLOOKUP(--SUBSTITUTE(订单贴现表!$B$6,"期",""),规则表!$A$10:$B$14,2,FALSE))+订单贴现表!O7*(1-VLOOKUP(--SUBSTITUTE(订单贴现表!$B$7,"期",""),规则表!$A$10:$B$14,2,FALSE)),(AK49-AK50-AK51*(1-VLOOKUP(--SUBSTITUTE(订单贴现表!$B$4,"期",""),规则表!$A$10:$B$14,2,FALSE))-AK52*(1-VLOOKUP(--SUBSTITUTE(订单贴现表!$B$5,"期",""),规则表!$A$10:$B$14,2,FALSE))-AK53*(1-VLOOKUP(--SUBSTITUTE(订单贴现表!$B$6,"期",""),规则表!$A$10:$B$14,2,FALSE)))/(1-VLOOKUP(--SUBSTITUTE(订单贴现表!$B$7,"期",""),规则表!$A$10:$B$14,2,FALSE)),TRUE,订单贴现表!O7)} -> 0 | AL54: {=_xlfn.IFS(AL49<=AL50+AL51*(1-VLOOKUP(--SUBSTITUTE(订单贴现表!$B$4,"期",""),规则表!$A$10:$B$14,2,FALSE))+AL52*(1-VLOOKUP(--SUBSTITUTE(订单贴现表!$B$5,"期",""),规则表!$A$10:$B$14,2,FALSE))+AL53*(1-VLOOKUP(--SUBSTITUTE(订单贴现表!$B$6,"期",""),规则表!$A$10:$B$14,2,FALSE)),0,AL49<AL50+AL51*(1-VLOOKUP(--SUBSTITUTE(订单贴现表!$B$4,"期",""),规则表!$A$10:$B$14,2,FALSE))+AL52*(1-VLOOKUP(--SUBSTITUTE(订单贴现表!$B$5,"期",""),规则表!$A$10:$B$14,2,FALSE))+AL53*(1-VLOOKUP(--SUBSTITUTE(订单贴现表!$B$6,"期",""),规则表!$A$10:$B$14,2,FALSE))+订单贴现表!P7*(1-VLOOKUP(--SUBSTITUTE(订单贴现表!$B$7,"期",""),规则表!$A$10:$B$14,2,FALSE)),(AL49-AL50-AL51*(1-VLOOKUP(--SUBSTITUTE(订单贴现表!$B$4,"期",""),规则表!$A$10:$B$14,2,FALSE))-AL52*(1-VLOOKUP(--SUBSTITUTE(订单贴现表!$B$5,"期",""),规则表!$A$10:$B$14,2,FALSE))-AL53*(1-VLOOKUP(--SUBSTITUTE(订单贴现表!$B$6,"期",""),规则表!$A$10:$B$14,2,FALSE)))/(1-VLOOKUP(--SUBSTITUTE(订单贴现表!$B$7,"期",""),规则表!$A$10:$B$14,2,FALSE)),TRUE,订单贴现表!P7)} -> 0 | AM54: {=_xlfn.IFS(AM49<=AM50+AM51*(1-VLOOKUP(--SUBSTITUTE(订单贴现表!$B$4,"期",""),规则表!$A$10:$B$14,2,FALSE))+AM52*(1-VLOOKUP(--SUBSTITUTE(订单贴现表!$B$5,"期",""),规则表!$A$10:$B$14,2,FALSE))+AM53*(1-VLOOKUP(--SUBSTITUTE(订单贴现表!$B$6,"期",""),规则表!$A$10:$B$14,2,FALSE)),0,AM49<AM50+AM51*(1-VLOOKUP(--SUBSTITUTE(订单贴现表!$B$4,"期",""),规则表!$A$10:$B$14,2,FALSE))+AM52*(1-VLOOKUP(--SUBSTITUTE(订单贴现表!$B$5,"期",""),规则表!$A$10:$B$14,2,FALSE))+AM53*(1-VLOOKUP(--SUBSTITUTE(订单贴现表!$B$6,"期",""),规则表!$A$10:$B$14,2,FALSE))+订单贴现表!Q7*(1-VLOOKUP(--SUBSTITUTE(订单贴现表!$B$7,"期",""),规则表!$A$10:$B$14,2,FALSE)),(AM49-AM50-AM51*(1-VLOOKUP(--SUBSTITUTE(订单贴现表!$B$4,"期",""),规则表!$A$10:$B$14,2,FALSE))-AM52*(1-VLOOKUP(--SUBSTITUTE(订单贴现表!$B$5,"期",""),规则表!$A$10:$B$14,2,FALSE))-AM53*(1-VLOOKUP(--SUBSTITUTE(订单贴现表!$B$6,"期",""),规则表!$A$10:$B$14,2,FALSE)))/(1-VLOOKUP(--SUBSTITUTE(订单贴现表!$B$7,"期",""),规则表!$A$10:$B$14,2,FALSE)),TRUE,订单贴现表!Q7)} -> 0 | AN54: {=_xlfn.IFS(AN49<=AN50+AN51*(1-VLOOKUP(--SUBSTITUTE(订单贴现表!$B$4,"期",""),规则表!$A$10:$B$14,2,FALSE))+AN52*(1-VLOOKUP(--SUBSTITUTE(订单贴现表!$B$5,"期",""),规则表!$A$10:$B$14,2,FALSE))+AN53*(1-VLOOKUP(--SUBSTITUTE(订单贴现表!$B$6,"期",""),规则表!$A$10:$B$14,2,FALSE)),0,AN49<AN50+AN51*(1-VLOOKUP(--SUBSTITUTE(订单贴现表!$B$4,"期",""),规则表!$A$10:$B$14,2,FALSE))+AN52*(1-VLOOKUP(--SUBSTITUTE(订单贴现表!$B$5,"期",""),规则表!$A$10:$B$14,2,FALSE))+AN53*(1-VLOOKUP(--SUBSTITUTE(订单贴现表!$B$6,"期",""),规则表!$A$10:$B$14,2,FALSE))+订单贴现表!R7*(1-VLOOKUP(--SUBSTITUTE(订单贴现表!$B$7,"期",""),规则表!$A$10:$B$14,2,FALSE)),(AN49-AN50-AN51*(1-VLOOKUP(--SUBSTITUTE(订单贴现表!$B$4,"期",""),规则表!$A$10:$B$14,2,FALSE))-AN52*(1-VLOOKUP(--SUBSTITUTE(订单贴现表!$B$5,"期",""),规则表!$A$10:$B$14,2,FALSE))-AN53*(1-VLOOKUP(--SUBSTITUTE(订单贴现表!$B$6,"期",""),规则表!$A$10:$B$14,2,FALSE)))/(1-VLOOKUP(--SUBSTITUTE(订单贴现表!$B$7,"期",""),规则表!$A$10:$B$14,2,FALSE)),TRUE,订单贴现表!R7)} -> 0
A55: 缺少金额 | C55: =IF((C49-C50-C51*(1-规则表!$B$11)-C52*(1-规则表!$B$12)-C53*(1-规则表!$B$13)-C54*(1-规则表!$B$14))>0,C49-C50-C51*(1-规则表!$B$11)-C52*(1-规则表!$B$12)-C53*(1-规则表!$B$13)-C54*(1-规则表!$B$14),0) -> 0 | D55: =IF((D49-D50-D51*(1-规则表!$B$11)-D52*(1-规则表!$B$12)-D53*(1-规则表!$B$13)-D54*(1-规则表!$B$14))>0,D49-D50-D51*(1-规则表!$B$11)-D52*(1-规则表!$B$12)-D53*(1-规则表!$B$13)-D54*(1-规则表!$B$14),0) -> 0 | E55: =IF((E49-E50-E51*(1-规则表!$B$11)-E52*(1-规则表!$B$12)-E53*(1-规则表!$B$13)-E54*(1-规则表!$B$14))>0,E49-E50-E51*(1-规则表!$B$11)-E52*(1-规则表!$B$12)-E53*(1-规则表!$B$13)-E54*(1-规则表!$B$14),0) -> 0 | F55: =IF((F49-F50-F51*(1-规则表!$B$11)-F52*(1-规则表!$B$12)-F53*(1-规则表!$B$13)-F54*(1-规则表!$B$14))>0,F49-F50-F51*(1-规则表!$B$11)-F52*(1-规则表!$B$12)-F53*(1-规则表!$B$13)-F54*(1-规则表!$B$14),0) -> 0 | H55: P2 | I55: 40000 | J55: 2 | K55: =IFERROR(_xlfn.MINIFS(原始订单表!L:L,原始订单表!E:E,H55)-VLOOKUP(H55,$H$53:$J$70,3,FALSE),0) -> 0 | M55: 缺少金额 | O55: =IF((O49-O50-O51*(1-规则表!$B$11)-O52*(1-规则表!$B$12)-O53*(1-规则表!$B$13)-O54*(1-规则表!$B$14))>0,O49-O50-O51*(1-规则表!$B$11)-O52*(1-规则表!$B$12)-O53*(1-规则表!$B$13)-O54*(1-规则表!$B$14),0) -> 0 | P55: =IF((P49-P50-P51*(1-规则表!$B$11)-P52*(1-规则表!$B$12)-P53*(1-规则表!$B$13)-P54*(1-规则表!$B$14))>0,P49-P50-P51*(1-规则表!$B$11)-P52*(1-规则表!$B$12)-P53*(1-规则表!$B$13)-P54*(1-规则表!$B$14),0) -> 0 | Q55: =IF((Q49-Q50-Q51*(1-规则表!$B$11)-Q52*(1-规则表!$B$12)-Q53*(1-规则表!$B$13)-Q54*(1-规则表!$B$14))>0,Q49-Q50-Q51*(1-规则表!$B$11)-Q52*(1-规则表!$B$12)-Q53*(1-规则表!$B$13)-Q54*(1-规则表!$B$14),0) -> 0 | R55: =IF((R49-R50-R51*(1-规则表!$B$11)-R52*(1-规则表!$B$12)-R53*(1-规则表!$B$13)-R54*(1-规则表!$B$14))>0,R49-R50-R51*(1-规则表!$B$11)-R52*(1-规则表!$B$12)-R53*(1-规则表!$B$13)-R54*(1-规则表!$B$14),0) -> 0 | Y55: 缺少金额 | AA55: =IF((AA49-AA50-AA51*(1-规则表!$B$11)-AA52*(1-规则表!$B$12)-AA53*(1-规则表!$B$13)-AA54*(1-规则表!$B$14))>0,AA49-AA50-AA51*(1-规则表!$B$11)-AA52*(1-规则表!$B$12)-AA53*(1-规则表!$B$13)-AA54*(1-规则表!$B$14),0) -> 0 | AB55: =IF((AB49-AB50-AB51*(1-规则表!$B$11)-AB52*(1-规则表!$B$12)-AB53*(1-规则表!$B$13)-AB54*(1-规则表!$B$14))>0,AB49-AB50-AB51*(1-规则表!$B$11)-AB52*(1-规则表!$B$12)-AB53*(1-规则表!$B$13)-AB54*(1-规则表!$B$14),0) -> 0 | AC55: =IF((AC49-AC50-AC51*(1-规则表!$B$11)-AC52*(1-规则表!$B$12)-AC53*(1-规则表!$B$13)-AC54*(1-规则表!$B$14))>0,AC49-AC50-AC51*(1-规则表!$B$11)-AC52*(1-规则表!$B$12)-AC53*(1-规则表!$B$13)-AC54*(1-规则表!$B$14),0) -> 0 | AD55: =IF((AD49-AD50-AD51*(1-规则表!$B$11)-AD52*(1-规则表!$B$12)-AD53*(1-规则表!$B$13)-AD54*(1-规则表!$B$14))>0,AD49-AD50-AD51*(1-规则表!$B$11)-AD52*(1-规则表!$B$12)-AD53*(1-规则表!$B$13)-AD54*(1-规则表!$B$14),0) -> 0 | AI55: 缺少金额 | AK55: =IF((AK49-AK50-AK51*(1-规则表!$B$11)-AK52*(1-规则表!$B$12)-AK53*(1-规则表!$B$13)-AK54*(1-规则表!$B$14))>0,AK49-AK50-AK51*(1-规则表!$B$11)-AK52*(1-规则表!$B$12)-AK53*(1-规则表!$B$13)-AK54*(1-规则表!$B$14),0) -> 0 | AL55: =IF((AL49-AL50-AL51*(1-规则表!$B$11)-AL52*(1-规则表!$B$12)-AL53*(1-规则表!$B$13)-AL54*(1-规则表!$B$14))>0,AL49-AL50-AL51*(1-规则表!$B$11)-AL52*(1-规则表!$B$12)-AL53*(1-规则表!$B$13)-AL54*(1-规则表!$B$14),0) -> 0 | AM55: =IF((AM49-AM50-AM51*(1-规则表!$B$11)-AM52*(1-规则表!$B$12)-AM53*(1-规则表!$B$13)-AM54*(1-规则表!$B$14))>0,AM49-AM50-AM51*(1-规则表!$B$11)-AM52*(1-规则表!$B$12)-AM53*(1-规则表!$B$13)-AM54*(1-规则表!$B$14),0) -> 0 | AN55: =IF((AN49-AN50-AN51*(1-规则表!$B$11)-AN52*(1-规则表!$B$12)-AN53*(1-规则表!$B$13)-AN54*(1-规则表!$B$14))>0,AN49-AN50-AN51*(1-规则表!$B$11)-AN52*(1-规则表!$B$12)-AN53*(1-规则表!$B$13)-AN54*(1-规则表!$B$14),0) -> 0
H56: P3 | I56: 60000 | J56: 4 | K56: =IFERROR(_xlfn.MINIFS(原始订单表!L:L,原始订单表!E:E,H56)-VLOOKUP(H56,$H$53:$J$70,3,FALSE),0) -> 1
H57: P4 | I57: 90000 | J57: 6 | K57: =IFERROR(_xlfn.MINIFS(原始订单表!L:L,原始订单表!E:E,H57)-VLOOKUP(H57,$H$53:$J$70,3,FALSE),0) -> -1
K58: =IFERROR(_xlfn.MINIFS(原始订单表!L:L,原始订单表!E:E,H58)-VLOOKUP(H58,$H$53:$J$70,3,FALSE),0) -> 0
H60: {=_xlfn.TOCOL(_xlfn.TAKE(_xlfn.UNIQUE(原始订单表!$D$1:$D$1000),COUNTA(_xlfn.UNIQUE(原始订单表!$D$1:$D$1000))+1),1)} -> 市场 | I60: 消耗金钱 (元) | J60: 消耗时间 (季) | K60: {=MIN(_xlfn._xlws.FILTER(原始订单表!$L:$L,原始订单表!$E:$E=H60,0))-VLOOKUP(H60,$H$53:$J$70,3,FALSE)} -> #VALUE!
H61: 国内市场 | I61: 20000 | J61: 1 | K61: =IFERROR(_xlfn.MINIFS(原始订单表!L:L,原始订单表!D:D,H61)-VLOOKUP(H61,$H$53:$J$70,3,FALSE),0) -> 1
H62: 亚洲市场 | I62: 40000 | J62: 2 | K62: =IFERROR(_xlfn.MINIFS(原始订单表!L:L,原始订单表!D:D,H62)-VLOOKUP(H62,$H$53:$J$70,3,FALSE),0) -> 1
H63: 欧洲市场 | I63: 80000 | J63: 4 | K63: =IFERROR(_xlfn.MINIFS(原始订单表!L:L,原始订单表!D:D,H63)-VLOOKUP(H63,$H$53:$J$70,3,FALSE),0) -> 1
H64: 美洲市场 | I64: 100000 | J64: 4 | K64: =IFERROR(_xlfn.MINIFS(原始订单表!L:L,原始订单表!D:D,H64)-VLOOKUP(H64,$H$53:$J$70,3,FALSE),0) -> 2
K65: =IFERROR(_xlfn.MINIFS(原始订单表!L:L,原始订单表!D:D,H65)-VLOOKUP(H65,$H$53:$J$70,3,FALSE),0) -> 0
H67: {=_xlfn.TOCOL(_xlfn.TAKE(_xlfn.UNIQUE(原始订单表!K1:K1000),COUNTA(_xlfn.UNIQUE(原始订单表!K1:K1000))+1),1)} -> 认证 | I67: 消耗金钱 (元) | J67: 消耗时间 (季) | K67: =_xlfn.MINIFS(原始订单表!L:L,原始订单表!D:D,H67)-VLOOKUP(H67,$H$53:$J$72,3,FALSE) -> #VALUE!
I68: 40000 | J68: 1 | K68: =IFERROR(_xlfn.MINIFS(原始订单表!L:L,原始订单表!K:K,H68)-VLOOKUP(H68,$H$53:$J$70,3,FALSE),0) -> 1
H69: IS09000 | I69: 60000 | J69: 2 | K69: =IFERROR(_xlfn.MINIFS(原始订单表!L:L,原始订单表!K:K,H69)-VLOOKUP(H69,$H$53:$J$70,3,FALSE),0) -> 1
H70: IS014000 | I70: 100000 | J70: 4 | K70: =IFERROR(_xlfn.MINIFS(原始订单表!L:L,原始订单表!K:K,H70)-VLOOKUP(H70,$H$53:$J$70,3,FALSE),0) -> 1
H71: IS021000 | I71: 20001 | J71: 5 | K71: =IFERROR(_xlfn.MINIFS(原始订单表!L:L,原始订单表!K:K,H71)-VLOOKUP(H71,$H$53:$J$70,3,FALSE),0) -> 0
I72: 20002 | J72: 6 | K72: =IFERROR(_xlfn.MINIFS(原始订单表!L:L,原始订单表!K:K,H72)-VLOOKUP(H72,$H$53:$J$70,3,FALSE),0) -> 0
T73: 囤货表（智能线）
T74: 产品 | U74: 2.2 | V74: 2.3 | W74: 2.4
B75: 涨薪 | C75: 激励 | T75: =S27 -> P1 | U75: =INT(MIN($Q$46,$P$46,$V$23)/((材料表!H47+$U$81*0.75)*材料表!$N$44)) -> 235 | V75: =INT(MIN($Q$46,$V$23)/((材料表!H47+$V$81*0.75)*材料表!$N$44)) -> 54 | W75: =INT($V$23/(材料表!H47*材料表!$N$44)) -> 0
T76: =S28 -> P2 | U76: =INT(MIN($Q$46,$P$46,$V$23)/((材料表!H48+$U$81*0.75)*材料表!$N$44)) -> 130 | V76: =INT(MIN($Q$46,$V$23)/((材料表!H48+$V$81*0.75)*材料表!$N$44)) -> 50 | W76: =INT($V$23/(材料表!H48*材料表!$N$44)) -> 0
T77: =S29 -> P3 | U77: =INT(MIN($Q$46,$P$46,$V$23)/((材料表!H49+$U$81*0.75)*材料表!$N$44)) -> 78 | V77: =INT(MIN($Q$46,$V$23)/((材料表!H49+$V$81*0.75)*材料表!$N$44)) -> 45 | W77: =INT($V$23/(材料表!H49*材料表!$N$44)) -> 0
T78: =S30 -> P4 | U78: =INT(MIN($Q$46,$P$46,$V$23)/((材料表!H50+$U$81*0.75)*材料表!$N$44)) -> 51 | V78: =INT(MIN($Q$46,$V$23)/((材料表!H50+$V$81*0.75)*材料表!$N$44)) -> 40 | W78: =INT($V$23/(材料表!H50*材料表!$N$44)) -> 0
T79: =S31 -> 0 | U79: =INT(MIN($Q$46,$P$46,$V$23)/((材料表!H51+$U$81*0.75)*材料表!$N$44)) -> #DIV/0! | V79: =INT(MIN($Q$46,$V$23)/((材料表!H51+$V$81*0.75)*材料表!$N$44)) -> 60 | W79: =INT($V$23/(材料表!H51*材料表!$N$44)) -> #DIV/0!
U80: 转产产线原先单个产品利润 | V80: 转产产线原先单个产品利润
V81: 6000
B82: 第一年做方案需考虑的内容
B83: 1.全智能开，还是全自动开 2.智能开划算还是自动开划算（2.1是否16智能） 3.涨薪划算还是激励划算 4.转产划算还是开线划算 5.是否要全激励 6.要不要全开自动线
B90: 1.看工人数量 2.看贴现有没有错误 3.原料能不能定出来 4.转产费用和涨薪费用

Sheet 生产建设
A1: 涨薪 | B1: 激励 | I1: 第一年 | M1: 第二年 | Q1: 第三年 | U1: 第四年
I2: 1 | J2: 2 | K2: 3 | L2: 4 | M2: 1 | N2: 2 | O2: 3 | P2: 4 | Q2: 1 | R2: 2 | S2: 3 | T2: 4 | U2: 1 | V2: 2 | W2: 3 | X2: 4
A3: 涨薪方案选择 | I3: 激励 | J3: 激励 | K3: 激励 | L3: 激励 | M3: 激励 | N3: 激励 | O3: 激励 | P3: 激励 | Q3: 激励 | R3: 激励 | S3: 激励 | T3: 激励 | U3: 激励 | V3: 激励 | W3: 激励 | X3: 激励
A4: 建设计划 | B4: 传统线 | C4: P1
C5: P2
C6: P3
C7: P4 | I7: 10
C8: P5
B9: 自动线 | C9: P1
C10: P2
C11: P3
C12: P4
C13: P5
B14: 智能线 | C14: P1
C15: P2
C16: P3
C17: P4
C18: P5
A20: 拆线计划 | B20: 传统线 | C20: P1
C21: P2
C22: P3
C23: P4
C24: P5
B25: 自动线 | C25: P1
C26: P2
C27: P3
C28: P4
C29: P5
B30: 智能线 | C30: P1
C31: P2
C32: P3
C33: P4
C34: P5
A36: 转产计划 | B36: 传统线 | C36: P1
C37: P2
C38: P3
C39: P4
C40: P5
B41: 自动线 | C41: P1
C42: P2
C43: P3
C44: P4
C45: P5
B46: 智能线 | C46: P1
C47: P2
C48: P3
C49: P4
C50: P5
C51: 建设费用 | I51: {=SUMPRODUCT(I60:I62,规则表!$B$17:$B$19)} -> 1000000 | J51: {=SUMPRODUCT(J60:J62,规则表!$B$17:$B$19)} -> 0 | K51: {=SUMPRODUCT(K60:K62,规则表!$B$17:$B$19)} -> 0 | L51: {=SUMPRODUCT(L60:L62,规则表!$B$17:$B$19)} -> 0 | M51: {=SUMPRODUCT(M60:M62,规则表!$B$17:$B$19)} -> 0 | N51: {=SUMPRODUCT(N60:N62,规则表!$B$17:$B$19)} -> 0 | O51: {=SUMPRODUCT(O60:O62,规则表!$B$17:$B$19)} -> 0 | P51: {=SUMPRODUCT(P60:P62,规则表!$B$17:$B$19)} -> 0 | ... X51: {=SUMPRODUCT(X60:X62,规则表!$B$17:$B$19)} -> 0
C52: 维修费用 | M52: {=SUMPRODUCT(INDEX($H$60:$X$60,MAX(COLUMN()-10-规则表!$C$17,1))*规则表!$I$17)-SUM(OFFSET(M64,0,-3,1,4))*规则表!$I$17-SUM(OFFSET(M65,0,-3,1,4))*规则表!$I$18-SUM(OFFSET(M66,0,-3,1,4))*规则表!$I$19+SUMPRODUCT(INDEX($H$61:$X$61,MAX(COLUMN()-10-规则表!$C$18,1))*规则表!$I$18)+SUMPRODUCT(INDEX($H$62:$X$62,MAX(COLUMN()-10-规则表!$C$19,1))*规则表!$I$19)} -> 0 | N52: {=SUMPRODUCT(INDEX($H$60:$X$60,MAX(COLUMN()-10-规则表!$C$17,1))*规则表!$I$17)-SUM(OFFSET(N64,0,-3,1,4))*规则表!$I$17-SUM(OFFSET(N65,0,-3,1,4))*规则表!$I$18-SUM(OFFSET(N66,0,-3,1,4))*规则表!$I$19+SUMPRODUCT(INDEX($H$61:$X$61,MAX(COLUMN()-10-规则表!$C$18,1))*规则表!$I$18)+SUMPRODUCT(INDEX($H$62:$X$62,MAX(COLUMN()-10-规则表!$C$19,1))*规则表!$I$19)} -> 0 | O52: {=SUMPRODUCT(INDEX($H$60:$X$60,MAX(COLUMN()-10-规则表!$C$17,1))*规则表!$I$17)-SUM(OFFSET(O64,0,-3,1,4))*规则表!$I$17-SUM(OFFSET(O65,0,-3,1,4))*规则表!$I$18-SUM(OFFSET(O66,0,-3,1,4))*规则表!$I$19+SUMPRODUCT(INDEX($H$61:$X$61,MAX(COLUMN()-10-规则表!$C$18,1))*规则表!$I$18)+SUMPRODUCT(INDEX($H$62:$X$62,MAX(COLUMN()-10-规则表!$C$19,1))*规则表!$I$19)} -> 0 | P52: {=SUMPRODUCT(INDEX($H$60:$X$60,MAX(COLUMN()-10-规则表!$C$17,1))*规则表!$I$17)-SUM(OFFSET(P64,0,-3,1,4))*规则表!$I$17-SUM(OFFSET(P65,0,-3,1,4))*规则表!$I$18-SUM(OFFSET(P66,0,-3,1,4))*规则表!$I$19+SUMPRODUCT(INDEX($H$61:$X$61,MAX(COLUMN()-10-规则表!$C$18,1))*规则表!$I$18)+SUMPRODUCT(INDEX($H$62:$X$62,MAX(COLUMN()-10-规则表!$C$19,1))*规则表!$I$19)} -> 0 | Y52: 维护费为参考值，尽可能自己计算
C53: 拆线折旧
C54: 总工资 | J54: {=SUMPRODUCT(INDEX($I$89:$X$91,0,COLUMN()-9),规则表!$R$17:$R$19)} -> 90000 | K54: {=SUMPRODUCT(INDEX($I$89:$X$91,0,COLUMN()-9),规则表!$R$17:$R$19)} -> 90000 | L54: {=SUMPRODUCT(INDEX($I$89:$X$91,0,COLUMN()-9),规则表!$R$17:$R$19)} -> 90000 | M54: {=SUMPRODUCT(INDEX($I$89:$X$91,0,COLUMN()-9),规则表!$R$17:$R$19)} -> 90000 | N54: {=SUMPRODUCT(INDEX($I$89:$X$91,0,COLUMN()-9),规则表!$R$17:$R$19)} -> 90000 | O54: {=SUMPRODUCT(INDEX($I$89:$X$91,0,COLUMN()-9),规则表!$R$17:$R$19)} -> 90000 | P54: {=SUMPRODUCT(INDEX($I$89:$X$91,0,COLUMN()-9),规则表!$R$17:$R$19)} -> 90000 | Q54: {=SUMPRODUCT(INDEX($I$89:$X$91,0,COLUMN()-9),规则表!$R$17:$R$19)} -> 90000 | ... X54: {=SUMPRODUCT(INDEX($I$89:$X$91,0,COLUMN()-9),规则表!$R$17:$R$19)} -> 90000
C55: 激励费用 | J55: {=SUMPRODUCT((INDEX($I$89:$X$91,0,COLUMN()-8)-INDEX($I$89:$X$91,0,COLUMN()-9)>0)*(INDEX($I$89:$X$91,0,COLUMN()-8)-INDEX($I$89:$X$91,0,COLUMN()-9)),规则表!$T$17:$T$19)+SUMPRODUCT((INDEX($I$111:$X$113,0,COLUMN()-8)-(INDEX($I$89:$X$91,0,COLUMN()-8)-INDEX($I$89:$X$91,0,COLUMN()-9))>0)*(INDEX($I$111:$X$113,0,COLUMN()-8)-(INDEX($I$89:$X$91,0,COLUMN()-8)-INDEX($I$89:$X$91,0,COLUMN()-9))),规则表!$U$17:$U$19)} -> 0 | K55: {=SUMPRODUCT((INDEX($I$89:$X$91,0,COLUMN()-8)-INDEX($I$89:$X$91,0,COLUMN()-9)>0)*(INDEX($I$89:$X$91,0,COLUMN()-8)-INDEX($I$89:$X$91,0,COLUMN()-9)),规则表!$T$17:$T$19)+SUMPRODUCT((INDEX($I$111:$X$113,0,COLUMN()-8)-(INDEX($I$89:$X$91,0,COLUMN()-8)-INDEX($I$89:$X$91,0,COLUMN()-9))>0)*(INDEX($I$111:$X$113,0,COLUMN()-8)-(INDEX($I$89:$X$91,0,COLUMN()-8)-INDEX($I$89:$X$91,0,COLUMN()-9))),规则表!$U$17:$U$19)} -> 6000 | L55: {=SUMPRODUCT((INDEX($I$89:$X$91,0,COLUMN()-8)-INDEX($I$89:$X$91,0,COLUMN()-9)>0)*(INDEX($I$89:$X$91,0,COLUMN()-8)-INDEX($I$89:$X$91,0,COLUMN()-9)),规则表!$T$17:$T$19)+SUMPRODUCT((INDEX($I$111:$X$113,0,COLUMN()-8)-(INDEX($I$89:$X$91,0,COLUMN()-8)-INDEX($I$89:$X$91,0,COLUMN()-9))>0)*(INDEX($I$111:$X$113,0,COLUMN()-8)-(INDEX($I$89:$X$91,0,COLUMN()-8)-INDEX($I$89:$X$91,0,COLUMN()-9))),规则表!$U$17:$U$19)} -> 0 | M55: {=SUMPRODUCT((INDEX($I$89:$X$91,0,COLUMN()-8)-INDEX($I$89:$X$91,0,COLUMN()-9)>0)*(INDEX($I$89:$X$91,0,COLUMN()-8)-INDEX($I$89:$X$91,0,COLUMN()-9)),规则表!$T$17:$T$19)+SUMPRODUCT((INDEX($I$111:$X$113,0,COLUMN()-8)-(INDEX($I$89:$X$91,0,COLUMN()-8)-INDEX($I$89:$X$91,0,COLUMN()-9))>0)*(INDEX($I$111:$X$113,0,COLUMN()-8)-(INDEX($I$89:$X$91,0,COLUMN()-8)-INDEX($I$89:$X$91,0,COLUMN()-9))),规则表!$U$17:$U$19)} -> 6000 | N55: {=SUMPRODUCT((INDEX($I$89:$X$91,0,COLUMN()-8)-INDEX($I$89:$X$91,0,COLUMN()-9)>0)*(INDEX($I$89:$X$91,0,COLUMN()-8)-INDEX($I$89:$X$91,0,COLUMN()-9)),规则表!$T$17:$T$19)+SUMPRODUCT((INDEX($I$111:$X$113,0,COLUMN()-8)-(INDEX($I$89:$X$91,0,COLUMN()-8)-INDEX($I$89:$X$91,0,COLUMN()-9))>0)*(INDEX($I$111:$X$113,0,COLUMN()-8)-(INDEX($I$89:$X$91,0,COLUMN()-8)-INDEX($I$89:$X$91,0,COLUMN()-9))),规则表!$U$17:$U$19)} -> 0 | O55: {=SUMPRODUCT((INDEX($I$89:$X$91,0,COLUMN()-8)-INDEX($I$89:$X$91,0,COLUMN()-9)>0)*(INDEX($I$89:$X$91,0,COLUMN()-8)-INDEX($I$89:$X$91,0,COLUMN()-9)),规则表!$T$17:$T$19)+SUMPRODUCT((INDEX($I$111:$X$113,0,COLUMN()-8)-(INDEX($I$89:$X$91,0,COLUMN()-8)-INDEX($I$89:$X$91,0,COLUMN()-9))>0)*(INDEX($I$111:$X$113,0,COLUMN()-8)-(INDEX($I$89:$X$91,0,COLUMN()-8)-INDEX($I$89:$X$91,0,COLUMN()-9))),规则表!$U$17:$U$19)} -> 6000 | P55: {=SUMPRODUCT((INDEX($I$89:$X$91,0,COLUMN()-8)-INDEX($I$89:$X$91,0,COLUMN()-9)>0)*(INDEX($I$89:$X$91,0,COLUMN()-8)-INDEX($I$89:$X$91,0,COLUMN()-9)),规则表!$T$17:$T$19)+SUMPRODUCT((INDEX($I$111:$X$113,0,COLUMN()-8)-(INDEX($I$89:$X$91,0,COLUMN()-8)-INDEX($I$89:$X$91,0,COLUMN()-9))>0)*(INDEX($I$111:$X$113,0,COLUMN()-8)-(INDEX($I$89:$X$91,0,COLUMN()-8)-INDEX($I$89:$X$91,0,COLUMN()-9))),规则表!$U$17:$U$19)} -> 0 | Q55: {=SUMPRODUCT((INDEX($I$89:$X$91,0,COLUMN()-8)-INDEX($I$89:$X$91,0,COLUMN()-9)>0)*(INDEX($I$89:$X$91,0,COLUMN()-8)-INDEX($I$89:$X$91,0,COLUMN()-9)),规则表!$T$17:$T$19)+SUMPRODUCT((INDEX($I$111:$X$113,0,COLUMN()-8)-(INDEX($I$89:$X$91,0,COLUMN()-8)-INDEX($I$89:$X$91,0,COLUMN()-9))>0)*(INDEX($I$111:$X$113,0,COLUMN()-8)-(INDEX($I$89:$X$91,0,COLUMN()-8)-INDEX($I$89:$X$91,0,COLUMN()-9))),规则表!$U$17:$U$19)} -> 0 | ... X55: {=SUMPRODUCT((INDEX($I$89:$X$91,0,COLUMN()-8)-INDEX($I$89:$X$91,0,COLUMN()-9)>0)*(INDEX($I$89:$X$91,0,COLUMN()-8)-INDEX($I$89:$X$91,0,COLUMN()-9)),规则表!$T$17:$T$19)+SUMPRODUCT((INDEX($I$111:$X$113,0,COLUMN()-8)-(INDEX($I$89:$X$91,0,COLUMN()-8)-INDEX($I$89:$X$91,0,COLUMN()-9))>0)*(INDEX($I$111:$X$113,0,COLUMN()-8)-(INDEX($I$89:$X$91,0,COLUMN()-8)-INDEX($I$89:$X$91,0,COLUMN()-9))),规则表!$U$17:$U$19)} -> 0
C56: 转产费 | I56: {=SUMPRODUCT(I68:I70>0,规则表!$G$17:$G$19)} -> 0 | J56: {=SUMPRODUCT(J68:J70>0,规则表!$G$17:$G$19)} -> 0 | K56: {=SUMPRODUCT(K68:K70>0,规则表!$G$17:$G$19)} -> 0 | L56: {=SUMPRODUCT(L68:L70>0,规则表!$G$17:$G$19)} -> 0 | M56: {=SUMPRODUCT(M68:M70>0,规则表!$G$17:$G$19)} -> 0 | N56: {=SUMPRODUCT(N68:N70>0,规则表!$G$17:$G$19)} -> 0 | O56: {=SUMPRODUCT(O68:O70>0,规则表!$G$17:$G$19)} -> 0 | P56: {=SUMPRODUCT(P68:P70>0,规则表!$G$17:$G$19)} -> 0 | ... X56: {=SUMPRODUCT(X68:X70>0,规则表!$G$17:$G$19)} -> 0
C57: 涨薪费用 | I57: 0 | J57: {=SUMPRODUCT((INDEX($I$89:$X$91,0,COLUMN()-8)-INDEX($I$89:$X$91,0,COLUMN()-9)>0)*(INDEX($I$89:$X$91,0,COLUMN()-8)-INDEX($I$89:$X$91,0,COLUMN()-9)),规则表!$W$17:$W$19)+SUMPRODUCT((INDEX($I$111:$X$113,0,COLUMN()-8)-(INDEX($I$89:$X$91,0,COLUMN()-8)-INDEX($I$89:$X$91,0,COLUMN()-9))>0)*(INDEX($I$111:$X$113,0,COLUMN()-8)-(INDEX($I$89:$X$91,0,COLUMN()-8)-INDEX($I$89:$X$91,0,COLUMN()-9))),规则表!$X$17:$X$19)} -> 0 | K57: {=SUMPRODUCT((INDEX($I$89:$X$91,0,COLUMN()-8)-INDEX($I$89:$X$91,0,COLUMN()-9)>0)*(INDEX($I$89:$X$91,0,COLUMN()-8)-INDEX($I$89:$X$91,0,COLUMN()-9)),规则表!$W$17:$W$19)+SUMPRODUCT((INDEX($I$111:$X$113,0,COLUMN()-8)-(INDEX($I$89:$X$91,0,COLUMN()-8)-INDEX($I$89:$X$91,0,COLUMN()-9))>0)*(INDEX($I$111:$X$113,0,COLUMN()-8)-(INDEX($I$89:$X$91,0,COLUMN()-8)-INDEX($I$89:$X$91,0,COLUMN()-9))),规则表!$X$17:$X$19)} -> 1020 | L57: {=SUMPRODUCT((INDEX($I$89:$X$91,0,COLUMN()-8)-INDEX($I$89:$X$91,0,COLUMN()-9)>0)*(INDEX($I$89:$X$91,0,COLUMN()-8)-INDEX($I$89:$X$91,0,COLUMN()-9)),规则表!$W$17:$W$19)+SUMPRODUCT((INDEX($I$111:$X$113,0,COLUMN()-8)-(INDEX($I$89:$X$91,0,COLUMN()-8)-INDEX($I$89:$X$91,0,COLUMN()-9))>0)*(INDEX($I$111:$X$113,0,COLUMN()-8)-(INDEX($I$89:$X$91,0,COLUMN()-8)-INDEX($I$89:$X$91,0,COLUMN()-9))),规则表!$X$17:$X$19)} -> 0 | M57: {=SUMPRODUCT((INDEX($I$89:$X$91,0,COLUMN()-8)-INDEX($I$89:$X$91,0,COLUMN()-9)>0)*(INDEX($I$89:$X$91,0,COLUMN()-8)-INDEX($I$89:$X$91,0,COLUMN()-9)),规则表!$W$17:$W$19)+SUMPRODUCT((INDEX($I$111:$X$113,0,COLUMN()-8)-(INDEX($I$89:$X$91,0,COLUMN()-8)-INDEX($I$89:$X$91,0,COLUMN()-9))>0)*(INDEX($I$111:$X$113,0,COLUMN()-8)-(INDEX($I$89:$X$91,0,COLUMN()-8)-INDEX($I$89:$X$91,0,COLUMN()-9))),规则表!$X$17:$X$19)} -> 1020 | N57: {=SUMPRODUCT((INDEX($I$89:$X$91,0,COLUMN()-8)-INDEX($I$89:$X$91,0,COLUMN()-9)>0)*(INDEX($I$89:$X$91,0,COLUMN()-8)-INDEX($I$89:$X$91,0,COLUMN()-9)),规则表!$W$17:$W$19)+SUMPRODUCT((INDEX($I$111:$X$113,0,COLUMN()-8)-(INDEX($I$89:$X$91,0,COLUMN()-8)-INDEX($I$89:$X$91,0,COLUMN()-9))>0)*(INDEX($I$111:$X$113,0,COLUMN()-8)-(INDEX($I$89:$X$91,0,COLUMN()-8)-INDEX($I$89:$X$91,0,COLUMN()-9))),规则表!$X$17:$X$19)} -> 0 | O57: {=SUMPRODUCT((INDEX($I$89:$X$91,0,COLUMN()-8)-INDEX($I$89:$X$91,0,COLUMN()-9)>0)*(INDEX($I$89:$X$91,0,COLUMN()-8)-INDEX($I$89:$X$91,0,COLUMN()-9)),规则表!$W$17:$W$19)+SUMPRODUCT((INDEX($I$111:$X$113,0,COLUMN()-8)-(INDEX($I$89:$X$91,0,COLUMN()-8)-INDEX($I$89:$X$91,0,COLUMN()-9))>0)*(INDEX($I$111:$X$113,0,COLUMN()-8)-(INDEX($I$89:$X$91,0,COLUMN()-8)-INDEX($I$89:$X$91,0,COLUMN()-9))),规则表!$X$17:$X$19)} -> 1020 | P57: {=SUMPRODUCT((INDEX($I$89:$X$91,0,COLUMN()-8)-INDEX($I$89:$X$91,0,COLUMN()-9)>0)*(INDEX($I$89:$X$91,0,COLUMN()-8)-INDEX($I$89:$X$91,0,COLUMN()-9)),规则表!$W$17:$W$19)+SUMPRODUCT((INDEX($I$111:$X$113,0,COLUMN()-8)-(INDEX($I$89:$X$91,0,COLUMN()-8)-INDEX($I$89:$X$91,0,COLUMN()-9))>0)*(INDEX($I$111:$X$113,0,COLUMN()-8)-(INDEX($I$89:$X$91,0,COLUMN()-8)-INDEX($I$89:$X$91,0,COLUMN()-9))),规则表!$X$17:$X$19)} -> 0 | Q57: {=SUMPRODUCT((INDEX($I$89:$X$91,0,COLUMN()-8)-INDEX($I$89:$X$91,0,COLUMN()-9)>0)*(INDEX($I$89:$X$91,0,COLUMN()-8)-INDEX($I$89:$X$91,0,COLUMN()-9)),规则表!$W$17:$W$19)+SUMPRODUCT((INDEX($I$111:$X$113,0,COLUMN()-8)-(INDEX($I$89:$X$91,0,COLUMN()-8)-INDEX($I$89:$X$91,0,COLUMN()-9))>0)*(INDEX($I$111:$X$113,0,COLUMN()-8)-(INDEX($I$89:$X$91,0,COLUMN()-8)-INDEX($I$89:$X$91,0,COLUMN()-9))),规则表!$X$17:$X$19)} -> 0 | ... X57: {=SUMPRODUCT((INDEX($I$89:$X$91,0,COLUMN()-8)-INDEX($I$89:$X$91,0,COLUMN()-9)>0)*(INDEX($I$89:$X$91,0,COLUMN()-8)-INDEX($I$89:$X$91,0,COLUMN()-9)),规则表!$W$17:$W$19)+SUMPRODUCT((INDEX($I$111:$X$113,0,COLUMN()-8)-(INDEX($I$89:$X$91,0,COLUMN()-8)-INDEX($I$89:$X$91,0,COLUMN()-9))>0)*(INDEX($I$111:$X$113,0,COLUMN()-8)-(INDEX($I$89:$X$91,0,COLUMN()-8)-INDEX($I$89:$X$91,0,COLUMN()-9))),规则表!$X$17:$X$19)} -> 0
C58: 总激励 | J58: {=SUMPRODUCT(($I$3:INDEX($I$3:$X$3,MAX(1,COLUMN()-9))=$A$1)*$I$57:INDEX($I$57:$X$57,MAX(1,COLUMN()-9)))+SUMPRODUCT((INDEX($I$3:$X$3,MAX(1,COLUMN()-8))=$B$1)*INDEX($I$55:$X$55,MAX(1,COLUMN()-8)))} -> 0 | K58: {=SUMPRODUCT(($I$3:INDEX($I$3:$X$3,MAX(1,COLUMN()-9))=$A$1)*$I$57:INDEX($I$57:$X$57,MAX(1,COLUMN()-9)))*3+SUMPRODUCT((INDEX($I$3:$X$3,MAX(1,COLUMN()-8))=$B$1)*INDEX($I$55:$X$55,MAX(1,COLUMN()-8)))} -> 6000 | L58: {=SUMPRODUCT(($I$3:INDEX($I$3:$X$3,MAX(1,COLUMN()-9))=$A$1)*$I$57:INDEX($I$57:$X$57,MAX(1,COLUMN()-9)))*3+SUMPRODUCT((INDEX($I$3:$X$3,MAX(1,COLUMN()-8))=$B$1)*INDEX($I$55:$X$55,MAX(1,COLUMN()-8)))} -> 0 | M58: {=SUMPRODUCT(($I$3:INDEX($I$3:$X$3,MAX(1,COLUMN()-9))=$A$1)*$I$57:INDEX($I$57:$X$57,MAX(1,COLUMN()-9)))*3+SUMPRODUCT((INDEX($I$3:$X$3,MAX(1,COLUMN()-8))=$B$1)*INDEX($I$55:$X$55,MAX(1,COLUMN()-8)))} -> 6000 | N58: {=SUMPRODUCT(($M$3:INDEX($M$3:$Q$3,MAX(1,COLUMN()-13))=$A$1)*$M$57:INDEX($M$57:$Q$57,MAX(1,COLUMN()-13)))*3+SUMPRODUCT((INDEX($I$3:$X$3,MAX(1,COLUMN()-8))=$B$1)*INDEX($I$55:$X$55,MAX(1,COLUMN()-8)))} -> 0 | O58: {=SUMPRODUCT(($M$3:INDEX($M$3:$Q$3,MAX(1,COLUMN()-13))=$A$1)*$M$57:INDEX($M$57:$Q$57,MAX(1,COLUMN()-13)))*3+SUMPRODUCT((INDEX($I$3:$X$3,MAX(1,COLUMN()-8))=$B$1)*INDEX($I$55:$X$55,MAX(1,COLUMN()-8)))} -> 6000 | P58: {=SUMPRODUCT(($M$3:INDEX($M$3:$Q$3,MAX(1,COLUMN()-13))=$A$1)*$M$57:INDEX($M$57:$Q$57,MAX(1,COLUMN()-13)))*3+SUMPRODUCT((INDEX($I$3:$X$3,MAX(1,COLUMN()-8))=$B$1)*INDEX($I$55:$X$55,MAX(1,COLUMN()-8)))} -> 0 | Q58: {=SUMPRODUCT(($M$3:INDEX($M$3:$Q$3,MAX(1,COLUMN()-13))=$A$1)*$M$57:INDEX($M$57:$Q$57,MAX(1,COLUMN()-13)))*3+SUMPRODUCT((INDEX($I$3:$X$3,MAX(1,COLUMN()-8))=$B$1)*INDEX($I$55:$X$55,MAX(1,COLUMN()-8)))} -> 0 | R58: {=SUMPRODUCT(($Q$3:INDEX($Q$3:$U$3,MAX(1,COLUMN()-17))=$A$1)*$Q$57:INDEX($Q$57:$U$57,MAX(1,COLUMN()-17)))*3+SUMPRODUCT((INDEX($I$3:$X$3,MAX(1,COLUMN()-8))=$B$1)*INDEX($I$55:$X$55,MAX(1,COLUMN()-8)))} -> 0 | S58: {=SUMPRODUCT(($Q$3:INDEX($Q$3:$U$3,MAX(1,COLUMN()-17))=$A$1)*$Q$57:INDEX($Q$57:$U$57,MAX(1,COLUMN()-17)))*3+SUMPRODUCT((INDEX($I$3:$X$3,MAX(1,COLUMN()-8))=$B$1)*INDEX($I$55:$X$55,MAX(1,COLUMN()-8)))} -> 0 | T58: {=SUMPRODUCT(($Q$3:INDEX($Q$3:$U$3,MAX(1,COLUMN()-17))=$A$1)*$Q$57:INDEX($Q$57:$U$57,MAX(1,COLUMN()-17)))*3+SUMPRODUCT((INDEX($I$3:$X$3,MAX(1,COLUMN()-8))=$B$1)*INDEX($I$55:$X$55,MAX(1,COLUMN()-8)))} -> 0 | U58: {=SUMPRODUCT(($Q$3:INDEX($Q$3:$U$3,MAX(1,COLUMN()-17))=$A$1)*$Q$57:INDEX($Q$57:$U$57,MAX(1,COLUMN()-17)))*3+SUMPRODUCT((INDEX($I$3:$X$3,MAX(1,COLUMN()-8))=$B$1)*INDEX($I$55:$X$55,MAX(1,COLUMN()-8)))} -> 0 | V58: {=SUMPRODUCT(($U$3:INDEX($U$3:$X$3,MAX(1,COLUMN())-21)=$A$1)*$U$57:INDEX($U$57:$X$57,MAX(1,COLUMN()-21)))*3+SUMPRODUCT((INDEX($I$3:$X$3,MAX(1,COLUMN()-8))=$B$1)*INDEX($I$55:$X$55,MAX(1,COLUMN()-8)))} -> 0 | W58: {=SUMPRODUCT(($U$3:INDEX($U$3:$X$3,MAX(1,COLUMN())-21)=$A$1)*$U$57:INDEX($U$57:$X$57,MAX(1,COLUMN()-21)))*3+SUMPRODUCT((INDEX($I$3:$X$3,MAX(1,COLUMN()-8))=$B$1)*INDEX($I$55:$X$55,MAX(1,COLUMN()-8)))} -> 0 | X58: {=SUMPRODUCT(($U$3:INDEX($U$3:$X$3,MAX(1,COLUMN())-21)=$A$1)*$U$57:INDEX($U$57:$X$57,MAX(1,COLUMN()-21)))*3+SUMPRODUCT((INDEX($I$3:$X$3,MAX(1,COLUMN()-8))=$B$1)*INDEX($I$55:$X$55,MAX(1,COLUMN()-8)))} -> 0
B60: 建设计划 | C60: 手工线 | I60: =SUM(I4:I8) -> 10 | J60: =SUM(J4:J8) -> 0 | K60: =SUM(K4:K8) -> 0 | L60: =SUM(L4:L8) -> 0 | M60: =SUM(M4:M8) -> 0 | N60: =SUM(N4:N8) -> 0 | O60: =SUM(O4:O8) -> 0 | P60: =SUM(P4:P8) -> 0 | ... X60: =SUM(X4:X8) -> 0
C61: 自动线 | I61: =SUM(I9:I13) -> 0 | J61: =SUM(J9:J13) -> 0 | K61: =SUM(K9:K13) -> 0 | L61: =SUM(L9:L13) -> 0 | M61: =SUM(M9:M13) -> 0 | N61: =SUM(N9:N13) -> 0 | O61: =SUM(O9:O13) -> 0 | P61: =SUM(P9:P13) -> 0 | ... X61: =SUM(X9:X13) -> 0
C62: 智能线 | I62: =SUM(I14:I18) -> 0 | J62: =SUM(J14:J18) -> 0 | K62: =SUM(K14:K18) -> 0 | L62: =SUM(L14:L18) -> 0 | M62: =SUM(M14:M18) -> 0 | N62: =SUM(N14:N18) -> 0 | O62: =SUM(O14:O18) -> 0 | P62: =SUM(P14:P18) -> 0 | ... X62: =SUM(X14:X18) -> 0
B64: 拆线计划 | C64: 手工线 | I64: =SUM(I20:I24) -> 0 | J64: =SUM(J20:J24) -> 0 | K64: =SUM(K20:K24) -> 0 | L64: =SUM(L20:L24) -> 0 | M64: =SUM(M20:M24) -> 0 | N64: =SUM(N20:N24) -> 0 | O64: =SUM(O20:O24) -> 0 | P64: =SUM(P20:P24) -> 0 | ... X64: =SUM(X20:X24) -> 0
C65: 自动线 | I65: =SUM(I25:I29) -> 0 | J65: =SUM(J25:J29) -> 0 | K65: =SUM(K25:K29) -> 0 | L65: =SUM(L25:L29) -> 0 | M65: =SUM(M25:M29) -> 0 | N65: =SUM(N25:N29) -> 0 | O65: =SUM(O25:O29) -> 0 | P65: =SUM(P25:P29) -> 0 | ... X65: =SUM(X25:X29) -> 0
C66: 智能线 | I66: =SUM(I30:I34) -> 0 | J66: =SUM(J30:J34) -> 0 | K66: =SUM(K30:K34) -> 0 | L66: =SUM(L30:L34) -> 0 | M66: =SUM(M30:M34) -> 0 | N66: =SUM(N30:N34) -> 0 | O66: =SUM(O30:O34) -> 0 | P66: =SUM(P30:P34) -> 0 | ... X66: =SUM(X30:X34) -> 0
B68: 转线计划 | C68: 手工线 | I68: =SUM(I36:I40) -> 0 | J68: =SUM(J36:J40) -> 0 | K68: =SUM(K36:K40) -> 0 | L68: =SUM(L36:L40) -> 0 | M68: =SUM(M36:M40) -> 0 | N68: =SUM(N36:N40) -> 0 | O68: =SUM(O36:O40) -> 0 | P68: =SUM(P36:P40) -> 0 | ... X68: =SUM(X36:X40) -> 0
C69: 自动线 | I69: =SUM(I41:I45) -> 0 | J69: =SUM(J41:J45) -> 0 | K69: =SUM(K41:K45) -> 0 | L69: =SUM(L41:L45) -> 0 | M69: =SUM(M41:M45) -> 0 | N69: =SUM(N41:N45) -> 0 | O69: =SUM(O41:O45) -> 0 | P69: =SUM(P41:P45) -> 0 | ... X69: =SUM(X41:X45) -> 0
C70: 智能线 | I70: =SUM(I46:I50) -> 0 | J70: =SUM(J46:J50) -> 0 | K70: =SUM(K46:K50) -> 0 | L70: =SUM(L46:L50) -> 0 | M70: =SUM(M46:M50) -> 0 | N70: =SUM(N46:N50) -> 0 | O70: =SUM(O46:O50) -> 0 | P70: =SUM(P46:P50) -> 0 | ... X70: =SUM(X46:X50) -> 0
A72: 现存产线情况 | B72: 传统线 | C72: P1 | I72: {=SUM(OFFSET(I4,0,-(COLUMN()-1),1,COLUMN()-规则表!$C$17))-SUM(OFFSET(I20,0,-(COLUMN()-1),1,COLUMN()))+SUM(OFFSET(I36,0,-(COLUMN()-1),1,COLUMN()-规则表!$F$17))+SUMPRODUCT((IFERROR(OFFSET(I36,0,-(规则表!$F$17-1),1,规则表!$F$17),0)<0)*IFERROR(FFSET(I36,0,-(规则表!$F$17-1),1,规则表!$F$17),0))} -> 0 | J72: {=SUM(OFFSET(J4,0,-(COLUMN()-1),1,COLUMN()-规则表!$C$17))-SUM(OFFSET(J20,0,-(COLUMN()-1),1,COLUMN()))+SUM(OFFSET(J36,0,-(COLUMN()-1),1,COLUMN()-规则表!$F$17))+SUMPRODUCT((IFERROR(OFFSET(J36,0,-(规则表!$F$17-1),1,规则表!$F$17),0)<0)*IFERROR(FFSET(J36,0,-(规则表!$F$17-1),1,规则表!$F$17),0))} -> 0 | K72: {=SUM(OFFSET(K4,0,-(COLUMN()-1),1,COLUMN()-规则表!$C$17))-SUM(OFFSET(K20,0,-(COLUMN()-1),1,COLUMN()))+SUM(OFFSET(K36,0,-(COLUMN()-1),1,COLUMN()-规则表!$F$17))+SUMPRODUCT((IFERROR(OFFSET(K36,0,-(规则表!$F$17-1),1,规则表!$F$17),0)<0)*IFERROR(FFSET(K36,0,-(规则表!$F$17-1),1,规则表!$F$17),0))} -> 0 | L72: {=SUM(OFFSET(L4,0,-(COLUMN()-1),1,COLUMN()-规则表!$C$17))-SUM(OFFSET(L20,0,-(COLUMN()-1),1,COLUMN()))+SUM(OFFSET(L36,0,-(COLUMN()-1),1,COLUMN()-规则表!$F$17))+SUMPRODUCT((IFERROR(OFFSET(L36,0,-(规则表!$F$17-1),1,规则表!$F$17),0)<0)*IFERROR(FFSET(L36,0,-(规则表!$F$17-1),1,规则表!$F$17),0))} -> 0 | M72: {=SUM(OFFSET(M4,0,-(COLUMN()-1),1,COLUMN()-规则表!$C$17))-SUM(OFFSET(M20,0,-(COLUMN()-1),1,COLUMN()))+SUM(OFFSET(M36,0,-(COLUMN()-1),1,COLUMN()-规则表!$F$17))+SUMPRODUCT((IFERROR(OFFSET(M36,0,-(规则表!$F$17-1),1,规则表!$F$17),0)<0)*IFERROR(FFSET(M36,0,-(规则表!$F$17-1),1,规则表!$F$17),0))} -> 0 | N72: {=SUM(OFFSET(N4,0,-(COLUMN()-1),1,COLUMN()-规则表!$C$17))-SUM(OFFSET(N20,0,-(COLUMN()-1),1,COLUMN()))+SUM(OFFSET(N36,0,-(COLUMN()-1),1,COLUMN()-规则表!$F$17))+SUMPRODUCT((IFERROR(OFFSET(N36,0,-(规则表!$F$17-1),1,规则表!$F$17),0)<0)*IFERROR(FFSET(N36,0,-(规则表!$F$17-1),1,规则表!$F$17),0))} -> 0 | O72: {=SUM(OFFSET(O4,0,-(COLUMN()-1),1,COLUMN()-规则表!$C$17))-SUM(OFFSET(O20,0,-(COLUMN()-1),1,COLUMN()))+SUM(OFFSET(O36,0,-(COLUMN()-1),1,COLUMN()-规则表!$F$17))+SUMPRODUCT((IFERROR(OFFSET(O36,0,-(规则表!$F$17-1),1,规则表!$F$17),0)<0)*IFERROR(FFSET(O36,0,-(规则表!$F$17-1),1,规则表!$F$17),0))} -> 0 | P72: {=SUM(OFFSET(P4,0,-(COLUMN()-1),1,COLUMN()-规则表!$C$17))-SUM(OFFSET(P20,0,-(COLUMN()-1),1,COLUMN()))+SUM(OFFSET(P36,0,-(COLUMN()-1),1,COLUMN()-规则表!$F$17))+SUMPRODUCT((IFERROR(OFFSET(P36,0,-(规则表!$F$17-1),1,规则表!$F$17),0)<0)*IFERROR(FFSET(P36,0,-(规则表!$F$17-1),1,规则表!$F$17),0))} -> 0 | ... X72: {=SUM(OFFSET(X4,0,-(COLUMN()-1),1,COLUMN()-规则表!$C$17))-SUM(OFFSET(X20,0,-(COLUMN()-1),1,COLUMN()))+SUM(OFFSET(X36,0,-(COLUMN()-1),1,COLUMN()-规则表!$F$17))+SUMPRODUCT((IFERROR(OFFSET(X36,0,-(规则表!$F$17-1),1,规则表!$F$17),0)<0)*IFERROR(FFSET(X36,0,-(规则表!$F$17-1),1,规则表!$F$17),0))} -> 0
C73: P2 | I73: {=SUM(OFFSET(I5,0,-(COLUMN()-1),1,COLUMN()-规则表!$C$17))-SUM(OFFSET(I21,0,-(COLUMN()-1),1,COLUMN()))+SUM(OFFSET(I37,0,-(COLUMN()-1),1,COLUMN()-规则表!$F$17))+SUMPRODUCT((IFERROR(OFFSET(I37,0,-(规则表!$F$17-1),1,规则表!$F$17),0)<0)*IFERROR(FFSET(I37,0,-(规则表!$F$17-1),1,规则表!$F$17),0))} -> 0 | J73: {=SUM(OFFSET(J5,0,-(COLUMN()-1),1,COLUMN()-规则表!$C$17))-SUM(OFFSET(J21,0,-(COLUMN()-1),1,COLUMN()))+SUM(OFFSET(J37,0,-(COLUMN()-1),1,COLUMN()-规则表!$F$17))+SUMPRODUCT((IFERROR(OFFSET(J37,0,-(规则表!$F$17-1),1,规则表!$F$17),0)<0)*IFERROR(FFSET(J37,0,-(规则表!$F$17-1),1,规则表!$F$17),0))} -> 0 | K73: {=SUM(OFFSET(K5,0,-(COLUMN()-1),1,COLUMN()-规则表!$C$17))-SUM(OFFSET(K21,0,-(COLUMN()-1),1,COLUMN()))+SUM(OFFSET(K37,0,-(COLUMN()-1),1,COLUMN()-规则表!$F$17))+SUMPRODUCT((IFERROR(OFFSET(K37,0,-(规则表!$F$17-1),1,规则表!$F$17),0)<0)*IFERROR(FFSET(K37,0,-(规则表!$F$17-1),1,规则表!$F$17),0))} -> 0 | L73: {=SUM(OFFSET(L5,0,-(COLUMN()-1),1,COLUMN()-规则表!$C$17))-SUM(OFFSET(L21,0,-(COLUMN()-1),1,COLUMN()))+SUM(OFFSET(L37,0,-(COLUMN()-1),1,COLUMN()-规则表!$F$17))+SUMPRODUCT((IFERROR(OFFSET(L37,0,-(规则表!$F$17-1),1,规则表!$F$17),0)<0)*IFERROR(FFSET(L37,0,-(规则表!$F$17-1),1,规则表!$F$17),0))} -> 0 | M73: {=SUM(OFFSET(M5,0,-(COLUMN()-1),1,COLUMN()-规则表!$C$17))-SUM(OFFSET(M21,0,-(COLUMN()-1),1,COLUMN()))+SUM(OFFSET(M37,0,-(COLUMN()-1),1,COLUMN()-规则表!$F$17))+SUMPRODUCT((IFERROR(OFFSET(M37,0,-(规则表!$F$17-1),1,规则表!$F$17),0)<0)*IFERROR(FFSET(M37,0,-(规则表!$F$17-1),1,规则表!$F$17),0))} -> 0 | N73: {=SUM(OFFSET(N5,0,-(COLUMN()-1),1,COLUMN()-规则表!$C$17))-SUM(OFFSET(N21,0,-(COLUMN()-1),1,COLUMN()))+SUM(OFFSET(N37,0,-(COLUMN()-1),1,COLUMN()-规则表!$F$17))+SUMPRODUCT((IFERROR(OFFSET(N37,0,-(规则表!$F$17-1),1,规则表!$F$17),0)<0)*IFERROR(FFSET(N37,0,-(规则表!$F$17-1),1,规则表!$F$17),0))} -> 0 | O73: {=SUM(OFFSET(O5,0,-(COLUMN()-1),1,COLUMN()-规则表!$C$17))-SUM(OFFSET(O21,0,-(COLUMN()-1),1,COLUMN()))+SUM(OFFSET(O37,0,-(COLUMN()-1),1,COLUMN()-规则表!$F$17))+SUMPRODUCT((IFERROR(OFFSET(O37,0,-(规则表!$F$17-1),1,规则表!$F$17),0)<0)*IFERROR(FFSET(O37,0,-(规则表!$F$17-1),1,规则表!$F$17),0))} -> 0 | P73: {=SUM(OFFSET(P5,0,-(COLUMN()-1),1,COLUMN()-规则表!$C$17))-SUM(OFFSET(P21,0,-(COLUMN()-1),1,COLUMN()))+SUM(OFFSET(P37,0,-(COLUMN()-1),1,COLUMN()-规则表!$F$17))+SUMPRODUCT((IFERROR(OFFSET(P37,0,-(规则表!$F$17-1),1,规则表!$F$17),0)<0)*IFERROR(FFSET(P37,0,-(规则表!$F$17-1),1,规则表!$F$17),0))} -> 0 | ... X73: {=SUM(OFFSET(X5,0,-(COLUMN()-1),1,COLUMN()-规则表!$C$17))-SUM(OFFSET(X21,0,-(COLUMN()-1),1,COLUMN()))+SUM(OFFSET(X37,0,-(COLUMN()-1),1,COLUMN()-规则表!$F$17))+SUMPRODUCT((IFERROR(OFFSET(X37,0,-(规则表!$F$17-1),1,规则表!$F$17),0)<0)*IFERROR(FFSET(X37,0,-(规则表!$F$17-1),1,规则表!$F$17),0))} -> 0
C74: P3 | I74: {=SUM(OFFSET(I6,0,-(COLUMN()-1),1,COLUMN()-规则表!$C$17))-SUM(OFFSET(I22,0,-(COLUMN()-1),1,COLUMN()))+SUM(OFFSET(I38,0,-(COLUMN()-1),1,COLUMN()-规则表!$F$17))+SUMPRODUCT((IFERROR(OFFSET(I38,0,-(规则表!$F$17-1),1,规则表!$F$17),0)<0)*IFERROR(FFSET(I38,0,-(规则表!$F$17-1),1,规则表!$F$17),0))} -> 0 | J74: {=SUM(OFFSET(J6,0,-(COLUMN()-1),1,COLUMN()-规则表!$C$17))-SUM(OFFSET(J22,0,-(COLUMN()-1),1,COLUMN()))+SUM(OFFSET(J38,0,-(COLUMN()-1),1,COLUMN()-规则表!$F$17))+SUMPRODUCT((IFERROR(OFFSET(J38,0,-(规则表!$F$17-1),1,规则表!$F$17),0)<0)*IFERROR(FFSET(J38,0,-(规则表!$F$17-1),1,规则表!$F$17),0))} -> 0 | K74: {=SUM(OFFSET(K6,0,-(COLUMN()-1),1,COLUMN()-规则表!$C$17))-SUM(OFFSET(K22,0,-(COLUMN()-1),1,COLUMN()))+SUM(OFFSET(K38,0,-(COLUMN()-1),1,COLUMN()-规则表!$F$17))+SUMPRODUCT((IFERROR(OFFSET(K38,0,-(规则表!$F$17-1),1,规则表!$F$17),0)<0)*IFERROR(FFSET(K38,0,-(规则表!$F$17-1),1,规则表!$F$17),0))} -> 0 | L74: {=SUM(OFFSET(L6,0,-(COLUMN()-1),1,COLUMN()-规则表!$C$17))-SUM(OFFSET(L22,0,-(COLUMN()-1),1,COLUMN()))+SUM(OFFSET(L38,0,-(COLUMN()-1),1,COLUMN()-规则表!$F$17))+SUMPRODUCT((IFERROR(OFFSET(L38,0,-(规则表!$F$17-1),1,规则表!$F$17),0)<0)*IFERROR(FFSET(L38,0,-(规则表!$F$17-1),1,规则表!$F$17),0))} -> 0 | M74: {=SUM(OFFSET(M6,0,-(COLUMN()-1),1,COLUMN()-规则表!$C$17))-SUM(OFFSET(M22,0,-(COLUMN()-1),1,COLUMN()))+SUM(OFFSET(M38,0,-(COLUMN()-1),1,COLUMN()-规则表!$F$17))+SUMPRODUCT((IFERROR(OFFSET(M38,0,-(规则表!$F$17-1),1,规则表!$F$17),0)<0)*IFERROR(FFSET(M38,0,-(规则表!$F$17-1),1,规则表!$F$17),0))} -> 0 | N74: {=SUM(OFFSET(N6,0,-(COLUMN()-1),1,COLUMN()-规则表!$C$17))-SUM(OFFSET(N22,0,-(COLUMN()-1),1,COLUMN()))+SUM(OFFSET(N38,0,-(COLUMN()-1),1,COLUMN()-规则表!$F$17))+SUMPRODUCT((IFERROR(OFFSET(N38,0,-(规则表!$F$17-1),1,规则表!$F$17),0)<0)*IFERROR(FFSET(N38,0,-(规则表!$F$17-1),1,规则表!$F$17),0))} -> 0 | O74: {=SUM(OFFSET(O6,0,-(COLUMN()-1),1,COLUMN()-规则表!$C$17))-SUM(OFFSET(O22,0,-(COLUMN()-1),1,COLUMN()))+SUM(OFFSET(O38,0,-(COLUMN()-1),1,COLUMN()-规则表!$F$17))+SUMPRODUCT((IFERROR(OFFSET(O38,0,-(规则表!$F$17-1),1,规则表!$F$17),0)<0)*IFERROR(FFSET(O38,0,-(规则表!$F$17-1),1,规则表!$F$17),0))} -> 0 | P74: {=SUM(OFFSET(P6,0,-(COLUMN()-1),1,COLUMN()-规则表!$C$17))-SUM(OFFSET(P22,0,-(COLUMN()-1),1,COLUMN()))+SUM(OFFSET(P38,0,-(COLUMN()-1),1,COLUMN()-规则表!$F$17))+SUMPRODUCT((IFERROR(OFFSET(P38,0,-(规则表!$F$17-1),1,规则表!$F$17),0)<0)*IFERROR(FFSET(P38,0,-(规则表!$F$17-1),1,规则表!$F$17),0))} -> 0 | ... X74: {=SUM(OFFSET(X6,0,-(COLUMN()-1),1,COLUMN()-规则表!$C$17))-SUM(OFFSET(X22,0,-(COLUMN()-1),1,COLUMN()))+SUM(OFFSET(X38,0,-(COLUMN()-1),1,COLUMN()-规则表!$F$17))+SUMPRODUCT((IFERROR(OFFSET(X38,0,-(规则表!$F$17-1),1,规则表!$F$17),0)<0)*IFERROR(FFSET(X38,0,-(规则表!$F$17-1),1,规则表!$F$17),0))} -> 0
C75: P4 | I75: {=SUM(OFFSET(I7,0,-(COLUMN()-1),1,COLUMN()-规则表!$C$17))-SUM(OFFSET(I23,0,-(COLUMN()-1),1,COLUMN()))+SUM(OFFSET(I39,0,-(COLUMN()-1),1,COLUMN()-规则表!$F$17))+SUMPRODUCT((IFERROR(OFFSET(I39,0,-(规则表!$F$17-1),1,规则表!$F$17),0)<0)*IFERROR(FFSET(I39,0,-(规则表!$F$17-1),1,规则表!$F$17),0))} -> 10 | J75: {=SUM(OFFSET(J7,0,-(COLUMN()-1),1,COLUMN()-规则表!$C$17))-SUM(OFFSET(J23,0,-(COLUMN()-1),1,COLUMN()))+SUM(OFFSET(J39,0,-(COLUMN()-1),1,COLUMN()-规则表!$F$17))+SUMPRODUCT((IFERROR(OFFSET(J39,0,-(规则表!$F$17-1),1,规则表!$F$17),0)<0)*IFERROR(FFSET(J39,0,-(规则表!$F$17-1),1,规则表!$F$17),0))} -> 10 | K75: {=SUM(OFFSET(K7,0,-(COLUMN()-1),1,COLUMN()-规则表!$C$17))-SUM(OFFSET(K23,0,-(COLUMN()-1),1,COLUMN()))+SUM(OFFSET(K39,0,-(COLUMN()-1),1,COLUMN()-规则表!$F$17))+SUMPRODUCT((IFERROR(OFFSET(K39,0,-(规则表!$F$17-1),1,规则表!$F$17),0)<0)*IFERROR(FFSET(K39,0,-(规则表!$F$17-1),1,规则表!$F$17),0))} -> 10 | L75: {=SUM(OFFSET(L7,0,-(COLUMN()-1),1,COLUMN()-规则表!$C$17))-SUM(OFFSET(L23,0,-(COLUMN()-1),1,COLUMN()))+SUM(OFFSET(L39,0,-(COLUMN()-1),1,COLUMN()-规则表!$F$17))+SUMPRODUCT((IFERROR(OFFSET(L39,0,-(规则表!$F$17-1),1,规则表!$F$17),0)<0)*IFERROR(FFSET(L39,0,-(规则表!$F$17-1),1,规则表!$F$17),0))} -> 10 | M75: {=SUM(OFFSET(M7,0,-(COLUMN()-1),1,COLUMN()-规则表!$C$17))-SUM(OFFSET(M23,0,-(COLUMN()-1),1,COLUMN()))+SUM(OFFSET(M39,0,-(COLUMN()-1),1,COLUMN()-规则表!$F$17))+SUMPRODUCT((IFERROR(OFFSET(M39,0,-(规则表!$F$17-1),1,规则表!$F$17),0)<0)*IFERROR(FFSET(M39,0,-(规则表!$F$17-1),1,规则表!$F$17),0))} -> 10 | N75: {=SUM(OFFSET(N7,0,-(COLUMN()-1),1,COLUMN()-规则表!$C$17))-SUM(OFFSET(N23,0,-(COLUMN()-1),1,COLUMN()))+SUM(OFFSET(N39,0,-(COLUMN()-1),1,COLUMN()-规则表!$F$17))+SUMPRODUCT((IFERROR(OFFSET(N39,0,-(规则表!$F$17-1),1,规则表!$F$17),0)<0)*IFERROR(FFSET(N39,0,-(规则表!$F$17-1),1,规则表!$F$17),0))} -> 10 | O75: {=SUM(OFFSET(O7,0,-(COLUMN()-1),1,COLUMN()-规则表!$C$17))-SUM(OFFSET(O23,0,-(COLUMN()-1),1,COLUMN()))+SUM(OFFSET(O39,0,-(COLUMN()-1),1,COLUMN()-规则表!$F$17))+SUMPRODUCT((IFERROR(OFFSET(O39,0,-(规则表!$F$17-1),1,规则表!$F$17),0)<0)*IFERROR(FFSET(O39,0,-(规则表!$F$17-1),1,规则表!$F$17),0))} -> 10 | P75: {=SUM(OFFSET(P7,0,-(COLUMN()-1),1,COLUMN()-规则表!$C$17))-SUM(OFFSET(P23,0,-(COLUMN()-1),1,COLUMN()))+SUM(OFFSET(P39,0,-(COLUMN()-1),1,COLUMN()-规则表!$F$17))+SUMPRODUCT((IFERROR(OFFSET(P39,0,-(规则表!$F$17-1),1,规则表!$F$17),0)<0)*IFERROR(FFSET(P39,0,-(规则表!$F$17-1),1,规则表!$F$17),0))} -> 10 | ... X75: {=SUM(OFFSET(X7,0,-(COLUMN()-1),1,COLUMN()-规则表!$C$17))-SUM(OFFSET(X23,0,-(COLUMN()-1),1,COLUMN()))+SUM(OFFSET(X39,0,-(COLUMN()-1),1,COLUMN()-规则表!$F$17))+SUMPRODUCT((IFERROR(OFFSET(X39,0,-(规则表!$F$17-1),1,规则表!$F$17),0)<0)*IFERROR(FFSET(X39,0,-(规则表!$F$17-1),1,规则表!$F$17),0))} -> 10
C76: P5 | I76: {=SUM(OFFSET(I8,0,-(COLUMN()-1),1,COLUMN()-规则表!$C$17))-SUM(OFFSET(I24,0,-(COLUMN()-1),1,COLUMN()))+SUM(OFFSET(I40,0,-(COLUMN()-1),1,COLUMN()-规则表!$F$17))+SUMPRODUCT((IFERROR(OFFSET(I40,0,-(规则表!$F$17-1),1,规则表!$F$17),0)<0)*IFERROR(FFSET(I40,0,-(规则表!$F$17-1),1,规则表!$F$17),0))} -> 0 | J76: {=SUM(OFFSET(J8,0,-(COLUMN()-1),1,COLUMN()-规则表!$C$17))-SUM(OFFSET(J24,0,-(COLUMN()-1),1,COLUMN()))+SUM(OFFSET(J40,0,-(COLUMN()-1),1,COLUMN()-规则表!$F$17))+SUMPRODUCT((IFERROR(OFFSET(J40,0,-(规则表!$F$17-1),1,规则表!$F$17),0)<0)*IFERROR(FFSET(J40,0,-(规则表!$F$17-1),1,规则表!$F$17),0))} -> 0 | K76: {=SUM(OFFSET(K8,0,-(COLUMN()-1),1,COLUMN()-规则表!$C$17))-SUM(OFFSET(K24,0,-(COLUMN()-1),1,COLUMN()))+SUM(OFFSET(K40,0,-(COLUMN()-1),1,COLUMN()-规则表!$F$17))+SUMPRODUCT((IFERROR(OFFSET(K40,0,-(规则表!$F$17-1),1,规则表!$F$17),0)<0)*IFERROR(FFSET(K40,0,-(规则表!$F$17-1),1,规则表!$F$17),0))} -> 0 | L76: {=SUM(OFFSET(L8,0,-(COLUMN()-1),1,COLUMN()-规则表!$C$17))-SUM(OFFSET(L24,0,-(COLUMN()-1),1,COLUMN()))+SUM(OFFSET(L40,0,-(COLUMN()-1),1,COLUMN()-规则表!$F$17))+SUMPRODUCT((IFERROR(OFFSET(L40,0,-(规则表!$F$17-1),1,规则表!$F$17),0)<0)*IFERROR(FFSET(L40,0,-(规则表!$F$17-1),1,规则表!$F$17),0))} -> 0 | M76: {=SUM(OFFSET(M8,0,-(COLUMN()-1),1,COLUMN()-规则表!$C$17))-SUM(OFFSET(M24,0,-(COLUMN()-1),1,COLUMN()))+SUM(OFFSET(M40,0,-(COLUMN()-1),1,COLUMN()-规则表!$F$17))+SUMPRODUCT((IFERROR(OFFSET(M40,0,-(规则表!$F$17-1),1,规则表!$F$17),0)<0)*IFERROR(FFSET(M40,0,-(规则表!$F$17-1),1,规则表!$F$17),0))} -> 0 | N76: {=SUM(OFFSET(N8,0,-(COLUMN()-1),1,COLUMN()-规则表!$C$17))-SUM(OFFSET(N24,0,-(COLUMN()-1),1,COLUMN()))+SUM(OFFSET(N40,0,-(COLUMN()-1),1,COLUMN()-规则表!$F$17))+SUMPRODUCT((IFERROR(OFFSET(N40,0,-(规则表!$F$17-1),1,规则表!$F$17),0)<0)*IFERROR(FFSET(N40,0,-(规则表!$F$17-1),1,规则表!$F$17),0))} -> 0 | O76: {=SUM(OFFSET(O8,0,-(COLUMN()-1),1,COLUMN()-规则表!$C$17))-SUM(OFFSET(O24,0,-(COLUMN()-1),1,COLUMN()))+SUM(OFFSET(O40,0,-(COLUMN()-1),1,COLUMN()-规则表!$F$17))+SUMPRODUCT((IFERROR(OFFSET(O40,0,-(规则表!$F$17-1),1,规则表!$F$17),0)<0)*IFERROR(FFSET(O40,0,-(规则表!$F$17-1),1,规则表!$F$17),0))} -> 0 | P76: {=SUM(OFFSET(P8,0,-(COLUMN()-1),1,COLUMN()-规则表!$C$17))-SUM(OFFSET(P24,0,-(COLUMN()-1),1,COLUMN()))+SUM(OFFSET(P40,0,-(COLUMN()-1),1,COLUMN()-规则表!$F$17))+SUMPRODUCT((IFERROR(OFFSET(P40,0,-(规则表!$F$17-1),1,规则表!$F$17),0)<0)*IFERROR(FFSET(P40,0,-(规则表!$F$17-1),1,规则表!$F$17),0))} -> 0 | ... X76: {=SUM(OFFSET(X8,0,-(COLUMN()-1),1,COLUMN()-规则表!$C$17))-SUM(OFFSET(X24,0,-(COLUMN()-1),1,COLUMN()))+SUM(OFFSET(X40,0,-(COLUMN()-1),1,COLUMN()-规则表!$F$17))+SUMPRODUCT((IFERROR(OFFSET(X40,0,-(规则表!$F$17-1),1,规则表!$F$17),0)<0)*IFERROR(FFSET(X40,0,-(规则表!$F$17-1),1,规则表!$F$17),0))} -> 0
B77: 自动线 | C77: P1 | I77: {=SUM(OFFSET(I9,0,-(COLUMN()-1),1,COLUMN()-规则表!$C$18))-SUM(OFFSET(I25,0,-(COLUMN()-1),1,COLUMN()))+SUM(OFFSET(I41,0,-(COLUMN()-1),1,COLUMN()-规则表!$F$18))+SUMPRODUCT((IFERROR(OFFSET(I41,0,-(规则表!$F$18-1),1,规则表!$F$18),0)<0)*IFERROR(FFSET(I41,0,-(规则表!$F$18-1),1,规则表!$F$18),0))} -> 0 | J77: {=SUM(OFFSET(J9,0,-(COLUMN()-1),1,COLUMN()-规则表!$C$18))-SUM(OFFSET(J25,0,-(COLUMN()-1),1,COLUMN()))+SUM(OFFSET(J41,0,-(COLUMN()-1),1,COLUMN()-规则表!$F$18))+SUMPRODUCT((IFERROR(OFFSET(J41,0,-(规则表!$F$18-1),1,规则表!$F$18),0)<0)*IFERROR(FFSET(J41,0,-(规则表!$F$18-1),1,规则表!$F$18),0))} -> 0 | K77: {=SUM(OFFSET(K9,0,-(COLUMN()-1),1,COLUMN()-规则表!$C$18))-SUM(OFFSET(K25,0,-(COLUMN()-1),1,COLUMN()))+SUM(OFFSET(K41,0,-(COLUMN()-1),1,COLUMN()-规则表!$F$18))+SUMPRODUCT((IFERROR(OFFSET(K41,0,-(规则表!$F$18-1),1,规则表!$F$18),0)<0)*IFERROR(FFSET(K41,0,-(规则表!$F$18-1),1,规则表!$F$18),0))} -> 0 | L77: {=SUM(OFFSET(L9,0,-(COLUMN()-1),1,COLUMN()-规则表!$C$18))-SUM(OFFSET(L25,0,-(COLUMN()-1),1,COLUMN()))+SUM(OFFSET(L41,0,-(COLUMN()-1),1,COLUMN()-规则表!$F$18))+SUMPRODUCT((IFERROR(OFFSET(L41,0,-(规则表!$F$18-1),1,规则表!$F$18),0)<0)*IFERROR(FFSET(L41,0,-(规则表!$F$18-1),1,规则表!$F$18),0))} -> 0 | M77: {=SUM(OFFSET(M9,0,-(COLUMN()-1),1,COLUMN()-规则表!$C$18))-SUM(OFFSET(M25,0,-(COLUMN()-1),1,COLUMN()))+SUM(OFFSET(M41,0,-(COLUMN()-1),1,COLUMN()-规则表!$F$18))+SUMPRODUCT((IFERROR(OFFSET(M41,0,-(规则表!$F$18-1),1,规则表!$F$18),0)<0)*IFERROR(FFSET(M41,0,-(规则表!$F$18-1),1,规则表!$F$18),0))} -> 0 | N77: {=SUM(OFFSET(N9,0,-(COLUMN()-1),1,COLUMN()-规则表!$C$18))-SUM(OFFSET(N25,0,-(COLUMN()-1),1,COLUMN()))+SUM(OFFSET(N41,0,-(COLUMN()-1),1,COLUMN()-规则表!$F$18))+SUMPRODUCT((IFERROR(OFFSET(N41,0,-(规则表!$F$18-1),1,规则表!$F$18),0)<0)*IFERROR(FFSET(N41,0,-(规则表!$F$18-1),1,规则表!$F$18),0))} -> 0 | O77: {=SUM(OFFSET(O9,0,-(COLUMN()-1),1,COLUMN()-规则表!$C$18))-SUM(OFFSET(O25,0,-(COLUMN()-1),1,COLUMN()))+SUM(OFFSET(O41,0,-(COLUMN()-1),1,COLUMN()-规则表!$F$18))+SUMPRODUCT((IFERROR(OFFSET(O41,0,-(规则表!$F$18-1),1,规则表!$F$18),0)<0)*IFERROR(FFSET(O41,0,-(规则表!$F$18-1),1,规则表!$F$18),0))} -> 0 | P77: {=SUM(OFFSET(P9,0,-(COLUMN()-1),1,COLUMN()-规则表!$C$18))-SUM(OFFSET(P25,0,-(COLUMN()-1),1,COLUMN()))+SUM(OFFSET(P41,0,-(COLUMN()-1),1,COLUMN()-规则表!$F$18))+SUMPRODUCT((IFERROR(OFFSET(P41,0,-(规则表!$F$18-1),1,规则表!$F$18),0)<0)*IFERROR(FFSET(P41,0,-(规则表!$F$18-1),1,规则表!$F$18),0))} -> 0 | ... X77: {=SUM(OFFSET(X9,0,-(COLUMN()-1),1,COLUMN()-规则表!$C$18))-SUM(OFFSET(X25,0,-(COLUMN()-1),1,COLUMN()))+SUM(OFFSET(X41,0,-(COLUMN()-1),1,COLUMN()-规则表!$F$18))+SUMPRODUCT((IFERROR(OFFSET(X41,0,-(规则表!$F$18-1),1,规则表!$F$18),0)<0)*IFERROR(FFSET(X41,0,-(规则表!$F$18-1),1,规则表!$F$18),0))} -> 0
C78: P2 | I78: {=SUM(OFFSET(I10,0,-(COLUMN()-1),1,COLUMN()-规则表!$C$18))-SUM(OFFSET(I26,0,-(COLUMN()-1),1,COLUMN()))+SUM(OFFSET(I42,0,-(COLUMN()-1),1,COLUMN()-规则表!$F$18))+SUMPRODUCT((IFERROR(OFFSET(I42,0,-(规则表!$F$18-1),1,规则表!$F$18),0)<0)*IFERROR(FFSET(I42,0,-(规则表!$F$18-1),1,规则表!$F$18),0))} -> 0 | J78: {=SUM(OFFSET(J10,0,-(COLUMN()-1),1,COLUMN()-规则表!$C$18))-SUM(OFFSET(J26,0,-(COLUMN()-1),1,COLUMN()))+SUM(OFFSET(J42,0,-(COLUMN()-1),1,COLUMN()-规则表!$F$18))+SUMPRODUCT((IFERROR(OFFSET(J42,0,-(规则表!$F$18-1),1,规则表!$F$18),0)<0)*IFERROR(FFSET(J42,0,-(规则表!$F$18-1),1,规则表!$F$18),0))} -> 0 | K78: {=SUM(OFFSET(K10,0,-(COLUMN()-1),1,COLUMN()-规则表!$C$18))-SUM(OFFSET(K26,0,-(COLUMN()-1),1,COLUMN()))+SUM(OFFSET(K42,0,-(COLUMN()-1),1,COLUMN()-规则表!$F$18))+SUMPRODUCT((IFERROR(OFFSET(K42,0,-(规则表!$F$18-1),1,规则表!$F$18),0)<0)*IFERROR(FFSET(K42,0,-(规则表!$F$18-1),1,规则表!$F$18),0))} -> 0 | L78: {=SUM(OFFSET(L10,0,-(COLUMN()-1),1,COLUMN()-规则表!$C$18))-SUM(OFFSET(L26,0,-(COLUMN()-1),1,COLUMN()))+SUM(OFFSET(L42,0,-(COLUMN()-1),1,COLUMN()-规则表!$F$18))+SUMPRODUCT((IFERROR(OFFSET(L42,0,-(规则表!$F$18-1),1,规则表!$F$18),0)<0)*IFERROR(FFSET(L42,0,-(规则表!$F$18-1),1,规则表!$F$18),0))} -> 0 | M78: {=SUM(OFFSET(M10,0,-(COLUMN()-1),1,COLUMN()-规则表!$C$18))-SUM(OFFSET(M26,0,-(COLUMN()-1),1,COLUMN()))+SUM(OFFSET(M42,0,-(COLUMN()-1),1,COLUMN()-规则表!$F$18))+SUMPRODUCT((IFERROR(OFFSET(M42,0,-(规则表!$F$18-1),1,规则表!$F$18),0)<0)*IFERROR(FFSET(M42,0,-(规则表!$F$18-1),1,规则表!$F$18),0))} -> 0 | N78: {=SUM(OFFSET(N10,0,-(COLUMN()-1),1,COLUMN()-规则表!$C$18))-SUM(OFFSET(N26,0,-(COLUMN()-1),1,COLUMN()))+SUM(OFFSET(N42,0,-(COLUMN()-1),1,COLUMN()-规则表!$F$18))+SUMPRODUCT((IFERROR(OFFSET(N42,0,-(规则表!$F$18-1),1,规则表!$F$18),0)<0)*IFERROR(FFSET(N42,0,-(规则表!$F$18-1),1,规则表!$F$18),0))} -> 0 | O78: {=SUM(OFFSET(O10,0,-(COLUMN()-1),1,COLUMN()-规则表!$C$18))-SUM(OFFSET(O26,0,-(COLUMN()-1),1,COLUMN()))+SUM(OFFSET(O42,0,-(COLUMN()-1),1,COLUMN()-规则表!$F$18))+SUMPRODUCT((IFERROR(OFFSET(O42,0,-(规则表!$F$18-1),1,规则表!$F$18),0)<0)*IFERROR(FFSET(O42,0,-(规则表!$F$18-1),1,规则表!$F$18),0))} -> 0 | P78: {=SUM(OFFSET(P10,0,-(COLUMN()-1),1,COLUMN()-规则表!$C$18))-SUM(OFFSET(P26,0,-(COLUMN()-1),1,COLUMN()))+SUM(OFFSET(P42,0,-(COLUMN()-1),1,COLUMN()-规则表!$F$18))+SUMPRODUCT((IFERROR(OFFSET(P42,0,-(规则表!$F$18-1),1,规则表!$F$18),0)<0)*IFERROR(FFSET(P42,0,-(规则表!$F$18-1),1,规则表!$F$18),0))} -> 0 | ... X78: {=SUM(OFFSET(X10,0,-(COLUMN()-1),1,COLUMN()-规则表!$C$18))-SUM(OFFSET(X26,0,-(COLUMN()-1),1,COLUMN()))+SUM(OFFSET(X42,0,-(COLUMN()-1),1,COLUMN()-规则表!$F$18))+SUMPRODUCT((IFERROR(OFFSET(X42,0,-(规则表!$F$18-1),1,规则表!$F$18),0)<0)*IFERROR(FFSET(X42,0,-(规则表!$F$18-1),1,规则表!$F$18),0))} -> 0
C79: P3 | I79: {=SUM(OFFSET(I11,0,-(COLUMN()-1),1,COLUMN()-规则表!$C$18))-SUM(OFFSET(I27,0,-(COLUMN()-1),1,COLUMN()))+SUM(OFFSET(I43,0,-(COLUMN()-1),1,COLUMN()-规则表!$F$18))+SUMPRODUCT((IFERROR(OFFSET(I43,0,-(规则表!$F$18-1),1,规则表!$F$18),0)<0)*IFERROR(FFSET(I43,0,-(规则表!$F$18-1),1,规则表!$F$18),0))} -> 0 | J79: {=SUM(OFFSET(J11,0,-(COLUMN()-1),1,COLUMN()-规则表!$C$18))-SUM(OFFSET(J27,0,-(COLUMN()-1),1,COLUMN()))+SUM(OFFSET(J43,0,-(COLUMN()-1),1,COLUMN()-规则表!$F$18))+SUMPRODUCT((IFERROR(OFFSET(J43,0,-(规则表!$F$18-1),1,规则表!$F$18),0)<0)*IFERROR(FFSET(J43,0,-(规则表!$F$18-1),1,规则表!$F$18),0))} -> 0 | K79: {=SUM(OFFSET(K11,0,-(COLUMN()-1),1,COLUMN()-规则表!$C$18))-SUM(OFFSET(K27,0,-(COLUMN()-1),1,COLUMN()))+SUM(OFFSET(K43,0,-(COLUMN()-1),1,COLUMN()-规则表!$F$18))+SUMPRODUCT((IFERROR(OFFSET(K43,0,-(规则表!$F$18-1),1,规则表!$F$18),0)<0)*IFERROR(FFSET(K43,0,-(规则表!$F$18-1),1,规则表!$F$18),0))} -> 0 | L79: {=SUM(OFFSET(L11,0,-(COLUMN()-1),1,COLUMN()-规则表!$C$18))-SUM(OFFSET(L27,0,-(COLUMN()-1),1,COLUMN()))+SUM(OFFSET(L43,0,-(COLUMN()-1),1,COLUMN()-规则表!$F$18))+SUMPRODUCT((IFERROR(OFFSET(L43,0,-(规则表!$F$18-1),1,规则表!$F$18),0)<0)*IFERROR(FFSET(L43,0,-(规则表!$F$18-1),1,规则表!$F$18),0))} -> 0 | M79: {=SUM(OFFSET(M11,0,-(COLUMN()-1),1,COLUMN()-规则表!$C$18))-SUM(OFFSET(M27,0,-(COLUMN()-1),1,COLUMN()))+SUM(OFFSET(M43,0,-(COLUMN()-1),1,COLUMN()-规则表!$F$18))+SUMPRODUCT((IFERROR(OFFSET(M43,0,-(规则表!$F$18-1),1,规则表!$F$18),0)<0)*IFERROR(FFSET(M43,0,-(规则表!$F$18-1),1,规则表!$F$18),0))} -> 0 | N79: {=SUM(OFFSET(N11,0,-(COLUMN()-1),1,COLUMN()-规则表!$C$18))-SUM(OFFSET(N27,0,-(COLUMN()-1),1,COLUMN()))+SUM(OFFSET(N43,0,-(COLUMN()-1),1,COLUMN()-规则表!$F$18))+SUMPRODUCT((IFERROR(OFFSET(N43,0,-(规则表!$F$18-1),1,规则表!$F$18),0)<0)*IFERROR(FFSET(N43,0,-(规则表!$F$18-1),1,规则表!$F$18),0))} -> 0 | O79: {=SUM(OFFSET(O11,0,-(COLUMN()-1),1,COLUMN()-规则表!$C$18))-SUM(OFFSET(O27,0,-(COLUMN()-1),1,COLUMN()))+SUM(OFFSET(O43,0,-(COLUMN()-1),1,COLUMN()-规则表!$F$18))+SUMPRODUCT((IFERROR(OFFSET(O43,0,-(规则表!$F$18-1),1,规则表!$F$18),0)<0)*IFERROR(FFSET(O43,0,-(规则表!$F$18-1),1,规则表!$F$18),0))} -> 0 | P79: {=SUM(OFFSET(P11,0,-(COLUMN()-1),1,COLUMN()-规则表!$C$18))-SUM(OFFSET(P27,0,-(COLUMN()-1),1,COLUMN()))+SUM(OFFSET(P43,0,-(COLUMN()-1),1,COLUMN()-规则表!$F$18))+SUMPRODUCT((IFERROR(OFFSET(P43,0,-(规则表!$F$18-1),1,规则表!$F$18),0)<0)*IFERROR(FFSET(P43,0,-(规则表!$F$18-1),1,规则表!$F$18),0))} -> 0 | ... X79: {=SUM(OFFSET(X11,0,-(COLUMN()-1),1,COLUMN()-规则表!$C$18))-SUM(OFFSET(X27,0,-(COLUMN()-1),1,COLUMN()))+SUM(OFFSET(X43,0,-(COLUMN()-1),1,COLUMN()-规则表!$F$18))+SUMPRODUCT((IFERROR(OFFSET(X43,0,-(规则表!$F$18-1),1,规则表!$F$18),0)<0)*IFERROR(FFSET(X43,0,-(规则表!$F$18-1),1,规则表!$F$18),0))} -> 0
C80: P4 | I80: {=SUM(OFFSET(I12,0,-(COLUMN()-1),1,COLUMN()-规则表!$C$18))-SUM(OFFSET(I28,0,-(COLUMN()-1),1,COLUMN()))+SUM(OFFSET(I44,0,-(COLUMN()-1),1,COLUMN()-规则表!$F$18))+SUMPRODUCT((IFERROR(OFFSET(I44,0,-(规则表!$F$18-1),1,规则表!$F$18),0)<0)*IFERROR(FFSET(I44,0,-(规则表!$F$18-1),1,规则表!$F$18),0))} -> 0 | J80: {=SUM(OFFSET(J12,0,-(COLUMN()-1),1,COLUMN()-规则表!$C$18))-SUM(OFFSET(J28,0,-(COLUMN()-1),1,COLUMN()))+SUM(OFFSET(J44,0,-(COLUMN()-1),1,COLUMN()-规则表!$F$18))+SUMPRODUCT((IFERROR(OFFSET(J44,0,-(规则表!$F$18-1),1,规则表!$F$18),0)<0)*IFERROR(FFSET(J44,0,-(规则表!$F$18-1),1,规则表!$F$18),0))} -> 0 | K80: {=SUM(OFFSET(K12,0,-(COLUMN()-1),1,COLUMN()-规则表!$C$18))-SUM(OFFSET(K28,0,-(COLUMN()-1),1,COLUMN()))+SUM(OFFSET(K44,0,-(COLUMN()-1),1,COLUMN()-规则表!$F$18))+SUMPRODUCT((IFERROR(OFFSET(K44,0,-(规则表!$F$18-1),1,规则表!$F$18),0)<0)*IFERROR(FFSET(K44,0,-(规则表!$F$18-1),1,规则表!$F$18),0))} -> 0 | L80: {=SUM(OFFSET(L12,0,-(COLUMN()-1),1,COLUMN()-规则表!$C$18))-SUM(OFFSET(L28,0,-(COLUMN()-1),1,COLUMN()))+SUM(OFFSET(L44,0,-(COLUMN()-1),1,COLUMN()-规则表!$F$18))+SUMPRODUCT((IFERROR(OFFSET(L44,0,-(规则表!$F$18-1),1,规则表!$F$18),0)<0)*IFERROR(FFSET(L44,0,-(规则表!$F$18-1),1,规则表!$F$18),0))} -> 0 | M80: {=SUM(OFFSET(M12,0,-(COLUMN()-1),1,COLUMN()-规则表!$C$18))-SUM(OFFSET(M28,0,-(COLUMN()-1),1,COLUMN()))+SUM(OFFSET(M44,0,-(COLUMN()-1),1,COLUMN()-规则表!$F$18))+SUMPRODUCT((IFERROR(OFFSET(M44,0,-(规则表!$F$18-1),1,规则表!$F$18),0)<0)*IFERROR(FFSET(M44,0,-(规则表!$F$18-1),1,规则表!$F$18),0))} -> 0 | N80: {=SUM(OFFSET(N12,0,-(COLUMN()-1),1,COLUMN()-规则表!$C$18))-SUM(OFFSET(N28,0,-(COLUMN()-1),1,COLUMN()))+SUM(OFFSET(N44,0,-(COLUMN()-1),1,COLUMN()-规则表!$F$18))+SUMPRODUCT((IFERROR(OFFSET(N44,0,-(规则表!$F$18-1),1,规则表!$F$18),0)<0)*IFERROR(FFSET(N44,0,-(规则表!$F$18-1),1,规则表!$F$18),0))} -> 0 | O80: {=SUM(OFFSET(O12,0,-(COLUMN()-1),1,COLUMN()-规则表!$C$18))-SUM(OFFSET(O28,0,-(COLUMN()-1),1,COLUMN()))+SUM(OFFSET(O44,0,-(COLUMN()-1),1,COLUMN()-规则表!$F$18))+SUMPRODUCT((IFERROR(OFFSET(O44,0,-(规则表!$F$18-1),1,规则表!$F$18),0)<0)*IFERROR(FFSET(O44,0,-(规则表!$F$18-1),1,规则表!$F$18),0))} -> 0 | P80: {=SUM(OFFSET(P12,0,-(COLUMN()-1),1,COLUMN()-规则表!$C$18))-SUM(OFFSET(P28,0,-(COLUMN()-1),1,COLUMN()))+SUM(OFFSET(P44,0,-(COLUMN()-1),1,COLUMN()-规则表!$F$18))+SUMPRODUCT((IFERROR(OFFSET(P44,0,-(规则表!$F$18-1),1,规则表!$F$18),0)<0)*IFERROR(FFSET(P44,0,-(规则表!$F$18-1),1,规则表!$F$18),0))} -> 0 | ... X80: {=SUM(OFFSET(X12,0,-(COLUMN()-1),1,COLUMN()-规则表!$C$18))-SUM(OFFSET(X28,0,-(COLUMN()-1),1,COLUMN()))+SUM(OFFSET(X44,0,-(COLUMN()-1),1,COLUMN()-规则表!$F$18))+SUMPRODUCT((IFERROR(OFFSET(X44,0,-(规则表!$F$18-1),1,规则表!$F$18),0)<0)*IFERROR(FFSET(X44,0,-(规则表!$F$18-1),1,规则表!$F$18),0))} -> 0
C81: P5 | I81: {=SUM(OFFSET(I13,0,-(COLUMN()-1),1,COLUMN()-规则表!$C$18))-SUM(OFFSET(I29,0,-(COLUMN()-1),1,COLUMN()))+SUM(OFFSET(I45,0,-(COLUMN()-1),1,COLUMN()-规则表!$F$18))+SUMPRODUCT((IFERROR(OFFSET(I45,0,-(规则表!$F$18-1),1,规则表!$F$18),0)<0)*IFERROR(FFSET(I45,0,-(规则表!$F$18-1),1,规则表!$F$18),0))} -> 0 | J81: {=SUM(OFFSET(J13,0,-(COLUMN()-1),1,COLUMN()-规则表!$C$18))-SUM(OFFSET(J29,0,-(COLUMN()-1),1,COLUMN()))+SUM(OFFSET(J45,0,-(COLUMN()-1),1,COLUMN()-规则表!$F$18))+SUMPRODUCT((IFERROR(OFFSET(J45,0,-(规则表!$F$18-1),1,规则表!$F$18),0)<0)*IFERROR(FFSET(J45,0,-(规则表!$F$18-1),1,规则表!$F$18),0))} -> 0 | K81: {=SUM(OFFSET(K13,0,-(COLUMN()-1),1,COLUMN()-规则表!$C$18))-SUM(OFFSET(K29,0,-(COLUMN()-1),1,COLUMN()))+SUM(OFFSET(K45,0,-(COLUMN()-1),1,COLUMN()-规则表!$F$18))+SUMPRODUCT((IFERROR(OFFSET(K45,0,-(规则表!$F$18-1),1,规则表!$F$18),0)<0)*IFERROR(FFSET(K45,0,-(规则表!$F$18-1),1,规则表!$F$18),0))} -> 0 | L81: {=SUM(OFFSET(L13,0,-(COLUMN()-1),1,COLUMN()-规则表!$C$18))-SUM(OFFSET(L29,0,-(COLUMN()-1),1,COLUMN()))+SUM(OFFSET(L45,0,-(COLUMN()-1),1,COLUMN()-规则表!$F$18))+SUMPRODUCT((IFERROR(OFFSET(L45,0,-(规则表!$F$18-1),1,规则表!$F$18),0)<0)*IFERROR(FFSET(L45,0,-(规则表!$F$18-1),1,规则表!$F$18),0))} -> 0 | M81: {=SUM(OFFSET(M13,0,-(COLUMN()-1),1,COLUMN()-规则表!$C$18))-SUM(OFFSET(M29,0,-(COLUMN()-1),1,COLUMN()))+SUM(OFFSET(M45,0,-(COLUMN()-1),1,COLUMN()-规则表!$F$18))+SUMPRODUCT((IFERROR(OFFSET(M45,0,-(规则表!$F$18-1),1,规则表!$F$18),0)<0)*IFERROR(FFSET(M45,0,-(规则表!$F$18-1),1,规则表!$F$18),0))} -> 0 | N81: {=SUM(OFFSET(N13,0,-(COLUMN()-1),1,COLUMN()-规则表!$C$18))-SUM(OFFSET(N29,0,-(COLUMN()-1),1,COLUMN()))+SUM(OFFSET(N45,0,-(COLUMN()-1),1,COLUMN()-规则表!$F$18))+SUMPRODUCT((IFERROR(OFFSET(N45,0,-(规则表!$F$18-1),1,规则表!$F$18),0)<0)*IFERROR(FFSET(N45,0,-(规则表!$F$18-1),1,规则表!$F$18),0))} -> 0 | O81: {=SUM(OFFSET(O13,0,-(COLUMN()-1),1,COLUMN()-规则表!$C$18))-SUM(OFFSET(O29,0,-(COLUMN()-1),1,COLUMN()))+SUM(OFFSET(O45,0,-(COLUMN()-1),1,COLUMN()-规则表!$F$18))+SUMPRODUCT((IFERROR(OFFSET(O45,0,-(规则表!$F$18-1),1,规则表!$F$18),0)<0)*IFERROR(FFSET(O45,0,-(规则表!$F$18-1),1,规则表!$F$18),0))} -> 0 | P81: {=SUM(OFFSET(P13,0,-(COLUMN()-1),1,COLUMN()-规则表!$C$18))-SUM(OFFSET(P29,0,-(COLUMN()-1),1,COLUMN()))+SUM(OFFSET(P45,0,-(COLUMN()-1),1,COLUMN()-规则表!$F$18))+SUMPRODUCT((IFERROR(OFFSET(P45,0,-(规则表!$F$18-1),1,规则表!$F$18),0)<0)*IFERROR(FFSET(P45,0,-(规则表!$F$18-1),1,规则表!$F$18),0))} -> 0 | ... X81: {=SUM(OFFSET(X13,0,-(COLUMN()-1),1,COLUMN()-规则表!$C$18))-SUM(OFFSET(X29,0,-(COLUMN()-1),1,COLUMN()))+SUM(OFFSET(X45,0,-(COLUMN()-1),1,COLUMN()-规则表!$F$18))+SUMPRODUCT((IFERROR(OFFSET(X45,0,-(规则表!$F$18-1),1,规则表!$F$18),0)<0)*IFERROR(FFSET(X45,0,-(规则表!$F$18-1),1,规则表!$F$18),0))} -> 0
B82: 智能线 | C82: P1 | I82: {=SUM(OFFSET(I14,0,-(COLUMN()-1),1,COLUMN()-规则表!$C$19))-SUM(OFFSET(I30,0,-(COLUMN()-1),1,COLUMN()))+SUM(OFFSET(I46,0,-(COLUMN()-1),1,COLUMN()-规则表!$F$19))+SUMPRODUCT((IFERROR(OFFSET(I46,0,-(规则表!$F$19-1),1,规则表!$F$18),0)<0)*IFERROR(FFSET(I46,0,-(规则表!$F$19-1),1,规则表!$F$19),0))} -> 0 | J82: {=SUM(OFFSET(J14,0,-(COLUMN()-1),1,COLUMN()-规则表!$C$19))-SUM(OFFSET(J30,0,-(COLUMN()-1),1,COLUMN()))+SUM(OFFSET(J46,0,-(COLUMN()-1),1,COLUMN()-规则表!$F$19))+SUMPRODUCT((IFERROR(OFFSET(J46,0,-(规则表!$F$19-1),1,规则表!$F$18),0)<0)*IFERROR(FFSET(J46,0,-(规则表!$F$19-1),1,规则表!$F$19),0))} -> 0 | K82: {=SUM(OFFSET(K14,0,-(COLUMN()-1),1,COLUMN()-规则表!$C$19))-SUM(OFFSET(K30,0,-(COLUMN()-1),1,COLUMN()))+SUM(OFFSET(K46,0,-(COLUMN()-1),1,COLUMN()-规则表!$F$19))+SUMPRODUCT((IFERROR(OFFSET(K46,0,-(规则表!$F$19-1),1,规则表!$F$18),0)<0)*IFERROR(FFSET(K46,0,-(规则表!$F$19-1),1,规则表!$F$19),0))} -> 0 | L82: {=SUM(OFFSET(L14,0,-(COLUMN()-1),1,COLUMN()-规则表!$C$19))-SUM(OFFSET(L30,0,-(COLUMN()-1),1,COLUMN()))+SUM(OFFSET(L46,0,-(COLUMN()-1),1,COLUMN()-规则表!$F$19))+SUMPRODUCT((IFERROR(OFFSET(L46,0,-(规则表!$F$19-1),1,规则表!$F$18),0)<0)*IFERROR(FFSET(L46,0,-(规则表!$F$19-1),1,规则表!$F$19),0))} -> 0 | M82: {=SUM(OFFSET(M14,0,-(COLUMN()-1),1,COLUMN()-规则表!$C$19))-SUM(OFFSET(M30,0,-(COLUMN()-1),1,COLUMN()))+SUM(OFFSET(M46,0,-(COLUMN()-1),1,COLUMN()-规则表!$F$19))+SUMPRODUCT((IFERROR(OFFSET(M46,0,-(规则表!$F$19-1),1,规则表!$F$18),0)<0)*IFERROR(FFSET(M46,0,-(规则表!$F$19-1),1,规则表!$F$19),0))} -> 0 | N82: {=SUM(OFFSET(N14,0,-(COLUMN()-1),1,COLUMN()-规则表!$C$19))-SUM(OFFSET(N30,0,-(COLUMN()-1),1,COLUMN()))+SUM(OFFSET(N46,0,-(COLUMN()-1),1,COLUMN()-规则表!$F$19))+SUMPRODUCT((IFERROR(OFFSET(N46,0,-(规则表!$F$19-1),1,规则表!$F$18),0)<0)*IFERROR(FFSET(N46,0,-(规则表!$F$19-1),1,规则表!$F$19),0))} -> 0 | O82: {=SUM(OFFSET(O14,0,-(COLUMN()-1),1,COLUMN()-规则表!$C$19))-SUM(OFFSET(O30,0,-(COLUMN()-1),1,COLUMN()))+SUM(OFFSET(O46,0,-(COLUMN()-1),1,COLUMN()-规则表!$F$19))+SUMPRODUCT((IFERROR(OFFSET(O46,0,-(规则表!$F$19-1),1,规则表!$F$18),0)<0)*IFERROR(FFSET(O46,0,-(规则表!$F$19-1),1,规则表!$F$19),0))} -> 0 | P82: {=SUM(OFFSET(P14,0,-(COLUMN()-1),1,COLUMN()-规则表!$C$19))-SUM(OFFSET(P30,0,-(COLUMN()-1),1,COLUMN()))+SUM(OFFSET(P46,0,-(COLUMN()-1),1,COLUMN()-规则表!$F$19))+SUMPRODUCT((IFERROR(OFFSET(P46,0,-(规则表!$F$19-1),1,规则表!$F$18),0)<0)*IFERROR(FFSET(P46,0,-(规则表!$F$19-1),1,规则表!$F$19),0))} -> 0 | ... X82: {=SUM(OFFSET(X14,0,-(COLUMN()-1),1,COLUMN()-规则表!$C$19))-SUM(OFFSET(X30,0,-(COLUMN()-1),1,COLUMN()))+SUM(OFFSET(X46,0,-(COLUMN()-1),1,COLUMN()-规则表!$F$19))+SUMPRODUCT((IFERROR(OFFSET(X46,0,-(规则表!$F$19-1),1,规则表!$F$18),0)<0)*IFERROR(FFSET(X46,0,-(规则表!$F$19-1),1,规则表!$F$19),0))} -> 0
C83: P2 | I83: {=SUM(OFFSET(I15,0,-(COLUMN()-1),1,COLUMN()-规则表!$C$19))-SUM(OFFSET(I31,0,-(COLUMN()-1),1,COLUMN()))+SUM(OFFSET(I47,0,-(COLUMN()-1),1,COLUMN()-规则表!$F$19))+SUMPRODUCT((IFERROR(OFFSET(I47,0,-(规则表!$F$19-1),1,规则表!$F$18),0)<0)*IFERROR(FFSET(I47,0,-(规则表!$F$19-1),1,规则表!$F$19),0))} -> 0 | J83: {=SUM(OFFSET(J15,0,-(COLUMN()-1),1,COLUMN()-规则表!$C$19))-SUM(OFFSET(J31,0,-(COLUMN()-1),1,COLUMN()))+SUM(OFFSET(J47,0,-(COLUMN()-1),1,COLUMN()-规则表!$F$19))+SUMPRODUCT((IFERROR(OFFSET(J47,0,-(规则表!$F$19-1),1,规则表!$F$18),0)<0)*IFERROR(FFSET(J47,0,-(规则表!$F$19-1),1,规则表!$F$19),0))} -> 0 | K83: {=SUM(OFFSET(K15,0,-(COLUMN()-1),1,COLUMN()-规则表!$C$19))-SUM(OFFSET(K31,0,-(COLUMN()-1),1,COLUMN()))+SUM(OFFSET(K47,0,-(COLUMN()-1),1,COLUMN()-规则表!$F$19))+SUMPRODUCT((IFERROR(OFFSET(K47,0,-(规则表!$F$19-1),1,规则表!$F$18),0)<0)*IFERROR(FFSET(K47,0,-(规则表!$F$19-1),1,规则表!$F$19),0))} -> 0 | L83: {=SUM(OFFSET(L15,0,-(COLUMN()-1),1,COLUMN()-规则表!$C$19))-SUM(OFFSET(L31,0,-(COLUMN()-1),1,COLUMN()))+SUM(OFFSET(L47,0,-(COLUMN()-1),1,COLUMN()-规则表!$F$19))+SUMPRODUCT((IFERROR(OFFSET(L47,0,-(规则表!$F$19-1),1,规则表!$F$18),0)<0)*IFERROR(FFSET(L47,0,-(规则表!$F$19-1),1,规则表!$F$19),0))} -> 0 | M83: {=SUM(OFFSET(M15,0,-(COLUMN()-1),1,COLUMN()-规则表!$C$19))-SUM(OFFSET(M31,0,-(COLUMN()-1),1,COLUMN()))+SUM(OFFSET(M47,0,-(COLUMN()-1),1,COLUMN()-规则表!$F$19))+SUMPRODUCT((IFERROR(OFFSET(M47,0,-(规则表!$F$19-1),1,规则表!$F$18),0)<0)*IFERROR(FFSET(M47,0,-(规则表!$F$19-1),1,规则表!$F$19),0))} -> 0 | N83: {=SUM(OFFSET(N15,0,-(COLUMN()-1),1,COLUMN()-规则表!$C$19))-SUM(OFFSET(N31,0,-(COLUMN()-1),1,COLUMN()))+SUM(OFFSET(N47,0,-(COLUMN()-1),1,COLUMN()-规则表!$F$19))+SUMPRODUCT((IFERROR(OFFSET(N47,0,-(规则表!$F$19-1),1,规则表!$F$18),0)<0)*IFERROR(FFSET(N47,0,-(规则表!$F$19-1),1,规则表!$F$19),0))} -> 0 | O83: {=SUM(OFFSET(O15,0,-(COLUMN()-1),1,COLUMN()-规则表!$C$19))-SUM(OFFSET(O31,0,-(COLUMN()-1),1,COLUMN()))+SUM(OFFSET(O47,0,-(COLUMN()-1),1,COLUMN()-规则表!$F$19))+SUMPRODUCT((IFERROR(OFFSET(O47,0,-(规则表!$F$19-1),1,规则表!$F$18),0)<0)*IFERROR(FFSET(O47,0,-(规则表!$F$19-1),1,规则表!$F$19),0))} -> 0 | P83: {=SUM(OFFSET(P15,0,-(COLUMN()-1),1,COLUMN()-规则表!$C$19))-SUM(OFFSET(P31,0,-(COLUMN()-1),1,COLUMN()))+SUM(OFFSET(P47,0,-(COLUMN()-1),1,COLUMN()-规则表!$F$19))+SUMPRODUCT((IFERROR(OFFSET(P47,0,-(规则表!$F$19-1),1,规则表!$F$18),0)<0)*IFERROR(FFSET(P47,0,-(规则表!$F$19-1),1,规则表!$F$19),0))} -> 0 | ... X83: {=SUM(OFFSET(X15,0,-(COLUMN()-1),1,COLUMN()-规则表!$C$19))-SUM(OFFSET(X31,0,-(COLUMN()-1),1,COLUMN()))+SUM(OFFSET(X47,0,-(COLUMN()-1),1,COLUMN()-规则表!$F$19))+SUMPRODUCT((IFERROR(OFFSET(X47,0,-(规则表!$F$19-1),1,规则表!$F$18),0)<0)*IFERROR(FFSET(X47,0,-(规则表!$F$19-1),1,规则表!$F$19),0))} -> 0
C84: P3 | I84: {=SUM(OFFSET(I16,0,-(COLUMN()-1),1,COLUMN()-规则表!$C$19))-SUM(OFFSET(I32,0,-(COLUMN()-1),1,COLUMN()))+SUM(OFFSET(I48,0,-(COLUMN()-1),1,COLUMN()-规则表!$F$19))+SUMPRODUCT((IFERROR(OFFSET(I48,0,-(规则表!$F$19-1),1,规则表!$F$18),0)<0)*IFERROR(FFSET(I48,0,-(规则表!$F$19-1),1,规则表!$F$19),0))} -> 0 | J84: {=SUM(OFFSET(J16,0,-(COLUMN()-1),1,COLUMN()-规则表!$C$19))-SUM(OFFSET(J32,0,-(COLUMN()-1),1,COLUMN()))+SUM(OFFSET(J48,0,-(COLUMN()-1),1,COLUMN()-规则表!$F$19))+SUMPRODUCT((IFERROR(OFFSET(J48,0,-(规则表!$F$19-1),1,规则表!$F$18),0)<0)*IFERROR(FFSET(J48,0,-(规则表!$F$19-1),1,规则表!$F$19),0))} -> 0 | K84: {=SUM(OFFSET(K16,0,-(COLUMN()-1),1,COLUMN()-规则表!$C$19))-SUM(OFFSET(K32,0,-(COLUMN()-1),1,COLUMN()))+SUM(OFFSET(K48,0,-(COLUMN()-1),1,COLUMN()-规则表!$F$19))+SUMPRODUCT((IFERROR(OFFSET(K48,0,-(规则表!$F$19-1),1,规则表!$F$18),0)<0)*IFERROR(FFSET(K48,0,-(规则表!$F$19-1),1,规则表!$F$19),0))} -> 0 | L84: {=SUM(OFFSET(L16,0,-(COLUMN()-1),1,COLUMN()-规则表!$C$19))-SUM(OFFSET(L32,0,-(COLUMN()-1),1,COLUMN()))+SUM(OFFSET(L48,0,-(COLUMN()-1),1,COLUMN()-规则表!$F$19))+SUMPRODUCT((IFERROR(OFFSET(L48,0,-(规则表!$F$19-1),1,规则表!$F$18),0)<0)*IFERROR(FFSET(L48,0,-(规则表!$F$19-1),1,规则表!$F$19),0))} -> 0 | M84: {=SUM(OFFSET(M16,0,-(COLUMN()-1),1,COLUMN()-规则表!$C$19))-SUM(OFFSET(M32,0,-(COLUMN()-1),1,COLUMN()))+SUM(OFFSET(M48,0,-(COLUMN()-1),1,COLUMN()-规则表!$F$19))+SUMPRODUCT((IFERROR(OFFSET(M48,0,-(规则表!$F$19-1),1,规则表!$F$18),0)<0)*IFERROR(FFSET(M48,0,-(规则表!$F$19-1),1,规则表!$F$19),0))} -> 0 | N84: {=SUM(OFFSET(N16,0,-(COLUMN()-1),1,COLUMN()-规则表!$C$19))-SUM(OFFSET(N32,0,-(COLUMN()-1),1,COLUMN()))+SUM(OFFSET(N48,0,-(COLUMN()-1),1,COLUMN()-规则表!$F$19))+SUMPRODUCT((IFERROR(OFFSET(N48,0,-(规则表!$F$19-1),1,规则表!$F$18),0)<0)*IFERROR(FFSET(N48,0,-(规则表!$F$19-1),1,规则表!$F$19),0))} -> 0 | O84: {=SUM(OFFSET(O16,0,-(COLUMN()-1),1,COLUMN()-规则表!$C$19))-SUM(OFFSET(O32,0,-(COLUMN()-1),1,COLUMN()))+SUM(OFFSET(O48,0,-(COLUMN()-1),1,COLUMN()-规则表!$F$19))+SUMPRODUCT((IFERROR(OFFSET(O48,0,-(规则表!$F$19-1),1,规则表!$F$18),0)<0)*IFERROR(FFSET(O48,0,-(规则表!$F$19-1),1,规则表!$F$19),0))} -> 0 | P84: {=SUM(OFFSET(P16,0,-(COLUMN()-1),1,COLUMN()-规则表!$C$19))-SUM(OFFSET(P32,0,-(COLUMN()-1),1,COLUMN()))+SUM(OFFSET(P48,0,-(COLUMN()-1),1,COLUMN()-规则表!$F$19))+SUMPRODUCT((IFERROR(OFFSET(P48,0,-(规则表!$F$19-1),1,规则表!$F$18),0)<0)*IFERROR(FFSET(P48,0,-(规则表!$F$19-1),1,规则表!$F$19),0))} -> 0 | ... X84: {=SUM(OFFSET(X16,0,-(COLUMN()-1),1,COLUMN()-规则表!$C$19))-SUM(OFFSET(X32,0,-(COLUMN()-1),1,COLUMN()))+SUM(OFFSET(X48,0,-(COLUMN()-1),1,COLUMN()-规则表!$F$19))+SUMPRODUCT((IFERROR(OFFSET(X48,0,-(规则表!$F$19-1),1,规则表!$F$18),0)<0)*IFERROR(FFSET(X48,0,-(规则表!$F$19-1),1,规则表!$F$19),0))} -> 0
C85: P4 | I85: {=SUM(OFFSET(I17,0,-(COLUMN()-1),1,COLUMN()-规则表!$C$19))-SUM(OFFSET(I33,0,-(COLUMN()-1),1,COLUMN()))+SUM(OFFSET(I49,0,-(COLUMN()-1),1,COLUMN()-规则表!$F$19))+SUMPRODUCT((IFERROR(OFFSET(I49,0,-(规则表!$F$19-1),1,规则表!$F$18),0)<0)*IFERROR(FFSET(I49,0,-(规则表!$F$19-1),1,规则表!$F$19),0))} -> 0 | J85: {=SUM(OFFSET(J17,0,-(COLUMN()-1),1,COLUMN()-规则表!$C$19))-SUM(OFFSET(J33,0,-(COLUMN()-1),1,COLUMN()))+SUM(OFFSET(J49,0,-(COLUMN()-1),1,COLUMN()-规则表!$F$19))+SUMPRODUCT((IFERROR(OFFSET(J49,0,-(规则表!$F$19-1),1,规则表!$F$18),0)<0)*IFERROR(FFSET(J49,0,-(规则表!$F$19-1),1,规则表!$F$19),0))} -> 0 | K85: {=SUM(OFFSET(K17,0,-(COLUMN()-1),1,COLUMN()-规则表!$C$19))-SUM(OFFSET(K33,0,-(COLUMN()-1),1,COLUMN()))+SUM(OFFSET(K49,0,-(COLUMN()-1),1,COLUMN()-规则表!$F$19))+SUMPRODUCT((IFERROR(OFFSET(K49,0,-(规则表!$F$19-1),1,规则表!$F$18),0)<0)*IFERROR(FFSET(K49,0,-(规则表!$F$19-1),1,规则表!$F$19),0))} -> 0 | L85: {=SUM(OFFSET(L17,0,-(COLUMN()-1),1,COLUMN()-规则表!$C$19))-SUM(OFFSET(L33,0,-(COLUMN()-1),1,COLUMN()))+SUM(OFFSET(L49,0,-(COLUMN()-1),1,COLUMN()-规则表!$F$19))+SUMPRODUCT((IFERROR(OFFSET(L49,0,-(规则表!$F$19-1),1,规则表!$F$18),0)<0)*IFERROR(FFSET(L49,0,-(规则表!$F$19-1),1,规则表!$F$19),0))} -> 0 | M85: {=SUM(OFFSET(M17,0,-(COLUMN()-1),1,COLUMN()-规则表!$C$19))-SUM(OFFSET(M33,0,-(COLUMN()-1),1,COLUMN()))+SUM(OFFSET(M49,0,-(COLUMN()-1),1,COLUMN()-规则表!$F$19))+SUMPRODUCT((IFERROR(OFFSET(M49,0,-(规则表!$F$19-1),1,规则表!$F$18),0)<0)*IFERROR(FFSET(M49,0,-(规则表!$F$19-1),1,规则表!$F$19),0))} -> 0 | N85: {=SUM(OFFSET(N17,0,-(COLUMN()-1),1,COLUMN()-规则表!$C$19))-SUM(OFFSET(N33,0,-(COLUMN()-1),1,COLUMN()))+SUM(OFFSET(N49,0,-(COLUMN()-1),1,COLUMN()-规则表!$F$19))+SUMPRODUCT((IFERROR(OFFSET(N49,0,-(规则表!$F$19-1),1,规则表!$F$18),0)<0)*IFERROR(FFSET(N49,0,-(规则表!$F$19-1),1,规则表!$F$19),0))} -> 0 | O85: {=SUM(OFFSET(O17,0,-(COLUMN()-1),1,COLUMN()-规则表!$C$19))-SUM(OFFSET(O33,0,-(COLUMN()-1),1,COLUMN()))+SUM(OFFSET(O49,0,-(COLUMN()-1),1,COLUMN()-规则表!$F$19))+SUMPRODUCT((IFERROR(OFFSET(O49,0,-(规则表!$F$19-1),1,规则表!$F$18),0)<0)*IFERROR(FFSET(O49,0,-(规则表!$F$19-1),1,规则表!$F$19),0))} -> 0 | P85: {=SUM(OFFSET(P17,0,-(COLUMN()-1),1,COLUMN()-规则表!$C$19))-SUM(OFFSET(P33,0,-(COLUMN()-1),1,COLUMN()))+SUM(OFFSET(P49,0,-(COLUMN()-1),1,COLUMN()-规则表!$F$19))+SUMPRODUCT((IFERROR(OFFSET(P49,0,-(规则表!$F$19-1),1,规则表!$F$18),0)<0)*IFERROR(FFSET(P49,0,-(规则表!$F$19-1),1,规则表!$F$19),0))} -> 0 | ... X85: {=SUM(OFFSET(X17,0,-(COLUMN()-1),1,COLUMN()-规则表!$C$19))-SUM(OFFSET(X33,0,-(COLUMN()-1),1,COLUMN()))+SUM(OFFSET(X49,0,-(COLUMN()-1),1,COLUMN()-规则表!$F$19))+SUMPRODUCT((IFERROR(OFFSET(X49,0,-(规则表!$F$19-1),1,规则表!$F$18),0)<0)*IFERROR(FFSET(X49,0,-(规则表!$F$19-1),1,规则表!$F$19),0))} -> 0
C86: P5 | I86: {=SUM(OFFSET(I18,0,-(COLUMN()-1),1,COLUMN()-规则表!$C$19))-SUM(OFFSET(I34,0,-(COLUMN()-1),1,COLUMN()))+SUM(OFFSET(I50,0,-(COLUMN()-1),1,COLUMN()-规则表!$F$19))+SUMPRODUCT((IFERROR(OFFSET(I50,0,-(规则表!$F$19-1),1,规则表!$F$18),0)<0)*IFERROR(FFSET(I50,0,-(规则表!$F$19-1),1,规则表!$F$19),0))} -> 0 | J86: {=SUM(OFFSET(J18,0,-(COLUMN()-1),1,COLUMN()-规则表!$C$19))-SUM(OFFSET(J34,0,-(COLUMN()-1),1,COLUMN()))+SUM(OFFSET(J50,0,-(COLUMN()-1),1,COLUMN()-规则表!$F$19))+SUMPRODUCT((IFERROR(OFFSET(J50,0,-(规则表!$F$19-1),1,规则表!$F$18),0)<0)*IFERROR(FFSET(J50,0,-(规则表!$F$19-1),1,规则表!$F$19),0))} -> 0 | K86: {=SUM(OFFSET(K18,0,-(COLUMN()-1),1,COLUMN()-规则表!$C$19))-SUM(OFFSET(K34,0,-(COLUMN()-1),1,COLUMN()))+SUM(OFFSET(K50,0,-(COLUMN()-1),1,COLUMN()-规则表!$F$19))+SUMPRODUCT((IFERROR(OFFSET(K50,0,-(规则表!$F$19-1),1,规则表!$F$18),0)<0)*IFERROR(FFSET(K50,0,-(规则表!$F$19-1),1,规则表!$F$19),0))} -> 0 | L86: {=SUM(OFFSET(L18,0,-(COLUMN()-1),1,COLUMN()-规则表!$C$19))-SUM(OFFSET(L34,0,-(COLUMN()-1),1,COLUMN()))+SUM(OFFSET(L50,0,-(COLUMN()-1),1,COLUMN()-规则表!$F$19))+SUMPRODUCT((IFERROR(OFFSET(L50,0,-(规则表!$F$19-1),1,规则表!$F$18),0)<0)*IFERROR(FFSET(L50,0,-(规则表!$F$19-1),1,规则表!$F$19),0))} -> 0 | M86: {=SUM(OFFSET(M18,0,-(COLUMN()-1),1,COLUMN()-规则表!$C$19))-SUM(OFFSET(M34,0,-(COLUMN()-1),1,COLUMN()))+SUM(OFFSET(M50,0,-(COLUMN()-1),1,COLUMN()-规则表!$F$19))+SUMPRODUCT((IFERROR(OFFSET(M50,0,-(规则表!$F$19-1),1,规则表!$F$18),0)<0)*IFERROR(FFSET(M50,0,-(规则表!$F$19-1),1,规则表!$F$19),0))} -> 0 | N86: {=SUM(OFFSET(N18,0,-(COLUMN()-1),1,COLUMN()-规则表!$C$19))-SUM(OFFSET(N34,0,-(COLUMN()-1),1,COLUMN()))+SUM(OFFSET(N50,0,-(COLUMN()-1),1,COLUMN()-规则表!$F$19))+SUMPRODUCT((IFERROR(OFFSET(N50,0,-(规则表!$F$19-1),1,规则表!$F$18),0)<0)*IFERROR(FFSET(N50,0,-(规则表!$F$19-1),1,规则表!$F$19),0))} -> 0 | O86: {=SUM(OFFSET(O18,0,-(COLUMN()-1),1,COLUMN()-规则表!$C$19))-SUM(OFFSET(O34,0,-(COLUMN()-1),1,COLUMN()))+SUM(OFFSET(O50,0,-(COLUMN()-1),1,COLUMN()-规则表!$F$19))+SUMPRODUCT((IFERROR(OFFSET(O50,0,-(规则表!$F$19-1),1,规则表!$F$18),0)<0)*IFERROR(FFSET(O50,0,-(规则表!$F$19-1),1,规则表!$F$19),0))} -> 0 | P86: {=SUM(OFFSET(P18,0,-(COLUMN()-1),1,COLUMN()-规则表!$C$19))-SUM(OFFSET(P34,0,-(COLUMN()-1),1,COLUMN()))+SUM(OFFSET(P50,0,-(COLUMN()-1),1,COLUMN()-规则表!$F$19))+SUMPRODUCT((IFERROR(OFFSET(P50,0,-(规则表!$F$19-1),1,规则表!$F$18),0)<0)*IFERROR(FFSET(P50,0,-(规则表!$F$19-1),1,规则表!$F$19),0))} -> 0 | ... X86: {=SUM(OFFSET(X18,0,-(COLUMN()-1),1,COLUMN()-规则表!$C$19))-SUM(OFFSET(X34,0,-(COLUMN()-1),1,COLUMN()))+SUM(OFFSET(X50,0,-(COLUMN()-1),1,COLUMN()-规则表!$F$19))+SUMPRODUCT((IFERROR(OFFSET(X50,0,-(规则表!$F$19-1),1,规则表!$F$18),0)<0)*IFERROR(FFSET(X50,0,-(规则表!$F$19-1),1,规则表!$F$19),0))} -> 0
I88: =COLUMN() -> 9
B89: 现存计划 | C89: 手工线 | I89: =SUM(I72:I76) -> 10 | J89: =SUM(J72:J76) -> 10 | K89: =SUM(K72:K76) -> 10 | L89: =SUM(L72:L76) -> 10 | M89: =SUM(M72:M76) -> 10 | N89: =SUM(N72:N76) -> 10 | O89: =SUM(O72:O76) -> 10 | P89: =SUM(P72:P76) -> 10 | ... X89: =SUM(X72:X76) -> 10
C90: 自动线 | I90: =SUM(I77:I81) -> 0 | J90: =SUM(J77:J81) -> 0 | K90: =SUM(K77:K81) -> 0 | L90: =SUM(L77:L81) -> 0 | M90: =SUM(M77:M81) -> 0 | N90: =SUM(N77:N81) -> 0 | O90: =SUM(O77:O81) -> 0 | P90: =SUM(P77:P81) -> 0 | ... X90: =SUM(X77:X81) -> 0
C91: 智能线 | I91: =SUM(I82:I86) -> 0 | J91: =SUM(J82:J86) -> 0 | K91: =SUM(K82:K86) -> 0 | L91: =SUM(L82:L86) -> 0 | M91: =SUM(M82:M86) -> 0 | N91: =SUM(N82:N86) -> 0 | O91: =SUM(O82:O86) -> 0 | P91: =SUM(P82:P86) -> 0 | ... X91: =SUM(X82:X86) -> 0
A94: 能产产线情况 | B94: 传统线 | C94: P1 | I94: {=SUMPRODUCT(IF(MOD((COLUMN()-规则表!$C$17-COLUMN($D4:INDEX(4:4,COLUMN()-规则表!$C$17)))/规则表!$D$17,1)=0,$D4:INDEX(4:4,COLUMN()-规则表!$C$17),0))-SUMPRODUCT(IF(MOD((COLUMN()-COLUMN($D20:INDEX(20:20,COLUMN())))/规则表!$D$17,1)=0,$D20:INDEX(20:20,COLUMN()),0))+SUMPRODUCT(($I36:INDEX(36:36,COLUMN())<0)*(MOD((COLUMN()-COLUMN($I36:INDEX(36:36,COLUMN())))/规则表!$D$17,1)=0)*($I36:INDEX(36:36,COLUMN())))+SUMPRODUCT(($I36:INDEX(36:36,COLUMN()-规则表!$F$17)>0)*(MOD((COLUMN()-规则表!$F$17-COLUMN($I36:INDEX(36:36,COLUMN()-规则表!$F$17)))/规则表!$D$17,1)=0)*($I36:INDEX(36:36,COLUMN()-规则表!$F$17)))} -> 0 | J94: {=SUMPRODUCT(IF(MOD((COLUMN()-规则表!$C$17-COLUMN($D4:INDEX(4:4,COLUMN()-规则表!$C$17)))/规则表!$D$17,1)=0,$D4:INDEX(4:4,COLUMN()-规则表!$C$17),0))-SUMPRODUCT(IF(MOD((COLUMN()-COLUMN($D20:INDEX(20:20,COLUMN())))/规则表!$D$17,1)=0,$D20:INDEX(20:20,COLUMN()),0))+SUMPRODUCT(($I36:INDEX(36:36,COLUMN())<0)*(MOD((COLUMN()-COLUMN($I36:INDEX(36:36,COLUMN())))/规则表!$D$17,1)=0)*($I36:INDEX(36:36,COLUMN())))+SUMPRODUCT(($I36:INDEX(36:36,COLUMN()-规则表!$F$17)>0)*(MOD((COLUMN()-规则表!$F$17-COLUMN($I36:INDEX(36:36,COLUMN()-规则表!$F$17)))/规则表!$D$17,1)=0)*($I36:INDEX(36:36,COLUMN()-规则表!$F$17)))} -> 0 | K94: {=SUMPRODUCT(IF(MOD((COLUMN()-规则表!$C$17-COLUMN($D4:INDEX(4:4,COLUMN()-规则表!$C$17)))/规则表!$D$17,1)=0,$D4:INDEX(4:4,COLUMN()-规则表!$C$17),0))-SUMPRODUCT(IF(MOD((COLUMN()-COLUMN($D20:INDEX(20:20,COLUMN())))/规则表!$D$17,1)=0,$D20:INDEX(20:20,COLUMN()),0))+SUMPRODUCT(($I36:INDEX(36:36,COLUMN())<0)*(MOD((COLUMN()-COLUMN($I36:INDEX(36:36,COLUMN())))/规则表!$D$17,1)=0)*($I36:INDEX(36:36,COLUMN())))+SUMPRODUCT(($I36:INDEX(36:36,COLUMN()-规则表!$F$17)>0)*(MOD((COLUMN()-规则表!$F$17-COLUMN($I36:INDEX(36:36,COLUMN()-规则表!$F$17)))/规则表!$D$17,1)=0)*($I36:INDEX(36:36,COLUMN()-规则表!$F$17)))} -> 0 | L94: {=SUMPRODUCT(IF(MOD((COLUMN()-规则表!$C$17-COLUMN($D4:INDEX(4:4,COLUMN()-规则表!$C$17)))/规则表!$D$17,1)=0,$D4:INDEX(4:4,COLUMN()-规则表!$C$17),0))-SUMPRODUCT(IF(MOD((COLUMN()-COLUMN($D20:INDEX(20:20,COLUMN())))/规则表!$D$17,1)=0,$D20:INDEX(20:20,COLUMN()),0))+SUMPRODUCT(($I36:INDEX(36:36,COLUMN())<0)*(MOD((COLUMN()-COLUMN($I36:INDEX(36:36,COLUMN())))/规则表!$D$17,1)=0)*($I36:INDEX(36:36,COLUMN())))+SUMPRODUCT(($I36:INDEX(36:36,COLUMN()-规则表!$F$17)>0)*(MOD((COLUMN()-规则表!$F$17-COLUMN($I36:INDEX(36:36,COLUMN()-规则表!$F$17)))/规则表!$D$17,1)=0)*($I36:INDEX(36:36,COLUMN()-规则表!$F$17)))} -> 0 | M94: {=SUMPRODUCT(IF(MOD((COLUMN()-规则表!$C$17-COLUMN($D4:INDEX(4:4,COLUMN()-规则表!$C$17)))/规则表!$D$17,1)=0,$D4:INDEX(4:4,COLUMN()-规则表!$C$17),0))-SUMPRODUCT(IF(MOD((COLUMN()-COLUMN($D20:INDEX(20:20,COLUMN())))/规则表!$D$17,1)=0,$D20:INDEX(20:20,COLUMN()),0))+SUMPRODUCT(($I36:INDEX(36:36,COLUMN())<0)*(MOD((COLUMN()-COLUMN($I36:INDEX(36:36,COLUMN())))/规则表!$D$17,1)=0)*($I36:INDEX(36:36,COLUMN())))+SUMPRODUCT(($I36:INDEX(36:36,COLUMN()-规则表!$F$17)>0)*(MOD((COLUMN()-规则表!$F$17-COLUMN($I36:INDEX(36:36,COLUMN()-规则表!$F$17)))/规则表!$D$17,1)=0)*($I36:INDEX(36:36,COLUMN()-规则表!$F$17)))} -> 0 | N94: {=SUMPRODUCT(IF(MOD((COLUMN()-规则表!$C$17-COLUMN($D4:INDEX(4:4,COLUMN()-规则表!$C$17)))/规则表!$D$17,1)=0,$D4:INDEX(4:4,COLUMN()-规则表!$C$17),0))-SUMPRODUCT(IF(MOD((COLUMN()-COLUMN($D20:INDEX(20:20,COLUMN())))/规则表!$D$17,1)=0,$D20:INDEX(20:20,COLUMN()),0))+SUMPRODUCT(($I36:INDEX(36:36,COLUMN())<0)*(MOD((COLUMN()-COLUMN($I36:INDEX(36:36,COLUMN())))/规则表!$D$17,1)=0)*($I36:INDEX(36:36,COLUMN())))+SUMPRODUCT(($I36:INDEX(36:36,COLUMN()-规则表!$F$17)>0)*(MOD((COLUMN()-规则表!$F$17-COLUMN($I36:INDEX(36:36,COLUMN()-规则表!$F$17)))/规则表!$D$17,1)=0)*($I36:INDEX(36:36,COLUMN()-规则表!$F$17)))} -> 0 | O94: {=SUMPRODUCT(IF(MOD((COLUMN()-规则表!$C$17-COLUMN($D4:INDEX(4:4,COLUMN()-规则表!$C$17)))/规则表!$D$17,1)=0,$D4:INDEX(4:4,COLUMN()-规则表!$C$17),0))-SUMPRODUCT(IF(MOD((COLUMN()-COLUMN($D20:INDEX(20:20,COLUMN())))/规则表!$D$17,1)=0,$D20:INDEX(20:20,COLUMN()),0))+SUMPRODUCT(($I36:INDEX(36:36,COLUMN())<0)*(MOD((COLUMN()-COLUMN($I36:INDEX(36:36,COLUMN())))/规则表!$D$17,1)=0)*($I36:INDEX(36:36,COLUMN())))+SUMPRODUCT(($I36:INDEX(36:36,COLUMN()-规则表!$F$17)>0)*(MOD((COLUMN()-规则表!$F$17-COLUMN($I36:INDEX(36:36,COLUMN()-规则表!$F$17)))/规则表!$D$17,1)=0)*($I36:INDEX(36:36,COLUMN()-规则表!$F$17)))} -> 0 | P94: {=SUMPRODUCT(IF(MOD((COLUMN()-规则表!$C$17-COLUMN($D4:INDEX(4:4,COLUMN()-规则表!$C$17)))/规则表!$D$17,1)=0,$D4:INDEX(4:4,COLUMN()-规则表!$C$17),0))-SUMPRODUCT(IF(MOD((COLUMN()-COLUMN($D20:INDEX(20:20,COLUMN())))/规则表!$D$17,1)=0,$D20:INDEX(20:20,COLUMN()),0))+SUMPRODUCT(($I36:INDEX(36:36,COLUMN())<0)*(MOD((COLUMN()-COLUMN($I36:INDEX(36:36,COLUMN())))/规则表!$D$17,1)=0)*($I36:INDEX(36:36,COLUMN())))+SUMPRODUCT(($I36:INDEX(36:36,COLUMN()-规则表!$F$17)>0)*(MOD((COLUMN()-规则表!$F$17-COLUMN($I36:INDEX(36:36,COLUMN()-规则表!$F$17)))/规则表!$D$17,1)=0)*($I36:INDEX(36:36,COLUMN()-规则表!$F$17)))} -> 0 | Q94: {=IF(Q$109,SUMPRODUCT(IF(MOD((COLUMN()-规则表!$C$17-COLUMN($D4:INDEX(4:4,COLUMN()-规则表!$C$17)))/规则表!$D$17,1)=0,$D4:INDEX(4:4,COLUMN()-规则表!$C$17),0))-SUMPRODUCT(IF(MOD((COLUMN()-COLUMN($D20:INDEX(20:20,COLUMN())))/规则表!$D$17,1)=0,$D20:INDEX(20:20,COLUMN()),0))+SUMPRODUCT(($I36:INDEX(36:36,COLUMN())<0)*(MOD((COLUMN()-COLUMN($I36:INDEX(36:36,COLUMN())))/规则表!$D$17,1)=0)*($I36:INDEX(36:36,COLUMN())))+SUMPRODUCT(($I36:INDEX(36:36,COLUMN()-规则表!$F$17)>0)*(MOD((COLUMN()-规则表!$F$17-COLUMN($I36:INDEX(36:36,COLUMN()-规则表!$F$17)))/规则表!$D$17,1)=0)*($I36:INDEX(36:36,COLUMN()-规则表!$F$17))),0)} -> 0 | R94: {=IF(R$109,SUMPRODUCT(IF(MOD((COLUMN()-规则表!$C$17-COLUMN($D4:INDEX(4:4,COLUMN()-规则表!$C$17)))/规则表!$D$17,1)=0,$D4:INDEX(4:4,COLUMN()-规则表!$C$17),0))-SUMPRODUCT(IF(MOD((COLUMN()-COLUMN($D20:INDEX(20:20,COLUMN())))/规则表!$D$17,1)=0,$D20:INDEX(20:20,COLUMN()),0))+SUMPRODUCT(($I36:INDEX(36:36,COLUMN())<0)*(MOD((COLUMN()-COLUMN($I36:INDEX(36:36,COLUMN())))/规则表!$D$17,1)=0)*($I36:INDEX(36:36,COLUMN())))+SUMPRODUCT(($I36:INDEX(36:36,COLUMN()-规则表!$F$17)>0)*(MOD((COLUMN()-规则表!$F$17-COLUMN($I36:INDEX(36:36,COLUMN()-规则表!$F$17)))/规则表!$D$17,1)=0)*($I36:INDEX(36:36,COLUMN()-规则表!$F$17))),0)} -> 0 | S94: {=IF(S$109,SUMPRODUCT(IF(MOD((COLUMN()-规则表!$C$17-COLUMN($D4:INDEX(4:4,COLUMN()-规则表!$C$17)))/规则表!$D$17,1)=0,$D4:INDEX(4:4,COLUMN()-规则表!$C$17),0))-SUMPRODUCT(IF(MOD((COLUMN()-COLUMN($D20:INDEX(20:20,COLUMN())))/规则表!$D$17,1)=0,$D20:INDEX(20:20,COLUMN()),0))+SUMPRODUCT(($I36:INDEX(36:36,COLUMN())<0)*(MOD((COLUMN()-COLUMN($I36:INDEX(36:36,COLUMN())))/规则表!$D$17,1)=0)*($I36:INDEX(36:36,COLUMN())))+SUMPRODUCT(($I36:INDEX(36:36,COLUMN()-规则表!$F$17)>0)*(MOD((COLUMN()-规则表!$F$17-COLUMN($I36:INDEX(36:36,COLUMN()-规则表!$F$17)))/规则表!$D$17,1)=0)*($I36:INDEX(36:36,COLUMN()-规则表!$F$17))),0)} -> 0 | T94: {=IF(T$109,SUMPRODUCT(IF(MOD((COLUMN()-规则表!$C$17-COLUMN($D4:INDEX(4:4,COLUMN()-规则表!$C$17)))/规则表!$D$17,1)=0,$D4:INDEX(4:4,COLUMN()-规则表!$C$17),0))-SUMPRODUCT(IF(MOD((COLUMN()-COLUMN($D20:INDEX(20:20,COLUMN())))/规则表!$D$17,1)=0,$D20:INDEX(20:20,COLUMN()),0))+SUMPRODUCT(($I36:INDEX(36:36,COLUMN())<0)*(MOD((COLUMN()-COLUMN($I36:INDEX(36:36,COLUMN())))/规则表!$D$17,1)=0)*($I36:INDEX(36:36,COLUMN())))+SUMPRODUCT(($I36:INDEX(36:36,COLUMN()-规则表!$F$17)>0)*(MOD((COLUMN()-规则表!$F$17-COLUMN($I36:INDEX(36:36,COLUMN()-规则表!$F$17)))/规则表!$D$17,1)=0)*($I36:INDEX(36:36,COLUMN()-规则表!$F$17))),0)} -> 0 | U94: {=IF(U$109,SUMPRODUCT(IF(MOD((COLUMN()-规则表!$C$17-COLUMN($D4:INDEX(4:4,COLUMN()-规则表!$C$17)))/规则表!$D$17,1)=0,$D4:INDEX(4:4,COLUMN()-规则表!$C$17),0))-SUMPRODUCT(IF(MOD((COLUMN()-COLUMN($D20:INDEX(20:20,COLUMN())))/规则表!$D$17,1)=0,$D20:INDEX(20:20,COLUMN()),0))+SUMPRODUCT(($I36:INDEX(36:36,COLUMN())<0)*(MOD((COLUMN()-COLUMN($I36:INDEX(36:36,COLUMN())))/规则表!$D$17,1)=0)*($I36:INDEX(36:36,COLUMN())))+SUMPRODUCT(($I36:INDEX(36:36,COLUMN()-规则表!$F$17)>0)*(MOD((COLUMN()-规则表!$F$17-COLUMN($I36:INDEX(36:36,COLUMN()-规则表!$F$17)))/规则表!$D$17,1)=0)*($I36:INDEX(36:36,COLUMN()-规则表!$F$17))),0)} -> 0 | V94: {=IF(V$109,SUMPRODUCT(IF(MOD((COLUMN()-规则表!$C$17-COLUMN($D4:INDEX(4:4,COLUMN()-规则表!$C$17)))/规则表!$D$17,1)=0,$D4:INDEX(4:4,COLUMN()-规则表!$C$17),0))-SUMPRODUCT(IF(MOD((COLUMN()-COLUMN($D20:INDEX(20:20,COLUMN())))/规则表!$D$17,1)=0,$D20:INDEX(20:20,COLUMN()),0))+SUMPRODUCT(($I36:INDEX(36:36,COLUMN())<0)*(MOD((COLUMN()-COLUMN($I36:INDEX(36:36,COLUMN())))/规则表!$D$17,1)=0)*($I36:INDEX(36:36,COLUMN())))+SUMPRODUCT(($I36:INDEX(36:36,COLUMN()-规则表!$F$17)>0)*(MOD((COLUMN()-规则表!$F$17-COLUMN($I36:INDEX(36:36,COLUMN()-规则表!$F$17)))/规则表!$D$17,1)=0)*($I36:INDEX(36:36,COLUMN()-规则表!$F$17))),0)} -> 0 | W94: {=IF(W$109,SUMPRODUCT(IF(MOD((COLUMN()-规则表!$C$17-COLUMN($D4:INDEX(4:4,COLUMN()-规则表!$C$17)))/规则表!$D$17,1)=0,$D4:INDEX(4:4,COLUMN()-规则表!$C$17),0))-SUMPRODUCT(IF(MOD((COLUMN()-COLUMN($D20:INDEX(20:20,COLUMN())))/规则表!$D$17,1)=0,$D20:INDEX(20:20,COLUMN()),0))+SUMPRODUCT(($I36:INDEX(36:36,COLUMN())<0)*(MOD((COLUMN()-COLUMN($I36:INDEX(36:36,COLUMN())))/规则表!$D$17,1)=0)*($I36:INDEX(36:36,COLUMN())))+SUMPRODUCT(($I36:INDEX(36:36,COLUMN()-规则表!$F$17)>0)*(MOD((COLUMN()-规则表!$F$17-COLUMN($I36:INDEX(36:36,COLUMN()-规则表!$F$17)))/规则表!$D$17,1)=0)*($I36:INDEX(36:36,COLUMN()-规则表!$F$17))),0)} -> 0 | X94: {=IF(X$109,SUMPRODUCT(IF(MOD((COLUMN()-规则表!$C$17-COLUMN($D4:INDEX(4:4,COLUMN()-规则表!$C$17)))/规则表!$D$17,1)=0,$D4:INDEX(4:4,COLUMN()-规则表!$C$17),0))-SUMPRODUCT(IF(MOD((COLUMN()-COLUMN($D20:INDEX(20:20,COLUMN())))/规则表!$D$17,1)=0,$D20:INDEX(20:20,COLUMN()),0))+SUMPRODUCT(($I36:INDEX(36:36,COLUMN())<0)*(MOD((COLUMN()-COLUMN($I36:INDEX(36:36,COLUMN())))/规则表!$D$17,1)=0)*($I36:INDEX(36:36,COLUMN())))+SUMPRODUCT(($I36:INDEX(36:36,COLUMN()-规则表!$F$17)>0)*(MOD((COLUMN()-规则表!$F$17-COLUMN($I36:INDEX(36:36,COLUMN()-规则表!$F$17)))/规则表!$D$17,1)=0)*($I36:INDEX(36:36,COLUMN()-规则表!$F$17))),0)} -> 0
C95: P2 | I95: {=SUMPRODUCT(IF(MOD((COLUMN()-规则表!$C$17-COLUMN($D5:INDEX(5:5,COLUMN()-规则表!$C$17)))/规则表!$D$17,1)=0,$D5:INDEX(5:5,COLUMN()-规则表!$C$17),0))-SUMPRODUCT(IF(MOD((COLUMN()-COLUMN($D21:INDEX(21:21,COLUMN())))/规则表!$D$17,1)=0,$D21:INDEX(21:21,COLUMN()),0))+SUMPRODUCT(($I37:INDEX(37:37,COLUMN())<0)*(MOD((COLUMN()-COLUMN($I37:INDEX(37:37,COLUMN())))/规则表!$D$17,1)=0)*($I37:INDEX(37:37,COLUMN())))+SUMPRODUCT(($I37:INDEX(37:37,COLUMN()-规则表!$F$17)>0)*(MOD((COLUMN()-规则表!$F$17-COLUMN($I37:INDEX(37:37,COLUMN()-规则表!$F$17)))/规则表!$D$17,1)=0)*($I37:INDEX(37:37,COLUMN()-规则表!$F$17)))} -> 0 | J95: {=SUMPRODUCT(IF(MOD((COLUMN()-规则表!$C$17-COLUMN($D5:INDEX(5:5,COLUMN()-规则表!$C$17)))/规则表!$D$17,1)=0,$D5:INDEX(5:5,COLUMN()-规则表!$C$17),0))-SUMPRODUCT(IF(MOD((COLUMN()-COLUMN($D21:INDEX(21:21,COLUMN())))/规则表!$D$17,1)=0,$D21:INDEX(21:21,COLUMN()),0))+SUMPRODUCT(($I37:INDEX(37:37,COLUMN())<0)*(MOD((COLUMN()-COLUMN($I37:INDEX(37:37,COLUMN())))/规则表!$D$17,1)=0)*($I37:INDEX(37:37,COLUMN())))+SUMPRODUCT(($I37:INDEX(37:37,COLUMN()-规则表!$F$17)>0)*(MOD((COLUMN()-规则表!$F$17-COLUMN($I37:INDEX(37:37,COLUMN()-规则表!$F$17)))/规则表!$D$17,1)=0)*($I37:INDEX(37:37,COLUMN()-规则表!$F$17)))} -> 0 | K95: {=SUMPRODUCT(IF(MOD((COLUMN()-规则表!$C$17-COLUMN($D5:INDEX(5:5,COLUMN()-规则表!$C$17)))/规则表!$D$17,1)=0,$D5:INDEX(5:5,COLUMN()-规则表!$C$17),0))-SUMPRODUCT(IF(MOD((COLUMN()-COLUMN($D21:INDEX(21:21,COLUMN())))/规则表!$D$17,1)=0,$D21:INDEX(21:21,COLUMN()),0))+SUMPRODUCT(($I37:INDEX(37:37,COLUMN())<0)*(MOD((COLUMN()-COLUMN($I37:INDEX(37:37,COLUMN())))/规则表!$D$17,1)=0)*($I37:INDEX(37:37,COLUMN())))+SUMPRODUCT(($I37:INDEX(37:37,COLUMN()-规则表!$F$17)>0)*(MOD((COLUMN()-规则表!$F$17-COLUMN($I37:INDEX(37:37,COLUMN()-规则表!$F$17)))/规则表!$D$17,1)=0)*($I37:INDEX(37:37,COLUMN()-规则表!$F$17)))} -> 0 | L95: {=SUMPRODUCT(IF(MOD((COLUMN()-规则表!$C$17-COLUMN($D5:INDEX(5:5,COLUMN()-规则表!$C$17)))/规则表!$D$17,1)=0,$D5:INDEX(5:5,COLUMN()-规则表!$C$17),0))-SUMPRODUCT(IF(MOD((COLUMN()-COLUMN($D21:INDEX(21:21,COLUMN())))/规则表!$D$17,1)=0,$D21:INDEX(21:21,COLUMN()),0))+SUMPRODUCT(($I37:INDEX(37:37,COLUMN())<0)*(MOD((COLUMN()-COLUMN($I37:INDEX(37:37,COLUMN())))/规则表!$D$17,1)=0)*($I37:INDEX(37:37,COLUMN())))+SUMPRODUCT(($I37:INDEX(37:37,COLUMN()-规则表!$F$17)>0)*(MOD((COLUMN()-规则表!$F$17-COLUMN($I37:INDEX(37:37,COLUMN()-规则表!$F$17)))/规则表!$D$17,1)=0)*($I37:INDEX(37:37,COLUMN()-规则表!$F$17)))} -> 0 | M95: {=SUMPRODUCT(IF(MOD((COLUMN()-规则表!$C$17-COLUMN($D5:INDEX(5:5,COLUMN()-规则表!$C$17)))/规则表!$D$17,1)=0,$D5:INDEX(5:5,COLUMN()-规则表!$C$17),0))-SUMPRODUCT(IF(MOD((COLUMN()-COLUMN($D21:INDEX(21:21,COLUMN())))/规则表!$D$17,1)=0,$D21:INDEX(21:21,COLUMN()),0))+SUMPRODUCT(($I37:INDEX(37:37,COLUMN())<0)*(MOD((COLUMN()-COLUMN($I37:INDEX(37:37,COLUMN())))/规则表!$D$17,1)=0)*($I37:INDEX(37:37,COLUMN())))+SUMPRODUCT(($I37:INDEX(37:37,COLUMN()-规则表!$F$17)>0)*(MOD((COLUMN()-规则表!$F$17-COLUMN($I37:INDEX(37:37,COLUMN()-规则表!$F$17)))/规则表!$D$17,1)=0)*($I37:INDEX(37:37,COLUMN()-规则表!$F$17)))} -> 0 | N95: {=SUMPRODUCT(IF(MOD((COLUMN()-规则表!$C$17-COLUMN($D5:INDEX(5:5,COLUMN()-规则表!$C$17)))/规则表!$D$17,1)=0,$D5:INDEX(5:5,COLUMN()-规则表!$C$17),0))-SUMPRODUCT(IF(MOD((COLUMN()-COLUMN($D21:INDEX(21:21,COLUMN())))/规则表!$D$17,1)=0,$D21:INDEX(21:21,COLUMN()),0))+SUMPRODUCT(($I37:INDEX(37:37,COLUMN())<0)*(MOD((COLUMN()-COLUMN($I37:INDEX(37:37,COLUMN())))/规则表!$D$17,1)=0)*($I37:INDEX(37:37,COLUMN())))+SUMPRODUCT(($I37:INDEX(37:37,COLUMN()-规则表!$F$17)>0)*(MOD((COLUMN()-规则表!$F$17-COLUMN($I37:INDEX(37:37,COLUMN()-规则表!$F$17)))/规则表!$D$17,1)=0)*($I37:INDEX(37:37,COLUMN()-规则表!$F$17)))} -> 0 | O95: {=SUMPRODUCT(IF(MOD((COLUMN()-规则表!$C$17-COLUMN($D5:INDEX(5:5,COLUMN()-规则表!$C$17)))/规则表!$D$17,1)=0,$D5:INDEX(5:5,COLUMN()-规则表!$C$17),0))-SUMPRODUCT(IF(MOD((COLUMN()-COLUMN($D21:INDEX(21:21,COLUMN())))/规则表!$D$17,1)=0,$D21:INDEX(21:21,COLUMN()),0))+SUMPRODUCT(($I37:INDEX(37:37,COLUMN())<0)*(MOD((COLUMN()-COLUMN($I37:INDEX(37:37,COLUMN())))/规则表!$D$17,1)=0)*($I37:INDEX(37:37,COLUMN())))+SUMPRODUCT(($I37:INDEX(37:37,COLUMN()-规则表!$F$17)>0)*(MOD((COLUMN()-规则表!$F$17-COLUMN($I37:INDEX(37:37,COLUMN()-规则表!$F$17)))/规则表!$D$17,1)=0)*($I37:INDEX(37:37,COLUMN()-规则表!$F$17)))} -> 0 | P95: {=SUMPRODUCT(IF(MOD((COLUMN()-规则表!$C$17-COLUMN($D5:INDEX(5:5,COLUMN()-规则表!$C$17)))/规则表!$D$17,1)=0,$D5:INDEX(5:5,COLUMN()-规则表!$C$17),0))-SUMPRODUCT(IF(MOD((COLUMN()-COLUMN($D21:INDEX(21:21,COLUMN())))/规则表!$D$17,1)=0,$D21:INDEX(21:21,COLUMN()),0))+SUMPRODUCT(($I37:INDEX(37:37,COLUMN())<0)*(MOD((COLUMN()-COLUMN($I37:INDEX(37:37,COLUMN())))/规则表!$D$17,1)=0)*($I37:INDEX(37:37,COLUMN())))+SUMPRODUCT(($I37:INDEX(37:37,COLUMN()-规则表!$F$17)>0)*(MOD((COLUMN()-规则表!$F$17-COLUMN($I37:INDEX(37:37,COLUMN()-规则表!$F$17)))/规则表!$D$17,1)=0)*($I37:INDEX(37:37,COLUMN()-规则表!$F$17)))} -> 0 | Q95: {=IF(Q$109,SUMPRODUCT(IF(MOD((COLUMN()-规则表!$C$17-COLUMN($D5:INDEX(5:5,COLUMN()-规则表!$C$17)))/规则表!$D$17,1)=0,$D5:INDEX(5:5,COLUMN()-规则表!$C$17),0))-SUMPRODUCT(IF(MOD((COLUMN()-COLUMN($D21:INDEX(21:21,COLUMN())))/规则表!$D$17,1)=0,$D21:INDEX(21:21,COLUMN()),0))+SUMPRODUCT(($I37:INDEX(37:37,COLUMN())<0)*(MOD((COLUMN()-COLUMN($I37:INDEX(37:37,COLUMN())))/规则表!$D$17,1)=0)*($I37:INDEX(37:37,COLUMN())))+SUMPRODUCT(($I37:INDEX(37:37,COLUMN()-规则表!$F$17)>0)*(MOD((COLUMN()-规则表!$F$17-COLUMN($I37:INDEX(37:37,COLUMN()-规则表!$F$17)))/规则表!$D$17,1)=0)*($I37:INDEX(37:37,COLUMN()-规则表!$F$17))),0)} -> 0 | R95: {=IF(R$109,SUMPRODUCT(IF(MOD((COLUMN()-规则表!$C$17-COLUMN($D5:INDEX(5:5,COLUMN()-规则表!$C$17)))/规则表!$D$17,1)=0,$D5:INDEX(5:5,COLUMN()-规则表!$C$17),0))-SUMPRODUCT(IF(MOD((COLUMN()-COLUMN($D21:INDEX(21:21,COLUMN())))/规则表!$D$17,1)=0,$D21:INDEX(21:21,COLUMN()),0))+SUMPRODUCT(($I37:INDEX(37:37,COLUMN())<0)*(MOD((COLUMN()-COLUMN($I37:INDEX(37:37,COLUMN())))/规则表!$D$17,1)=0)*($I37:INDEX(37:37,COLUMN())))+SUMPRODUCT(($I37:INDEX(37:37,COLUMN()-规则表!$F$17)>0)*(MOD((COLUMN()-规则表!$F$17-COLUMN($I37:INDEX(37:37,COLUMN()-规则表!$F$17)))/规则表!$D$17,1)=0)*($I37:INDEX(37:37,COLUMN()-规则表!$F$17))),0)} -> 0 | S95: {=IF(S$109,SUMPRODUCT(IF(MOD((COLUMN()-规则表!$C$17-COLUMN($D5:INDEX(5:5,COLUMN()-规则表!$C$17)))/规则表!$D$17,1)=0,$D5:INDEX(5:5,COLUMN()-规则表!$C$17),0))-SUMPRODUCT(IF(MOD((COLUMN()-COLUMN($D21:INDEX(21:21,COLUMN())))/规则表!$D$17,1)=0,$D21:INDEX(21:21,COLUMN()),0))+SUMPRODUCT(($I37:INDEX(37:37,COLUMN())<0)*(MOD((COLUMN()-COLUMN($I37:INDEX(37:37,COLUMN())))/规则表!$D$17,1)=0)*($I37:INDEX(37:37,COLUMN())))+SUMPRODUCT(($I37:INDEX(37:37,COLUMN()-规则表!$F$17)>0)*(MOD((COLUMN()-规则表!$F$17-COLUMN($I37:INDEX(37:37,COLUMN()-规则表!$F$17)))/规则表!$D$17,1)=0)*($I37:INDEX(37:37,COLUMN()-规则表!$F$17))),0)} -> 0 | T95: {=IF(T$109,SUMPRODUCT(IF(MOD((COLUMN()-规则表!$C$17-COLUMN($D5:INDEX(5:5,COLUMN()-规则表!$C$17)))/规则表!$D$17,1)=0,$D5:INDEX(5:5,COLUMN()-规则表!$C$17),0))-SUMPRODUCT(IF(MOD((COLUMN()-COLUMN($D21:INDEX(21:21,COLUMN())))/规则表!$D$17,1)=0,$D21:INDEX(21:21,COLUMN()),0))+SUMPRODUCT(($I37:INDEX(37:37,COLUMN())<0)*(MOD((COLUMN()-COLUMN($I37:INDEX(37:37,COLUMN())))/规则表!$D$17,1)=0)*($I37:INDEX(37:37,COLUMN())))+SUMPRODUCT(($I37:INDEX(37:37,COLUMN()-规则表!$F$17)>0)*(MOD((COLUMN()-规则表!$F$17-COLUMN($I37:INDEX(37:37,COLUMN()-规则表!$F$17)))/规则表!$D$17,1)=0)*($I37:INDEX(37:37,COLUMN()-规则表!$F$17))),0)} -> 0 | U95: {=IF(U$109,SUMPRODUCT(IF(MOD((COLUMN()-规则表!$C$17-COLUMN($D5:INDEX(5:5,COLUMN()-规则表!$C$17)))/规则表!$D$17,1)=0,$D5:INDEX(5:5,COLUMN()-规则表!$C$17),0))-SUMPRODUCT(IF(MOD((COLUMN()-COLUMN($D21:INDEX(21:21,COLUMN())))/规则表!$D$17,1)=0,$D21:INDEX(21:21,COLUMN()),0))+SUMPRODUCT(($I37:INDEX(37:37,COLUMN())<0)*(MOD((COLUMN()-COLUMN($I37:INDEX(37:37,COLUMN())))/规则表!$D$17,1)=0)*($I37:INDEX(37:37,COLUMN())))+SUMPRODUCT(($I37:INDEX(37:37,COLUMN()-规则表!$F$17)>0)*(MOD((COLUMN()-规则表!$F$17-COLUMN($I37:INDEX(37:37,COLUMN()-规则表!$F$17)))/规则表!$D$17,1)=0)*($I37:INDEX(37:37,COLUMN()-规则表!$F$17))),0)} -> 0 | V95: {=IF(V$109,SUMPRODUCT(IF(MOD((COLUMN()-规则表!$C$17-COLUMN($D5:INDEX(5:5,COLUMN()-规则表!$C$17)))/规则表!$D$17,1)=0,$D5:INDEX(5:5,COLUMN()-规则表!$C$17),0))-SUMPRODUCT(IF(MOD((COLUMN()-COLUMN($D21:INDEX(21:21,COLUMN())))/规则表!$D$17,1)=0,$D21:INDEX(21:21,COLUMN()),0))+SUMPRODUCT(($I37:INDEX(37:37,COLUMN())<0)*(MOD((COLUMN()-COLUMN($I37:INDEX(37:37,COLUMN())))/规则表!$D$17,1)=0)*($I37:INDEX(37:37,COLUMN())))+SUMPRODUCT(($I37:INDEX(37:37,COLUMN()-规则表!$F$17)>0)*(MOD((COLUMN()-规则表!$F$17-COLUMN($I37:INDEX(37:37,COLUMN()-规则表!$F$17)))/规则表!$D$17,1)=0)*($I37:INDEX(37:37,COLUMN()-规则表!$F$17))),0)} -> 0 | W95: {=IF(W$109,SUMPRODUCT(IF(MOD((COLUMN()-规则表!$C$17-COLUMN($D5:INDEX(5:5,COLUMN()-规则表!$C$17)))/规则表!$D$17,1)=0,$D5:INDEX(5:5,COLUMN()-规则表!$C$17),0))-SUMPRODUCT(IF(MOD((COLUMN()-COLUMN($D21:INDEX(21:21,COLUMN())))/规则表!$D$17,1)=0,$D21:INDEX(21:21,COLUMN()),0))+SUMPRODUCT(($I37:INDEX(37:37,COLUMN())<0)*(MOD((COLUMN()-COLUMN($I37:INDEX(37:37,COLUMN())))/规则表!$D$17,1)=0)*($I37:INDEX(37:37,COLUMN())))+SUMPRODUCT(($I37:INDEX(37:37,COLUMN()-规则表!$F$17)>0)*(MOD((COLUMN()-规则表!$F$17-COLUMN($I37:INDEX(37:37,COLUMN()-规则表!$F$17)))/规则表!$D$17,1)=0)*($I37:INDEX(37:37,COLUMN()-规则表!$F$17))),0)} -> 0 | X95: {=IF(X$109,SUMPRODUCT(IF(MOD((COLUMN()-规则表!$C$17-COLUMN($D5:INDEX(5:5,COLUMN()-规则表!$C$17)))/规则表!$D$17,1)=0,$D5:INDEX(5:5,COLUMN()-规则表!$C$17),0))-SUMPRODUCT(IF(MOD((COLUMN()-COLUMN($D21:INDEX(21:21,COLUMN())))/规则表!$D$17,1)=0,$D21:INDEX(21:21,COLUMN()),0))+SUMPRODUCT(($I37:INDEX(37:37,COLUMN())<0)*(MOD((COLUMN()-COLUMN($I37:INDEX(37:37,COLUMN())))/规则表!$D$17,1)=0)*($I37:INDEX(37:37,COLUMN())))+SUMPRODUCT(($I37:INDEX(37:37,COLUMN()-规则表!$F$17)>0)*(MOD((COLUMN()-规则表!$F$17-COLUMN($I37:INDEX(37:37,COLUMN()-规则表!$F$17)))/规则表!$D$17,1)=0)*($I37:INDEX(37:37,COLUMN()-规则表!$F$17))),0)} -> 0
C96: P3 | I96: {=SUMPRODUCT(IF(MOD((COLUMN()-规则表!$C$17-COLUMN($D6:INDEX(6:6,COLUMN()-规则表!$C$17)))/规则表!$D$17,1)=0,$D6:INDEX(6:6,COLUMN()-规则表!$C$17),0))-SUMPRODUCT(IF(MOD((COLUMN()-COLUMN($D22:INDEX(22:22,COLUMN())))/规则表!$D$17,1)=0,$D22:INDEX(22:22,COLUMN()),0))+SUMPRODUCT(($I38:INDEX(38:38,COLUMN())<0)*(MOD((COLUMN()-COLUMN($I38:INDEX(38:38,COLUMN())))/规则表!$D$17,1)=0)*($I38:INDEX(38:38,COLUMN())))+SUMPRODUCT(($I38:INDEX(38:38,COLUMN()-规则表!$F$17)>0)*(MOD((COLUMN()-规则表!$F$17-COLUMN($I38:INDEX(38:38,COLUMN()-规则表!$F$17)))/规则表!$D$17,1)=0)*($I38:INDEX(38:38,COLUMN()-规则表!$F$17)))} -> 0 | J96: {=SUMPRODUCT(IF(MOD((COLUMN()-规则表!$C$17-COLUMN($D6:INDEX(6:6,COLUMN()-规则表!$C$17)))/规则表!$D$17,1)=0,$D6:INDEX(6:6,COLUMN()-规则表!$C$17),0))-SUMPRODUCT(IF(MOD((COLUMN()-COLUMN($D22:INDEX(22:22,COLUMN())))/规则表!$D$17,1)=0,$D22:INDEX(22:22,COLUMN()),0))+SUMPRODUCT(($I38:INDEX(38:38,COLUMN())<0)*(MOD((COLUMN()-COLUMN($I38:INDEX(38:38,COLUMN())))/规则表!$D$17,1)=0)*($I38:INDEX(38:38,COLUMN())))+SUMPRODUCT(($I38:INDEX(38:38,COLUMN()-规则表!$F$17)>0)*(MOD((COLUMN()-规则表!$F$17-COLUMN($I38:INDEX(38:38,COLUMN()-规则表!$F$17)))/规则表!$D$17,1)=0)*($I38:INDEX(38:38,COLUMN()-规则表!$F$17)))} -> 0 | K96: {=SUMPRODUCT(IF(MOD((COLUMN()-规则表!$C$17-COLUMN($D6:INDEX(6:6,COLUMN()-规则表!$C$17)))/规则表!$D$17,1)=0,$D6:INDEX(6:6,COLUMN()-规则表!$C$17),0))-SUMPRODUCT(IF(MOD((COLUMN()-COLUMN($D22:INDEX(22:22,COLUMN())))/规则表!$D$17,1)=0,$D22:INDEX(22:22,COLUMN()),0))+SUMPRODUCT(($I38:INDEX(38:38,COLUMN())<0)*(MOD((COLUMN()-COLUMN($I38:INDEX(38:38,COLUMN())))/规则表!$D$17,1)=0)*($I38:INDEX(38:38,COLUMN())))+SUMPRODUCT(($I38:INDEX(38:38,COLUMN()-规则表!$F$17)>0)*(MOD((COLUMN()-规则表!$F$17-COLUMN($I38:INDEX(38:38,COLUMN()-规则表!$F$17)))/规则表!$D$17,1)=0)*($I38:INDEX(38:38,COLUMN()-规则表!$F$17)))} -> 0 | L96: {=SUMPRODUCT(IF(MOD((COLUMN()-规则表!$C$17-COLUMN($D6:INDEX(6:6,COLUMN()-规则表!$C$17)))/规则表!$D$17,1)=0,$D6:INDEX(6:6,COLUMN()-规则表!$C$17),0))-SUMPRODUCT(IF(MOD((COLUMN()-COLUMN($D22:INDEX(22:22,COLUMN())))/规则表!$D$17,1)=0,$D22:INDEX(22:22,COLUMN()),0))+SUMPRODUCT(($I38:INDEX(38:38,COLUMN())<0)*(MOD((COLUMN()-COLUMN($I38:INDEX(38:38,COLUMN())))/规则表!$D$17,1)=0)*($I38:INDEX(38:38,COLUMN())))+SUMPRODUCT(($I38:INDEX(38:38,COLUMN()-规则表!$F$17)>0)*(MOD((COLUMN()-规则表!$F$17-COLUMN($I38:INDEX(38:38,COLUMN()-规则表!$F$17)))/规则表!$D$17,1)=0)*($I38:INDEX(38:38,COLUMN()-规则表!$F$17)))} -> 0 | M96: {=SUMPRODUCT(IF(MOD((COLUMN()-规则表!$C$17-COLUMN($D6:INDEX(6:6,COLUMN()-规则表!$C$17)))/规则表!$D$17,1)=0,$D6:INDEX(6:6,COLUMN()-规则表!$C$17),0))-SUMPRODUCT(IF(MOD((COLUMN()-COLUMN($D22:INDEX(22:22,COLUMN())))/规则表!$D$17,1)=0,$D22:INDEX(22:22,COLUMN()),0))+SUMPRODUCT(($I38:INDEX(38:38,COLUMN())<0)*(MOD((COLUMN()-COLUMN($I38:INDEX(38:38,COLUMN())))/规则表!$D$17,1)=0)*($I38:INDEX(38:38,COLUMN())))+SUMPRODUCT(($I38:INDEX(38:38,COLUMN()-规则表!$F$17)>0)*(MOD((COLUMN()-规则表!$F$17-COLUMN($I38:INDEX(38:38,COLUMN()-规则表!$F$17)))/规则表!$D$17,1)=0)*($I38:INDEX(38:38,COLUMN()-规则表!$F$17)))} -> 0 | N96: {=SUMPRODUCT(IF(MOD((COLUMN()-规则表!$C$17-COLUMN($D6:INDEX(6:6,COLUMN()-规则表!$C$17)))/规则表!$D$17,1)=0,$D6:INDEX(6:6,COLUMN()-规则表!$C$17),0))-SUMPRODUCT(IF(MOD((COLUMN()-COLUMN($D22:INDEX(22:22,COLUMN())))/规则表!$D$17,1)=0,$D22:INDEX(22:22,COLUMN()),0))+SUMPRODUCT(($I38:INDEX(38:38,COLUMN())<0)*(MOD((COLUMN()-COLUMN($I38:INDEX(38:38,COLUMN())))/规则表!$D$17,1)=0)*($I38:INDEX(38:38,COLUMN())))+SUMPRODUCT(($I38:INDEX(38:38,COLUMN()-规则表!$F$17)>0)*(MOD((COLUMN()-规则表!$F$17-COLUMN($I38:INDEX(38:38,COLUMN()-规则表!$F$17)))/规则表!$D$17,1)=0)*($I38:INDEX(38:38,COLUMN()-规则表!$F$17)))} -> 0 | O96: {=SUMPRODUCT(IF(MOD((COLUMN()-规则表!$C$17-COLUMN($D6:INDEX(6:6,COLUMN()-规则表!$C$17)))/规则表!$D$17,1)=0,$D6:INDEX(6:6,COLUMN()-规则表!$C$17),0))-SUMPRODUCT(IF(MOD((COLUMN()-COLUMN($D22:INDEX(22:22,COLUMN())))/规则表!$D$17,1)=0,$D22:INDEX(22:22,COLUMN()),0))+SUMPRODUCT(($I38:INDEX(38:38,COLUMN())<0)*(MOD((COLUMN()-COLUMN($I38:INDEX(38:38,COLUMN())))/规则表!$D$17,1)=0)*($I38:INDEX(38:38,COLUMN())))+SUMPRODUCT(($I38:INDEX(38:38,COLUMN()-规则表!$F$17)>0)*(MOD((COLUMN()-规则表!$F$17-COLUMN($I38:INDEX(38:38,COLUMN()-规则表!$F$17)))/规则表!$D$17,1)=0)*($I38:INDEX(38:38,COLUMN()-规则表!$F$17)))} -> 0 | P96: {=SUMPRODUCT(IF(MOD((COLUMN()-规则表!$C$17-COLUMN($D6:INDEX(6:6,COLUMN()-规则表!$C$17)))/规则表!$D$17,1)=0,$D6:INDEX(6:6,COLUMN()-规则表!$C$17),0))-SUMPRODUCT(IF(MOD((COLUMN()-COLUMN($D22:INDEX(22:22,COLUMN())))/规则表!$D$17,1)=0,$D22:INDEX(22:22,COLUMN()),0))+SUMPRODUCT(($I38:INDEX(38:38,COLUMN())<0)*(MOD((COLUMN()-COLUMN($I38:INDEX(38:38,COLUMN())))/规则表!$D$17,1)=0)*($I38:INDEX(38:38,COLUMN())))+SUMPRODUCT(($I38:INDEX(38:38,COLUMN()-规则表!$F$17)>0)*(MOD((COLUMN()-规则表!$F$17-COLUMN($I38:INDEX(38:38,COLUMN()-规则表!$F$17)))/规则表!$D$17,1)=0)*($I38:INDEX(38:38,COLUMN()-规则表!$F$17)))} -> 0 | Q96: {=IF(Q$109,SUMPRODUCT(IF(MOD((COLUMN()-规则表!$C$17-COLUMN($D6:INDEX(6:6,COLUMN()-规则表!$C$17)))/规则表!$D$17,1)=0,$D6:INDEX(6:6,COLUMN()-规则表!$C$17),0))-SUMPRODUCT(IF(MOD((COLUMN()-COLUMN($D22:INDEX(22:22,COLUMN())))/规则表!$D$17,1)=0,$D22:INDEX(22:22,COLUMN()),0))+SUMPRODUCT(($I38:INDEX(38:38,COLUMN())<0)*(MOD((COLUMN()-COLUMN($I38:INDEX(38:38,COLUMN())))/规则表!$D$17,1)=0)*($I38:INDEX(38:38,COLUMN())))+SUMPRODUCT(($I38:INDEX(38:38,COLUMN()-规则表!$F$17)>0)*(MOD((COLUMN()-规则表!$F$17-COLUMN($I38:INDEX(38:38,COLUMN()-规则表!$F$17)))/规则表!$D$17,1)=0)*($I38:INDEX(38:38,COLUMN()-规则表!$F$17))),0)} -> 0 | R96: {=IF(R$109,SUMPRODUCT(IF(MOD((COLUMN()-规则表!$C$17-COLUMN($D6:INDEX(6:6,COLUMN()-规则表!$C$17)))/规则表!$D$17,1)=0,$D6:INDEX(6:6,COLUMN()-规则表!$C$17),0))-SUMPRODUCT(IF(MOD((COLUMN()-COLUMN($D22:INDEX(22:22,COLUMN())))/规则表!$D$17,1)=0,$D22:INDEX(22:22,COLUMN()),0))+SUMPRODUCT(($I38:INDEX(38:38,COLUMN())<0)*(MOD((COLUMN()-COLUMN($I38:INDEX(38:38,COLUMN())))/规则表!$D$17,1)=0)*($I38:INDEX(38:38,COLUMN())))+SUMPRODUCT(($I38:INDEX(38:38,COLUMN()-规则表!$F$17)>0)*(MOD((COLUMN()-规则表!$F$17-COLUMN($I38:INDEX(38:38,COLUMN()-规则表!$F$17)))/规则表!$D$17,1)=0)*($I38:INDEX(38:38,COLUMN()-规则表!$F$17))),0)} -> 0 | S96: {=IF(S$109,SUMPRODUCT(IF(MOD((COLUMN()-规则表!$C$17-COLUMN($D6:INDEX(6:6,COLUMN()-规则表!$C$17)))/规则表!$D$17,1)=0,$D6:INDEX(6:6,COLUMN()-规则表!$C$17),0))-SUMPRODUCT(IF(MOD((COLUMN()-COLUMN($D22:INDEX(22:22,COLUMN())))/规则表!$D$17,1)=0,$D22:INDEX(22:22,COLUMN()),0))+SUMPRODUCT(($I38:INDEX(38:38,COLUMN())<0)*(MOD((COLUMN()-COLUMN($I38:INDEX(38:38,COLUMN())))/规则表!$D$17,1)=0)*($I38:INDEX(38:38,COLUMN())))+SUMPRODUCT(($I38:INDEX(38:38,COLUMN()-规则表!$F$17)>0)*(MOD((COLUMN()-规则表!$F$17-COLUMN($I38:INDEX(38:38,COLUMN()-规则表!$F$17)))/规则表!$D$17,1)=0)*($I38:INDEX(38:38,COLUMN()-规则表!$F$17))),0)} -> 0 | T96: {=IF(T$109,SUMPRODUCT(IF(MOD((COLUMN()-规则表!$C$17-COLUMN($D6:INDEX(6:6,COLUMN()-规则表!$C$17)))/规则表!$D$17,1)=0,$D6:INDEX(6:6,COLUMN()-规则表!$C$17),0))-SUMPRODUCT(IF(MOD((COLUMN()-COLUMN($D22:INDEX(22:22,COLUMN())))/规则表!$D$17,1)=0,$D22:INDEX(22:22,COLUMN()),0))+SUMPRODUCT(($I38:INDEX(38:38,COLUMN())<0)*(MOD((COLUMN()-COLUMN($I38:INDEX(38:38,COLUMN())))/规则表!$D$17,1)=0)*($I38:INDEX(38:38,COLUMN())))+SUMPRODUCT(($I38:INDEX(38:38,COLUMN()-规则表!$F$17)>0)*(MOD((COLUMN()-规则表!$F$17-COLUMN($I38:INDEX(38:38,COLUMN()-规则表!$F$17)))/规则表!$D$17,1)=0)*($I38:INDEX(38:38,COLUMN()-规则表!$F$17))),0)} -> 0 | U96: {=IF(U$109,SUMPRODUCT(IF(MOD((COLUMN()-规则表!$C$17-COLUMN($D6:INDEX(6:6,COLUMN()-规则表!$C$17)))/规则表!$D$17,1)=0,$D6:INDEX(6:6,COLUMN()-规则表!$C$17),0))-SUMPRODUCT(IF(MOD((COLUMN()-COLUMN($D22:INDEX(22:22,COLUMN())))/规则表!$D$17,1)=0,$D22:INDEX(22:22,COLUMN()),0))+SUMPRODUCT(($I38:INDEX(38:38,COLUMN())<0)*(MOD((COLUMN()-COLUMN($I38:INDEX(38:38,COLUMN())))/规则表!$D$17,1)=0)*($I38:INDEX(38:38,COLUMN())))+SUMPRODUCT(($I38:INDEX(38:38,COLUMN()-规则表!$F$17)>0)*(MOD((COLUMN()-规则表!$F$17-COLUMN($I38:INDEX(38:38,COLUMN()-规则表!$F$17)))/规则表!$D$17,1)=0)*($I38:INDEX(38:38,COLUMN()-规则表!$F$17))),0)} -> 0 | V96: {=IF(V$109,SUMPRODUCT(IF(MOD((COLUMN()-规则表!$C$17-COLUMN($D6:INDEX(6:6,COLUMN()-规则表!$C$17)))/规则表!$D$17,1)=0,$D6:INDEX(6:6,COLUMN()-规则表!$C$17),0))-SUMPRODUCT(IF(MOD((COLUMN()-COLUMN($D22:INDEX(22:22,COLUMN())))/规则表!$D$17,1)=0,$D22:INDEX(22:22,COLUMN()),0))+SUMPRODUCT(($I38:INDEX(38:38,COLUMN())<0)*(MOD((COLUMN()-COLUMN($I38:INDEX(38:38,COLUMN())))/规则表!$D$17,1)=0)*($I38:INDEX(38:38,COLUMN())))+SUMPRODUCT(($I38:INDEX(38:38,COLUMN()-规则表!$F$17)>0)*(MOD((COLUMN()-规则表!$F$17-COLUMN($I38:INDEX(38:38,COLUMN()-规则表!$F$17)))/规则表!$D$17,1)=0)*($I38:INDEX(38:38,COLUMN()-规则表!$F$17))),0)} -> 0 | W96: {=IF(W$109,SUMPRODUCT(IF(MOD((COLUMN()-规则表!$C$17-COLUMN($D6:INDEX(6:6,COLUMN()-规则表!$C$17)))/规则表!$D$17,1)=0,$D6:INDEX(6:6,COLUMN()-规则表!$C$17),0))-SUMPRODUCT(IF(MOD((COLUMN()-COLUMN($D22:INDEX(22:22,COLUMN())))/规则表!$D$17,1)=0,$D22:INDEX(22:22,COLUMN()),0))+SUMPRODUCT(($I38:INDEX(38:38,COLUMN())<0)*(MOD((COLUMN()-COLUMN($I38:INDEX(38:38,COLUMN())))/规则表!$D$17,1)=0)*($I38:INDEX(38:38,COLUMN())))+SUMPRODUCT(($I38:INDEX(38:38,COLUMN()-规则表!$F$17)>0)*(MOD((COLUMN()-规则表!$F$17-COLUMN($I38:INDEX(38:38,COLUMN()-规则表!$F$17)))/规则表!$D$17,1)=0)*($I38:INDEX(38:38,COLUMN()-规则表!$F$17))),0)} -> 0 | X96: {=IF(X$109,SUMPRODUCT(IF(MOD((COLUMN()-规则表!$C$17-COLUMN($D6:INDEX(6:6,COLUMN()-规则表!$C$17)))/规则表!$D$17,1)=0,$D6:INDEX(6:6,COLUMN()-规则表!$C$17),0))-SUMPRODUCT(IF(MOD((COLUMN()-COLUMN($D22:INDEX(22:22,COLUMN())))/规则表!$D$17,1)=0,$D22:INDEX(22:22,COLUMN()),0))+SUMPRODUCT(($I38:INDEX(38:38,COLUMN())<0)*(MOD((COLUMN()-COLUMN($I38:INDEX(38:38,COLUMN())))/规则表!$D$17,1)=0)*($I38:INDEX(38:38,COLUMN())))+SUMPRODUCT(($I38:INDEX(38:38,COLUMN()-规则表!$F$17)>0)*(MOD((COLUMN()-规则表!$F$17-COLUMN($I38:INDEX(38:38,COLUMN()-规则表!$F$17)))/规则表!$D$17,1)=0)*($I38:INDEX(38:38,COLUMN()-规则表!$F$17))),0)} -> 0
C97: P4 | I97: {=SUMPRODUCT(IF(MOD((COLUMN()-规则表!$C$17-COLUMN($D7:INDEX(7:7,COLUMN()-规则表!$C$17)))/规则表!$D$17,1)=0,$D7:INDEX(7:7,COLUMN()-规则表!$C$17),0))-SUMPRODUCT(IF(MOD((COLUMN()-COLUMN($D23:INDEX(23:23,COLUMN())))/规则表!$D$17,1)=0,$D23:INDEX(23:23,COLUMN()),0))+SUMPRODUCT(($I39:INDEX(39:39,COLUMN())<0)*(MOD((COLUMN()-COLUMN($I39:INDEX(39:39,COLUMN())))/规则表!$D$17,1)=0)*($I39:INDEX(39:39,COLUMN())))+SUMPRODUCT(($I39:INDEX(39:39,COLUMN()-规则表!$F$17)>0)*(MOD((COLUMN()-规则表!$F$17-COLUMN($I39:INDEX(39:39,COLUMN()-规则表!$F$17)))/规则表!$D$17,1)=0)*($I39:INDEX(39:39,COLUMN()-规则表!$F$17)))} -> 10 | J97: {=SUMPRODUCT(IF(MOD((COLUMN()-规则表!$C$17-COLUMN($D7:INDEX(7:7,COLUMN()-规则表!$C$17)))/规则表!$D$17,1)=0,$D7:INDEX(7:7,COLUMN()-规则表!$C$17),0))-SUMPRODUCT(IF(MOD((COLUMN()-COLUMN($D23:INDEX(23:23,COLUMN())))/规则表!$D$17,1)=0,$D23:INDEX(23:23,COLUMN()),0))+SUMPRODUCT(($I39:INDEX(39:39,COLUMN())<0)*(MOD((COLUMN()-COLUMN($I39:INDEX(39:39,COLUMN())))/规则表!$D$17,1)=0)*($I39:INDEX(39:39,COLUMN())))+SUMPRODUCT(($I39:INDEX(39:39,COLUMN()-规则表!$F$17)>0)*(MOD((COLUMN()-规则表!$F$17-COLUMN($I39:INDEX(39:39,COLUMN()-规则表!$F$17)))/规则表!$D$17,1)=0)*($I39:INDEX(39:39,COLUMN()-规则表!$F$17)))} -> 0 | K97: {=SUMPRODUCT(IF(MOD((COLUMN()-规则表!$C$17-COLUMN($D7:INDEX(7:7,COLUMN()-规则表!$C$17)))/规则表!$D$17,1)=0,$D7:INDEX(7:7,COLUMN()-规则表!$C$17),0))-SUMPRODUCT(IF(MOD((COLUMN()-COLUMN($D23:INDEX(23:23,COLUMN())))/规则表!$D$17,1)=0,$D23:INDEX(23:23,COLUMN()),0))+SUMPRODUCT(($I39:INDEX(39:39,COLUMN())<0)*(MOD((COLUMN()-COLUMN($I39:INDEX(39:39,COLUMN())))/规则表!$D$17,1)=0)*($I39:INDEX(39:39,COLUMN())))+SUMPRODUCT(($I39:INDEX(39:39,COLUMN()-规则表!$F$17)>0)*(MOD((COLUMN()-规则表!$F$17-COLUMN($I39:INDEX(39:39,COLUMN()-规则表!$F$17)))/规则表!$D$17,1)=0)*($I39:INDEX(39:39,COLUMN()-规则表!$F$17)))} -> 10 | L97: {=SUMPRODUCT(IF(MOD((COLUMN()-规则表!$C$17-COLUMN($D7:INDEX(7:7,COLUMN()-规则表!$C$17)))/规则表!$D$17,1)=0,$D7:INDEX(7:7,COLUMN()-规则表!$C$17),0))-SUMPRODUCT(IF(MOD((COLUMN()-COLUMN($D23:INDEX(23:23,COLUMN())))/规则表!$D$17,1)=0,$D23:INDEX(23:23,COLUMN()),0))+SUMPRODUCT(($I39:INDEX(39:39,COLUMN())<0)*(MOD((COLUMN()-COLUMN($I39:INDEX(39:39,COLUMN())))/规则表!$D$17,1)=0)*($I39:INDEX(39:39,COLUMN())))+SUMPRODUCT(($I39:INDEX(39:39,COLUMN()-规则表!$F$17)>0)*(MOD((COLUMN()-规则表!$F$17-COLUMN($I39:INDEX(39:39,COLUMN()-规则表!$F$17)))/规则表!$D$17,1)=0)*($I39:INDEX(39:39,COLUMN()-规则表!$F$17)))} -> 0 | M97: {=SUMPRODUCT(IF(MOD((COLUMN()-规则表!$C$17-COLUMN($D7:INDEX(7:7,COLUMN()-规则表!$C$17)))/规则表!$D$17,1)=0,$D7:INDEX(7:7,COLUMN()-规则表!$C$17),0))-SUMPRODUCT(IF(MOD((COLUMN()-COLUMN($D23:INDEX(23:23,COLUMN())))/规则表!$D$17,1)=0,$D23:INDEX(23:23,COLUMN()),0))+SUMPRODUCT(($I39:INDEX(39:39,COLUMN())<0)*(MOD((COLUMN()-COLUMN($I39:INDEX(39:39,COLUMN())))/规则表!$D$17,1)=0)*($I39:INDEX(39:39,COLUMN())))+SUMPRODUCT(($I39:INDEX(39:39,COLUMN()-规则表!$F$17)>0)*(MOD((COLUMN()-规则表!$F$17-COLUMN($I39:INDEX(39:39,COLUMN()-规则表!$F$17)))/规则表!$D$17,1)=0)*($I39:INDEX(39:39,COLUMN()-规则表!$F$17)))} -> 10 | N97: {=SUMPRODUCT(IF(MOD((COLUMN()-规则表!$C$17-COLUMN($D7:INDEX(7:7,COLUMN()-规则表!$C$17)))/规则表!$D$17,1)=0,$D7:INDEX(7:7,COLUMN()-规则表!$C$17),0))-SUMPRODUCT(IF(MOD((COLUMN()-COLUMN($D23:INDEX(23:23,COLUMN())))/规则表!$D$17,1)=0,$D23:INDEX(23:23,COLUMN()),0))+SUMPRODUCT(($I39:INDEX(39:39,COLUMN())<0)*(MOD((COLUMN()-COLUMN($I39:INDEX(39:39,COLUMN())))/规则表!$D$17,1)=0)*($I39:INDEX(39:39,COLUMN())))+SUMPRODUCT(($I39:INDEX(39:39,COLUMN()-规则表!$F$17)>0)*(MOD((COLUMN()-规则表!$F$17-COLUMN($I39:INDEX(39:39,COLUMN()-规则表!$F$17)))/规则表!$D$17,1)=0)*($I39:INDEX(39:39,COLUMN()-规则表!$F$17)))} -> 0 | O97: {=SUMPRODUCT(IF(MOD((COLUMN()-规则表!$C$17-COLUMN($D7:INDEX(7:7,COLUMN()-规则表!$C$17)))/规则表!$D$17,1)=0,$D7:INDEX(7:7,COLUMN()-规则表!$C$17),0))-SUMPRODUCT(IF(MOD((COLUMN()-COLUMN($D23:INDEX(23:23,COLUMN())))/规则表!$D$17,1)=0,$D23:INDEX(23:23,COLUMN()),0))+SUMPRODUCT(($I39:INDEX(39:39,COLUMN())<0)*(MOD((COLUMN()-COLUMN($I39:INDEX(39:39,COLUMN())))/规则表!$D$17,1)=0)*($I39:INDEX(39:39,COLUMN())))+SUMPRODUCT(($I39:INDEX(39:39,COLUMN()-规则表!$F$17)>0)*(MOD((COLUMN()-规则表!$F$17-COLUMN($I39:INDEX(39:39,COLUMN()-规则表!$F$17)))/规则表!$D$17,1)=0)*($I39:INDEX(39:39,COLUMN()-规则表!$F$17)))} -> 10 | P97: {=SUMPRODUCT(IF(MOD((COLUMN()-规则表!$C$17-COLUMN($D7:INDEX(7:7,COLUMN()-规则表!$C$17)))/规则表!$D$17,1)=0,$D7:INDEX(7:7,COLUMN()-规则表!$C$17),0))-SUMPRODUCT(IF(MOD((COLUMN()-COLUMN($D23:INDEX(23:23,COLUMN())))/规则表!$D$17,1)=0,$D23:INDEX(23:23,COLUMN()),0))+SUMPRODUCT(($I39:INDEX(39:39,COLUMN())<0)*(MOD((COLUMN()-COLUMN($I39:INDEX(39:39,COLUMN())))/规则表!$D$17,1)=0)*($I39:INDEX(39:39,COLUMN())))+SUMPRODUCT(($I39:INDEX(39:39,COLUMN()-规则表!$F$17)>0)*(MOD((COLUMN()-规则表!$F$17-COLUMN($I39:INDEX(39:39,COLUMN()-规则表!$F$17)))/规则表!$D$17,1)=0)*($I39:INDEX(39:39,COLUMN()-规则表!$F$17)))} -> 0 | Q97: {=IF(Q$109,SUMPRODUCT(IF(MOD((COLUMN()-规则表!$C$17-COLUMN($D7:INDEX(7:7,COLUMN()-规则表!$C$17)))/规则表!$D$17,1)=0,$D7:INDEX(7:7,COLUMN()-规则表!$C$17),0))-SUMPRODUCT(IF(MOD((COLUMN()-COLUMN($D23:INDEX(23:23,COLUMN())))/规则表!$D$17,1)=0,$D23:INDEX(23:23,COLUMN()),0))+SUMPRODUCT(($I39:INDEX(39:39,COLUMN())<0)*(MOD((COLUMN()-COLUMN($I39:INDEX(39:39,COLUMN())))/规则表!$D$17,1)=0)*($I39:INDEX(39:39,COLUMN())))+SUMPRODUCT(($I39:INDEX(39:39,COLUMN()-规则表!$F$17)>0)*(MOD((COLUMN()-规则表!$F$17-COLUMN($I39:INDEX(39:39,COLUMN()-规则表!$F$17)))/规则表!$D$17,1)=0)*($I39:INDEX(39:39,COLUMN()-规则表!$F$17))),0)} -> 0 | R97: {=IF(R$109,SUMPRODUCT(IF(MOD((COLUMN()-规则表!$C$17-COLUMN($D7:INDEX(7:7,COLUMN()-规则表!$C$17)))/规则表!$D$17,1)=0,$D7:INDEX(7:7,COLUMN()-规则表!$C$17),0))-SUMPRODUCT(IF(MOD((COLUMN()-COLUMN($D23:INDEX(23:23,COLUMN())))/规则表!$D$17,1)=0,$D23:INDEX(23:23,COLUMN()),0))+SUMPRODUCT(($I39:INDEX(39:39,COLUMN())<0)*(MOD((COLUMN()-COLUMN($I39:INDEX(39:39,COLUMN())))/规则表!$D$17,1)=0)*($I39:INDEX(39:39,COLUMN())))+SUMPRODUCT(($I39:INDEX(39:39,COLUMN()-规则表!$F$17)>0)*(MOD((COLUMN()-规则表!$F$17-COLUMN($I39:INDEX(39:39,COLUMN()-规则表!$F$17)))/规则表!$D$17,1)=0)*($I39:INDEX(39:39,COLUMN()-规则表!$F$17))),0)} -> 0 | S97: {=IF(S$109,SUMPRODUCT(IF(MOD((COLUMN()-规则表!$C$17-COLUMN($D7:INDEX(7:7,COLUMN()-规则表!$C$17)))/规则表!$D$17,1)=0,$D7:INDEX(7:7,COLUMN()-规则表!$C$17),0))-SUMPRODUCT(IF(MOD((COLUMN()-COLUMN($D23:INDEX(23:23,COLUMN())))/规则表!$D$17,1)=0,$D23:INDEX(23:23,COLUMN()),0))+SUMPRODUCT(($I39:INDEX(39:39,COLUMN())<0)*(MOD((COLUMN()-COLUMN($I39:INDEX(39:39,COLUMN())))/规则表!$D$17,1)=0)*($I39:INDEX(39:39,COLUMN())))+SUMPRODUCT(($I39:INDEX(39:39,COLUMN()-规则表!$F$17)>0)*(MOD((COLUMN()-规则表!$F$17-COLUMN($I39:INDEX(39:39,COLUMN()-规则表!$F$17)))/规则表!$D$17,1)=0)*($I39:INDEX(39:39,COLUMN()-规则表!$F$17))),0)} -> 0 | T97: {=IF(T$109,SUMPRODUCT(IF(MOD((COLUMN()-规则表!$C$17-COLUMN($D7:INDEX(7:7,COLUMN()-规则表!$C$17)))/规则表!$D$17,1)=0,$D7:INDEX(7:7,COLUMN()-规则表!$C$17),0))-SUMPRODUCT(IF(MOD((COLUMN()-COLUMN($D23:INDEX(23:23,COLUMN())))/规则表!$D$17,1)=0,$D23:INDEX(23:23,COLUMN()),0))+SUMPRODUCT(($I39:INDEX(39:39,COLUMN())<0)*(MOD((COLUMN()-COLUMN($I39:INDEX(39:39,COLUMN())))/规则表!$D$17,1)=0)*($I39:INDEX(39:39,COLUMN())))+SUMPRODUCT(($I39:INDEX(39:39,COLUMN()-规则表!$F$17)>0)*(MOD((COLUMN()-规则表!$F$17-COLUMN($I39:INDEX(39:39,COLUMN()-规则表!$F$17)))/规则表!$D$17,1)=0)*($I39:INDEX(39:39,COLUMN()-规则表!$F$17))),0)} -> 0 | U97: {=IF(U$109,SUMPRODUCT(IF(MOD((COLUMN()-规则表!$C$17-COLUMN($D7:INDEX(7:7,COLUMN()-规则表!$C$17)))/规则表!$D$17,1)=0,$D7:INDEX(7:7,COLUMN()-规则表!$C$17),0))-SUMPRODUCT(IF(MOD((COLUMN()-COLUMN($D23:INDEX(23:23,COLUMN())))/规则表!$D$17,1)=0,$D23:INDEX(23:23,COLUMN()),0))+SUMPRODUCT(($I39:INDEX(39:39,COLUMN())<0)*(MOD((COLUMN()-COLUMN($I39:INDEX(39:39,COLUMN())))/规则表!$D$17,1)=0)*($I39:INDEX(39:39,COLUMN())))+SUMPRODUCT(($I39:INDEX(39:39,COLUMN()-规则表!$F$17)>0)*(MOD((COLUMN()-规则表!$F$17-COLUMN($I39:INDEX(39:39,COLUMN()-规则表!$F$17)))/规则表!$D$17,1)=0)*($I39:INDEX(39:39,COLUMN()-规则表!$F$17))),0)} -> 0 | V97: {=IF(V$109,SUMPRODUCT(IF(MOD((COLUMN()-规则表!$C$17-COLUMN($D7:INDEX(7:7,COLUMN()-规则表!$C$17)))/规则表!$D$17,1)=0,$D7:INDEX(7:7,COLUMN()-规则表!$C$17),0))-SUMPRODUCT(IF(MOD((COLUMN()-COLUMN($D23:INDEX(23:23,COLUMN())))/规则表!$D$17,1)=0,$D23:INDEX(23:23,COLUMN()),0))+SUMPRODUCT(($I39:INDEX(39:39,COLUMN())<0)*(MOD((COLUMN()-COLUMN($I39:INDEX(39:39,COLUMN())))/规则表!$D$17,1)=0)*($I39:INDEX(39:39,COLUMN())))+SUMPRODUCT(($I39:INDEX(39:39,COLUMN()-规则表!$F$17)>0)*(MOD((COLUMN()-规则表!$F$17-COLUMN($I39:INDEX(39:39,COLUMN()-规则表!$F$17)))/规则表!$D$17,1)=0)*($I39:INDEX(39:39,COLUMN()-规则表!$F$17))),0)} -> 0 | W97: {=IF(W$109,SUMPRODUCT(IF(MOD((COLUMN()-规则表!$C$17-COLUMN($D7:INDEX(7:7,COLUMN()-规则表!$C$17)))/规则表!$D$17,1)=0,$D7:INDEX(7:7,COLUMN()-规则表!$C$17),0))-SUMPRODUCT(IF(MOD((COLUMN()-COLUMN($D23:INDEX(23:23,COLUMN())))/规则表!$D$17,1)=0,$D23:INDEX(23:23,COLUMN()),0))+SUMPRODUCT(($I39:INDEX(39:39,COLUMN())<0)*(MOD((COLUMN()-COLUMN($I39:INDEX(39:39,COLUMN())))/规则表!$D$17,1)=0)*($I39:INDEX(39:39,COLUMN())))+SUMPRODUCT(($I39:INDEX(39:39,COLUMN()-规则表!$F$17)>0)*(MOD((COLUMN()-规则表!$F$17-COLUMN($I39:INDEX(39:39,COLUMN()-规则表!$F$17)))/规则表!$D$17,1)=0)*($I39:INDEX(39:39,COLUMN()-规则表!$F$17))),0)} -> 0 | X97: {=IF(X$109,SUMPRODUCT(IF(MOD((COLUMN()-规则表!$C$17-COLUMN($D7:INDEX(7:7,COLUMN()-规则表!$C$17)))/规则表!$D$17,1)=0,$D7:INDEX(7:7,COLUMN()-规则表!$C$17),0))-SUMPRODUCT(IF(MOD((COLUMN()-COLUMN($D23:INDEX(23:23,COLUMN())))/规则表!$D$17,1)=0,$D23:INDEX(23:23,COLUMN()),0))+SUMPRODUCT(($I39:INDEX(39:39,COLUMN())<0)*(MOD((COLUMN()-COLUMN($I39:INDEX(39:39,COLUMN())))/规则表!$D$17,1)=0)*($I39:INDEX(39:39,COLUMN())))+SUMPRODUCT(($I39:INDEX(39:39,COLUMN()-规则表!$F$17)>0)*(MOD((COLUMN()-规则表!$F$17-COLUMN($I39:INDEX(39:39,COLUMN()-规则表!$F$17)))/规则表!$D$17,1)=0)*($I39:INDEX(39:39,COLUMN()-规则表!$F$17))),0)} -> 0
C98: P5 | I98: {=SUMPRODUCT(IF(MOD((COLUMN()-规则表!$C$17-COLUMN($D8:INDEX(8:8,COLUMN()-规则表!$C$17)))/规则表!$D$17,1)=0,$D8:INDEX(8:8,COLUMN()-规则表!$C$17),0))-SUMPRODUCT(IF(MOD((COLUMN()-COLUMN($D24:INDEX(24:24,COLUMN())))/规则表!$D$17,1)=0,$D24:INDEX(24:24,COLUMN()),0))+SUMPRODUCT(($I40:INDEX(40:40,COLUMN())<0)*(MOD((COLUMN()-COLUMN($I40:INDEX(40:40,COLUMN())))/规则表!$D$17,1)=0)*($I40:INDEX(40:40,COLUMN())))+SUMPRODUCT(($I40:INDEX(40:40,COLUMN()-规则表!$F$17)>0)*(MOD((COLUMN()-规则表!$F$17-COLUMN($I40:INDEX(40:40,COLUMN()-规则表!$F$17)))/规则表!$D$17,1)=0)*($I40:INDEX(40:40,COLUMN()-规则表!$F$17)))} -> 0 | J98: {=SUMPRODUCT(IF(MOD((COLUMN()-规则表!$C$17-COLUMN($D8:INDEX(8:8,COLUMN()-规则表!$C$17)))/规则表!$D$17,1)=0,$D8:INDEX(8:8,COLUMN()-规则表!$C$17),0))-SUMPRODUCT(IF(MOD((COLUMN()-COLUMN($D24:INDEX(24:24,COLUMN())))/规则表!$D$17,1)=0,$D24:INDEX(24:24,COLUMN()),0))+SUMPRODUCT(($I40:INDEX(40:40,COLUMN())<0)*(MOD((COLUMN()-COLUMN($I40:INDEX(40:40,COLUMN())))/规则表!$D$17,1)=0)*($I40:INDEX(40:40,COLUMN())))+SUMPRODUCT(($I40:INDEX(40:40,COLUMN()-规则表!$F$17)>0)*(MOD((COLUMN()-规则表!$F$17-COLUMN($I40:INDEX(40:40,COLUMN()-规则表!$F$17)))/规则表!$D$17,1)=0)*($I40:INDEX(40:40,COLUMN()-规则表!$F$17)))} -> 0 | K98: {=SUMPRODUCT(IF(MOD((COLUMN()-规则表!$C$17-COLUMN($D8:INDEX(8:8,COLUMN()-规则表!$C$17)))/规则表!$D$17,1)=0,$D8:INDEX(8:8,COLUMN()-规则表!$C$17),0))-SUMPRODUCT(IF(MOD((COLUMN()-COLUMN($D24:INDEX(24:24,COLUMN())))/规则表!$D$17,1)=0,$D24:INDEX(24:24,COLUMN()),0))+SUMPRODUCT(($I40:INDEX(40:40,COLUMN())<0)*(MOD((COLUMN()-COLUMN($I40:INDEX(40:40,COLUMN())))/规则表!$D$17,1)=0)*($I40:INDEX(40:40,COLUMN())))+SUMPRODUCT(($I40:INDEX(40:40,COLUMN()-规则表!$F$17)>0)*(MOD((COLUMN()-规则表!$F$17-COLUMN($I40:INDEX(40:40,COLUMN()-规则表!$F$17)))/规则表!$D$17,1)=0)*($I40:INDEX(40:40,COLUMN()-规则表!$F$17)))} -> 0 | L98: {=SUMPRODUCT(IF(MOD((COLUMN()-规则表!$C$17-COLUMN($D8:INDEX(8:8,COLUMN()-规则表!$C$17)))/规则表!$D$17,1)=0,$D8:INDEX(8:8,COLUMN()-规则表!$C$17),0))-SUMPRODUCT(IF(MOD((COLUMN()-COLUMN($D24:INDEX(24:24,COLUMN())))/规则表!$D$17,1)=0,$D24:INDEX(24:24,COLUMN()),0))+SUMPRODUCT(($I40:INDEX(40:40,COLUMN())<0)*(MOD((COLUMN()-COLUMN($I40:INDEX(40:40,COLUMN())))/规则表!$D$17,1)=0)*($I40:INDEX(40:40,COLUMN())))+SUMPRODUCT(($I40:INDEX(40:40,COLUMN()-规则表!$F$17)>0)*(MOD((COLUMN()-规则表!$F$17-COLUMN($I40:INDEX(40:40,COLUMN()-规则表!$F$17)))/规则表!$D$17,1)=0)*($I40:INDEX(40:40,COLUMN()-规则表!$F$17)))} -> 0 | M98: {=SUMPRODUCT(IF(MOD((COLUMN()-规则表!$C$17-COLUMN($D8:INDEX(8:8,COLUMN()-规则表!$C$17)))/规则表!$D$17,1)=0,$D8:INDEX(8:8,COLUMN()-规则表!$C$17),0))-SUMPRODUCT(IF(MOD((COLUMN()-COLUMN($D24:INDEX(24:24,COLUMN())))/规则表!$D$17,1)=0,$D24:INDEX(24:24,COLUMN()),0))+SUMPRODUCT(($I40:INDEX(40:40,COLUMN())<0)*(MOD((COLUMN()-COLUMN($I40:INDEX(40:40,COLUMN())))/规则表!$D$17,1)=0)*($I40:INDEX(40:40,COLUMN())))+SUMPRODUCT(($I40:INDEX(40:40,COLUMN()-规则表!$F$17)>0)*(MOD((COLUMN()-规则表!$F$17-COLUMN($I40:INDEX(40:40,COLUMN()-规则表!$F$17)))/规则表!$D$17,1)=0)*($I40:INDEX(40:40,COLUMN()-规则表!$F$17)))} -> 0 | N98: {=SUMPRODUCT(IF(MOD((COLUMN()-规则表!$C$17-COLUMN($D8:INDEX(8:8,COLUMN()-规则表!$C$17)))/规则表!$D$17,1)=0,$D8:INDEX(8:8,COLUMN()-规则表!$C$17),0))-SUMPRODUCT(IF(MOD((COLUMN()-COLUMN($D24:INDEX(24:24,COLUMN())))/规则表!$D$17,1)=0,$D24:INDEX(24:24,COLUMN()),0))+SUMPRODUCT(($I40:INDEX(40:40,COLUMN())<0)*(MOD((COLUMN()-COLUMN($I40:INDEX(40:40,COLUMN())))/规则表!$D$17,1)=0)*($I40:INDEX(40:40,COLUMN())))+SUMPRODUCT(($I40:INDEX(40:40,COLUMN()-规则表!$F$17)>0)*(MOD((COLUMN()-规则表!$F$17-COLUMN($I40:INDEX(40:40,COLUMN()-规则表!$F$17)))/规则表!$D$17,1)=0)*($I40:INDEX(40:40,COLUMN()-规则表!$F$17)))} -> 0 | O98: {=SUMPRODUCT(IF(MOD((COLUMN()-规则表!$C$17-COLUMN($D8:INDEX(8:8,COLUMN()-规则表!$C$17)))/规则表!$D$17,1)=0,$D8:INDEX(8:8,COLUMN()-规则表!$C$17),0))-SUMPRODUCT(IF(MOD((COLUMN()-COLUMN($D24:INDEX(24:24,COLUMN())))/规则表!$D$17,1)=0,$D24:INDEX(24:24,COLUMN()),0))+SUMPRODUCT(($I40:INDEX(40:40,COLUMN())<0)*(MOD((COLUMN()-COLUMN($I40:INDEX(40:40,COLUMN())))/规则表!$D$17,1)=0)*($I40:INDEX(40:40,COLUMN())))+SUMPRODUCT(($I40:INDEX(40:40,COLUMN()-规则表!$F$17)>0)*(MOD((COLUMN()-规则表!$F$17-COLUMN($I40:INDEX(40:40,COLUMN()-规则表!$F$17)))/规则表!$D$17,1)=0)*($I40:INDEX(40:40,COLUMN()-规则表!$F$17)))} -> 0 | P98: {=SUMPRODUCT(IF(MOD((COLUMN()-规则表!$C$17-COLUMN($D8:INDEX(8:8,COLUMN()-规则表!$C$17)))/规则表!$D$17,1)=0,$D8:INDEX(8:8,COLUMN()-规则表!$C$17),0))-SUMPRODUCT(IF(MOD((COLUMN()-COLUMN($D24:INDEX(24:24,COLUMN())))/规则表!$D$17,1)=0,$D24:INDEX(24:24,COLUMN()),0))+SUMPRODUCT(($I40:INDEX(40:40,COLUMN())<0)*(MOD((COLUMN()-COLUMN($I40:INDEX(40:40,COLUMN())))/规则表!$D$17,1)=0)*($I40:INDEX(40:40,COLUMN())))+SUMPRODUCT(($I40:INDEX(40:40,COLUMN()-规则表!$F$17)>0)*(MOD((COLUMN()-规则表!$F$17-COLUMN($I40:INDEX(40:40,COLUMN()-规则表!$F$17)))/规则表!$D$17,1)=0)*($I40:INDEX(40:40,COLUMN()-规则表!$F$17)))} -> 0 | Q98: {=IF(Q$109,SUMPRODUCT(IF(MOD((COLUMN()-规则表!$C$17-COLUMN($D8:INDEX(8:8,COLUMN()-规则表!$C$17)))/规则表!$D$17,1)=0,$D8:INDEX(8:8,COLUMN()-规则表!$C$17),0))-SUMPRODUCT(IF(MOD((COLUMN()-COLUMN($D24:INDEX(24:24,COLUMN())))/规则表!$D$17,1)=0,$D24:INDEX(24:24,COLUMN()),0))+SUMPRODUCT(($I40:INDEX(40:40,COLUMN())<0)*(MOD((COLUMN()-COLUMN($I40:INDEX(40:40,COLUMN())))/规则表!$D$17,1)=0)*($I40:INDEX(40:40,COLUMN())))+SUMPRODUCT(($I40:INDEX(40:40,COLUMN()-规则表!$F$17)>0)*(MOD((COLUMN()-规则表!$F$17-COLUMN($I40:INDEX(40:40,COLUMN()-规则表!$F$17)))/规则表!$D$17,1)=0)*($I40:INDEX(40:40,COLUMN()-规则表!$F$17))),0)} -> 0 | R98: {=IF(R$109,SUMPRODUCT(IF(MOD((COLUMN()-规则表!$C$17-COLUMN($D8:INDEX(8:8,COLUMN()-规则表!$C$17)))/规则表!$D$17,1)=0,$D8:INDEX(8:8,COLUMN()-规则表!$C$17),0))-SUMPRODUCT(IF(MOD((COLUMN()-COLUMN($D24:INDEX(24:24,COLUMN())))/规则表!$D$17,1)=0,$D24:INDEX(24:24,COLUMN()),0))+SUMPRODUCT(($I40:INDEX(40:40,COLUMN())<0)*(MOD((COLUMN()-COLUMN($I40:INDEX(40:40,COLUMN())))/规则表!$D$17,1)=0)*($I40:INDEX(40:40,COLUMN())))+SUMPRODUCT(($I40:INDEX(40:40,COLUMN()-规则表!$F$17)>0)*(MOD((COLUMN()-规则表!$F$17-COLUMN($I40:INDEX(40:40,COLUMN()-规则表!$F$17)))/规则表!$D$17,1)=0)*($I40:INDEX(40:40,COLUMN()-规则表!$F$17))),0)} -> 0 | S98: {=IF(S$109,SUMPRODUCT(IF(MOD((COLUMN()-规则表!$C$17-COLUMN($D8:INDEX(8:8,COLUMN()-规则表!$C$17)))/规则表!$D$17,1)=0,$D8:INDEX(8:8,COLUMN()-规则表!$C$17),0))-SUMPRODUCT(IF(MOD((COLUMN()-COLUMN($D24:INDEX(24:24,COLUMN())))/规则表!$D$17,1)=0,$D24:INDEX(24:24,COLUMN()),0))+SUMPRODUCT(($I40:INDEX(40:40,COLUMN())<0)*(MOD((COLUMN()-COLUMN($I40:INDEX(40:40,COLUMN())))/规则表!$D$17,1)=0)*($I40:INDEX(40:40,COLUMN())))+SUMPRODUCT(($I40:INDEX(40:40,COLUMN()-规则表!$F$17)>0)*(MOD((COLUMN()-规则表!$F$17-COLUMN($I40:INDEX(40:40,COLUMN()-规则表!$F$17)))/规则表!$D$17,1)=0)*($I40:INDEX(40:40,COLUMN()-规则表!$F$17))),0)} -> 0 | T98: {=IF(T$109,SUMPRODUCT(IF(MOD((COLUMN()-规则表!$C$17-COLUMN($D8:INDEX(8:8,COLUMN()-规则表!$C$17)))/规则表!$D$17,1)=0,$D8:INDEX(8:8,COLUMN()-规则表!$C$17),0))-SUMPRODUCT(IF(MOD((COLUMN()-COLUMN($D24:INDEX(24:24,COLUMN())))/规则表!$D$17,1)=0,$D24:INDEX(24:24,COLUMN()),0))+SUMPRODUCT(($I40:INDEX(40:40,COLUMN())<0)*(MOD((COLUMN()-COLUMN($I40:INDEX(40:40,COLUMN())))/规则表!$D$17,1)=0)*($I40:INDEX(40:40,COLUMN())))+SUMPRODUCT(($I40:INDEX(40:40,COLUMN()-规则表!$F$17)>0)*(MOD((COLUMN()-规则表!$F$17-COLUMN($I40:INDEX(40:40,COLUMN()-规则表!$F$17)))/规则表!$D$17,1)=0)*($I40:INDEX(40:40,COLUMN()-规则表!$F$17))),0)} -> 0 | U98: {=IF(U$109,SUMPRODUCT(IF(MOD((COLUMN()-规则表!$C$17-COLUMN($D8:INDEX(8:8,COLUMN()-规则表!$C$17)))/规则表!$D$17,1)=0,$D8:INDEX(8:8,COLUMN()-规则表!$C$17),0))-SUMPRODUCT(IF(MOD((COLUMN()-COLUMN($D24:INDEX(24:24,COLUMN())))/规则表!$D$17,1)=0,$D24:INDEX(24:24,COLUMN()),0))+SUMPRODUCT(($I40:INDEX(40:40,COLUMN())<0)*(MOD((COLUMN()-COLUMN($I40:INDEX(40:40,COLUMN())))/规则表!$D$17,1)=0)*($I40:INDEX(40:40,COLUMN())))+SUMPRODUCT(($I40:INDEX(40:40,COLUMN()-规则表!$F$17)>0)*(MOD((COLUMN()-规则表!$F$17-COLUMN($I40:INDEX(40:40,COLUMN()-规则表!$F$17)))/规则表!$D$17,1)=0)*($I40:INDEX(40:40,COLUMN()-规则表!$F$17))),0)} -> 0 | V98: {=IF(V$109,SUMPRODUCT(IF(MOD((COLUMN()-规则表!$C$17-COLUMN($D8:INDEX(8:8,COLUMN()-规则表!$C$17)))/规则表!$D$17,1)=0,$D8:INDEX(8:8,COLUMN()-规则表!$C$17),0))-SUMPRODUCT(IF(MOD((COLUMN()-COLUMN($D24:INDEX(24:24,COLUMN())))/规则表!$D$17,1)=0,$D24:INDEX(24:24,COLUMN()),0))+SUMPRODUCT(($I40:INDEX(40:40,COLUMN())<0)*(MOD((COLUMN()-COLUMN($I40:INDEX(40:40,COLUMN())))/规则表!$D$17,1)=0)*($I40:INDEX(40:40,COLUMN())))+SUMPRODUCT(($I40:INDEX(40:40,COLUMN()-规则表!$F$17)>0)*(MOD((COLUMN()-规则表!$F$17-COLUMN($I40:INDEX(40:40,COLUMN()-规则表!$F$17)))/规则表!$D$17,1)=0)*($I40:INDEX(40:40,COLUMN()-规则表!$F$17))),0)} -> 0 | W98: {=IF(W$109,SUMPRODUCT(IF(MOD((COLUMN()-规则表!$C$17-COLUMN($D8:INDEX(8:8,COLUMN()-规则表!$C$17)))/规则表!$D$17,1)=0,$D8:INDEX(8:8,COLUMN()-规则表!$C$17),0))-SUMPRODUCT(IF(MOD((COLUMN()-COLUMN($D24:INDEX(24:24,COLUMN())))/规则表!$D$17,1)=0,$D24:INDEX(24:24,COLUMN()),0))+SUMPRODUCT(($I40:INDEX(40:40,COLUMN())<0)*(MOD((COLUMN()-COLUMN($I40:INDEX(40:40,COLUMN())))/规则表!$D$17,1)=0)*($I40:INDEX(40:40,COLUMN())))+SUMPRODUCT(($I40:INDEX(40:40,COLUMN()-规则表!$F$17)>0)*(MOD((COLUMN()-规则表!$F$17-COLUMN($I40:INDEX(40:40,COLUMN()-规则表!$F$17)))/规则表!$D$17,1)=0)*($I40:INDEX(40:40,COLUMN()-规则表!$F$17))),0)} -> 0 | X98: {=IF(X$109,SUMPRODUCT(IF(MOD((COLUMN()-规则表!$C$17-COLUMN($D8:INDEX(8:8,COLUMN()-规则表!$C$17)))/规则表!$D$17,1)=0,$D8:INDEX(8:8,COLUMN()-规则表!$C$17),0))-SUMPRODUCT(IF(MOD((COLUMN()-COLUMN($D24:INDEX(24:24,COLUMN())))/规则表!$D$17,1)=0,$D24:INDEX(24:24,COLUMN()),0))+SUMPRODUCT(($I40:INDEX(40:40,COLUMN())<0)*(MOD((COLUMN()-COLUMN($I40:INDEX(40:40,COLUMN())))/规则表!$D$17,1)=0)*($I40:INDEX(40:40,COLUMN())))+SUMPRODUCT(($I40:INDEX(40:40,COLUMN()-规则表!$F$17)>0)*(MOD((COLUMN()-规则表!$F$17-COLUMN($I40:INDEX(40:40,COLUMN()-规则表!$F$17)))/规则表!$D$17,1)=0)*($I40:INDEX(40:40,COLUMN()-规则表!$F$17))),0)} -> 0
B99: 自动线 | C99: P1 | I99: {=SUMPRODUCT(IF(MOD((COLUMN()-规则表!$C$18-COLUMN($D9:INDEX(9:9,COLUMN()-规则表!$C$18)))/规则表!$D$18,1)=0,$D9:INDEX(9:9,COLUMN()-规则表!$C$18),0))-SUMPRODUCT(IF(MOD((COLUMN()-COLUMN($D25:INDEX(25:25,COLUMN())))/规则表!$D$18,1)=0,$D25:INDEX(25:25,COLUMN()),0))+SUMPRODUCT(($I41:INDEX(41:41,COLUMN())<0)*(MOD((COLUMN()-COLUMN($I41:INDEX(41:41,COLUMN())))/规则表!$D$18,1)=0)*($I41:INDEX(41:41,COLUMN())))+SUMPRODUCT(($I41:INDEX(41:41,COLUMN()-规则表!$F$18)>0)*(MOD((COLUMN()-规则表!$F$18-COLUMN($I41:INDEX(41:41,COLUMN()-规则表!$F$18)))/规则表!$D$18,1)=0)*($I41:INDEX(41:41,COLUMN()-规则表!$F$18)))} -> 0 | J99: {=SUMPRODUCT(IF(MOD((COLUMN()-规则表!$C$18-COLUMN($D9:INDEX(9:9,COLUMN()-规则表!$C$18)))/规则表!$D$18,1)=0,$D9:INDEX(9:9,COLUMN()-规则表!$C$18),0))-SUMPRODUCT(IF(MOD((COLUMN()-COLUMN($D25:INDEX(25:25,COLUMN())))/规则表!$D$18,1)=0,$D25:INDEX(25:25,COLUMN()),0))+SUMPRODUCT(($I41:INDEX(41:41,COLUMN())<0)*(MOD((COLUMN()-COLUMN($I41:INDEX(41:41,COLUMN())))/规则表!$D$18,1)=0)*($I41:INDEX(41:41,COLUMN())))+SUMPRODUCT(($I41:INDEX(41:41,COLUMN()-规则表!$F$18)>0)*(MOD((COLUMN()-规则表!$F$18-COLUMN($I41:INDEX(41:41,COLUMN()-规则表!$F$18)))/规则表!$D$18,1)=0)*($I41:INDEX(41:41,COLUMN()-规则表!$F$18)))} -> 0 | K99: {=SUMPRODUCT(IF(MOD((COLUMN()-规则表!$C$18-COLUMN($D9:INDEX(9:9,COLUMN()-规则表!$C$18)))/规则表!$D$18,1)=0,$D9:INDEX(9:9,COLUMN()-规则表!$C$18),0))-SUMPRODUCT(IF(MOD((COLUMN()-COLUMN($D25:INDEX(25:25,COLUMN())))/规则表!$D$18,1)=0,$D25:INDEX(25:25,COLUMN()),0))+SUMPRODUCT(($I41:INDEX(41:41,COLUMN())<0)*(MOD((COLUMN()-COLUMN($I41:INDEX(41:41,COLUMN())))/规则表!$D$18,1)=0)*($I41:INDEX(41:41,COLUMN())))+SUMPRODUCT(($I41:INDEX(41:41,COLUMN()-规则表!$F$18)>0)*(MOD((COLUMN()-规则表!$F$18-COLUMN($I41:INDEX(41:41,COLUMN()-规则表!$F$18)))/规则表!$D$18,1)=0)*($I41:INDEX(41:41,COLUMN()-规则表!$F$18)))} -> 0 | L99: {=SUMPRODUCT(IF(MOD((COLUMN()-规则表!$C$18-COLUMN($D9:INDEX(9:9,COLUMN()-规则表!$C$18)))/规则表!$D$18,1)=0,$D9:INDEX(9:9,COLUMN()-规则表!$C$18),0))-SUMPRODUCT(IF(MOD((COLUMN()-COLUMN($D25:INDEX(25:25,COLUMN())))/规则表!$D$18,1)=0,$D25:INDEX(25:25,COLUMN()),0))+SUMPRODUCT(($I41:INDEX(41:41,COLUMN())<0)*(MOD((COLUMN()-COLUMN($I41:INDEX(41:41,COLUMN())))/规则表!$D$18,1)=0)*($I41:INDEX(41:41,COLUMN())))+SUMPRODUCT(($I41:INDEX(41:41,COLUMN()-规则表!$F$18)>0)*(MOD((COLUMN()-规则表!$F$18-COLUMN($I41:INDEX(41:41,COLUMN()-规则表!$F$18)))/规则表!$D$18,1)=0)*($I41:INDEX(41:41,COLUMN()-规则表!$F$18)))} -> 0 | M99: {=SUMPRODUCT(IF(MOD((COLUMN()-规则表!$C$18-COLUMN($D9:INDEX(9:9,COLUMN()-规则表!$C$18)))/规则表!$D$18,1)=0,$D9:INDEX(9:9,COLUMN()-规则表!$C$18),0))-SUMPRODUCT(IF(MOD((COLUMN()-COLUMN($D25:INDEX(25:25,COLUMN())))/规则表!$D$18,1)=0,$D25:INDEX(25:25,COLUMN()),0))+SUMPRODUCT(($I41:INDEX(41:41,COLUMN())<0)*(MOD((COLUMN()-COLUMN($I41:INDEX(41:41,COLUMN())))/规则表!$D$18,1)=0)*($I41:INDEX(41:41,COLUMN())))+SUMPRODUCT(($I41:INDEX(41:41,COLUMN()-规则表!$F$18)>0)*(MOD((COLUMN()-规则表!$F$18-COLUMN($I41:INDEX(41:41,COLUMN()-规则表!$F$18)))/规则表!$D$18,1)=0)*($I41:INDEX(41:41,COLUMN()-规则表!$F$18)))} -> 0 | N99: {=SUMPRODUCT(IF(MOD((COLUMN()-规则表!$C$18-COLUMN($D9:INDEX(9:9,COLUMN()-规则表!$C$18)))/规则表!$D$18,1)=0,$D9:INDEX(9:9,COLUMN()-规则表!$C$18),0))-SUMPRODUCT(IF(MOD((COLUMN()-COLUMN($D25:INDEX(25:25,COLUMN())))/规则表!$D$18,1)=0,$D25:INDEX(25:25,COLUMN()),0))+SUMPRODUCT(($I41:INDEX(41:41,COLUMN())<0)*(MOD((COLUMN()-COLUMN($I41:INDEX(41:41,COLUMN())))/规则表!$D$18,1)=0)*($I41:INDEX(41:41,COLUMN())))+SUMPRODUCT(($I41:INDEX(41:41,COLUMN()-规则表!$F$18)>0)*(MOD((COLUMN()-规则表!$F$18-COLUMN($I41:INDEX(41:41,COLUMN()-规则表!$F$18)))/规则表!$D$18,1)=0)*($I41:INDEX(41:41,COLUMN()-规则表!$F$18)))} -> 0 | O99: {=SUMPRODUCT(IF(MOD((COLUMN()-规则表!$C$18-COLUMN($D9:INDEX(9:9,COLUMN()-规则表!$C$18)))/规则表!$D$18,1)=0,$D9:INDEX(9:9,COLUMN()-规则表!$C$18),0))-SUMPRODUCT(IF(MOD((COLUMN()-COLUMN($D25:INDEX(25:25,COLUMN())))/规则表!$D$18,1)=0,$D25:INDEX(25:25,COLUMN()),0))+SUMPRODUCT(($I41:INDEX(41:41,COLUMN())<0)*(MOD((COLUMN()-COLUMN($I41:INDEX(41:41,COLUMN())))/规则表!$D$18,1)=0)*($I41:INDEX(41:41,COLUMN())))+SUMPRODUCT(($I41:INDEX(41:41,COLUMN()-规则表!$F$18)>0)*(MOD((COLUMN()-规则表!$F$18-COLUMN($I41:INDEX(41:41,COLUMN()-规则表!$F$18)))/规则表!$D$18,1)=0)*($I41:INDEX(41:41,COLUMN()-规则表!$F$18)))} -> 0 | P99: {=SUMPRODUCT(IF(MOD((COLUMN()-规则表!$C$18-COLUMN($D9:INDEX(9:9,COLUMN()-规则表!$C$18)))/规则表!$D$18,1)=0,$D9:INDEX(9:9,COLUMN()-规则表!$C$18),0))-SUMPRODUCT(IF(MOD((COLUMN()-COLUMN($D25:INDEX(25:25,COLUMN())))/规则表!$D$18,1)=0,$D25:INDEX(25:25,COLUMN()),0))+SUMPRODUCT(($I41:INDEX(41:41,COLUMN())<0)*(MOD((COLUMN()-COLUMN($I41:INDEX(41:41,COLUMN())))/规则表!$D$18,1)=0)*($I41:INDEX(41:41,COLUMN())))+SUMPRODUCT(($I41:INDEX(41:41,COLUMN()-规则表!$F$18)>0)*(MOD((COLUMN()-规则表!$F$18-COLUMN($I41:INDEX(41:41,COLUMN()-规则表!$F$18)))/规则表!$D$18,1)=0)*($I41:INDEX(41:41,COLUMN()-规则表!$F$18)))} -> 0 | Q99: {=IF(Q$109,SUMPRODUCT(IF(MOD((COLUMN()-规则表!$C$18-COLUMN($D9:INDEX(9:9,COLUMN()-规则表!$C$18)))/规则表!$D$18,1)=0,$D9:INDEX(9:9,COLUMN()-规则表!$C$18),0))-SUMPRODUCT(IF(MOD((COLUMN()-COLUMN($D25:INDEX(25:25,COLUMN())))/规则表!$D$18,1)=0,$D25:INDEX(25:25,COLUMN()),0))+SUMPRODUCT(($I41:INDEX(41:41,COLUMN())<0)*(MOD((COLUMN()-COLUMN($I41:INDEX(41:41,COLUMN())))/规则表!$D$18,1)=0)*($I41:INDEX(41:41,COLUMN())))+SUMPRODUCT(($I41:INDEX(41:41,COLUMN()-规则表!$F$18)>0)*(MOD((COLUMN()-规则表!$F$18-COLUMN($I41:INDEX(41:41,COLUMN()-规则表!$F$18)))/规则表!$D$18,1)=0)*($I41:INDEX(41:41,COLUMN()-规则表!$F$18))),0)} -> 0 | R99: {=IF(R$109,SUMPRODUCT(IF(MOD((COLUMN()-规则表!$C$18-COLUMN($D9:INDEX(9:9,COLUMN()-规则表!$C$18)))/规则表!$D$18,1)=0,$D9:INDEX(9:9,COLUMN()-规则表!$C$18),0))-SUMPRODUCT(IF(MOD((COLUMN()-COLUMN($D25:INDEX(25:25,COLUMN())))/规则表!$D$18,1)=0,$D25:INDEX(25:25,COLUMN()),0))+SUMPRODUCT(($I41:INDEX(41:41,COLUMN())<0)*(MOD((COLUMN()-COLUMN($I41:INDEX(41:41,COLUMN())))/规则表!$D$18,1)=0)*($I41:INDEX(41:41,COLUMN())))+SUMPRODUCT(($I41:INDEX(41:41,COLUMN()-规则表!$F$18)>0)*(MOD((COLUMN()-规则表!$F$18-COLUMN($I41:INDEX(41:41,COLUMN()-规则表!$F$18)))/规则表!$D$18,1)=0)*($I41:INDEX(41:41,COLUMN()-规则表!$F$18))),0)} -> 0 | S99: {=IF(S$109,SUMPRODUCT(IF(MOD((COLUMN()-规则表!$C$18-COLUMN($D9:INDEX(9:9,COLUMN()-规则表!$C$18)))/规则表!$D$18,1)=0,$D9:INDEX(9:9,COLUMN()-规则表!$C$18),0))-SUMPRODUCT(IF(MOD((COLUMN()-COLUMN($D25:INDEX(25:25,COLUMN())))/规则表!$D$18,1)=0,$D25:INDEX(25:25,COLUMN()),0))+SUMPRODUCT(($I41:INDEX(41:41,COLUMN())<0)*(MOD((COLUMN()-COLUMN($I41:INDEX(41:41,COLUMN())))/规则表!$D$18,1)=0)*($I41:INDEX(41:41,COLUMN())))+SUMPRODUCT(($I41:INDEX(41:41,COLUMN()-规则表!$F$18)>0)*(MOD((COLUMN()-规则表!$F$18-COLUMN($I41:INDEX(41:41,COLUMN()-规则表!$F$18)))/规则表!$D$18,1)=0)*($I41:INDEX(41:41,COLUMN()-规则表!$F$18))),0)} -> 0 | T99: {=IF(T$109,SUMPRODUCT(IF(MOD((COLUMN()-规则表!$C$18-COLUMN($D9:INDEX(9:9,COLUMN()-规则表!$C$18)))/规则表!$D$18,1)=0,$D9:INDEX(9:9,COLUMN()-规则表!$C$18),0))-SUMPRODUCT(IF(MOD((COLUMN()-COLUMN($D25:INDEX(25:25,COLUMN())))/规则表!$D$18,1)=0,$D25:INDEX(25:25,COLUMN()),0))+SUMPRODUCT(($I41:INDEX(41:41,COLUMN())<0)*(MOD((COLUMN()-COLUMN($I41:INDEX(41:41,COLUMN())))/规则表!$D$18,1)=0)*($I41:INDEX(41:41,COLUMN())))+SUMPRODUCT(($I41:INDEX(41:41,COLUMN()-规则表!$F$18)>0)*(MOD((COLUMN()-规则表!$F$18-COLUMN($I41:INDEX(41:41,COLUMN()-规则表!$F$18)))/规则表!$D$18,1)=0)*($I41:INDEX(41:41,COLUMN()-规则表!$F$18))),0)} -> 0 | U99: {=IF(U$109,SUMPRODUCT(IF(MOD((COLUMN()-规则表!$C$18-COLUMN($D9:INDEX(9:9,COLUMN()-规则表!$C$18)))/规则表!$D$18,1)=0,$D9:INDEX(9:9,COLUMN()-规则表!$C$18),0))-SUMPRODUCT(IF(MOD((COLUMN()-COLUMN($D25:INDEX(25:25,COLUMN())))/规则表!$D$18,1)=0,$D25:INDEX(25:25,COLUMN()),0))+SUMPRODUCT(($I41:INDEX(41:41,COLUMN())<0)*(MOD((COLUMN()-COLUMN($I41:INDEX(41:41,COLUMN())))/规则表!$D$18,1)=0)*($I41:INDEX(41:41,COLUMN())))+SUMPRODUCT(($I41:INDEX(41:41,COLUMN()-规则表!$F$18)>0)*(MOD((COLUMN()-规则表!$F$18-COLUMN($I41:INDEX(41:41,COLUMN()-规则表!$F$18)))/规则表!$D$18,1)=0)*($I41:INDEX(41:41,COLUMN()-规则表!$F$18))),0)} -> 0 | V99: {=IF(V$109,SUMPRODUCT(IF(MOD((COLUMN()-规则表!$C$18-COLUMN($D9:INDEX(9:9,COLUMN()-规则表!$C$18)))/规则表!$D$18,1)=0,$D9:INDEX(9:9,COLUMN()-规则表!$C$18),0))-SUMPRODUCT(IF(MOD((COLUMN()-COLUMN($D25:INDEX(25:25,COLUMN())))/规则表!$D$18,1)=0,$D25:INDEX(25:25,COLUMN()),0))+SUMPRODUCT(($I41:INDEX(41:41,COLUMN())<0)*(MOD((COLUMN()-COLUMN($I41:INDEX(41:41,COLUMN())))/规则表!$D$18,1)=0)*($I41:INDEX(41:41,COLUMN())))+SUMPRODUCT(($I41:INDEX(41:41,COLUMN()-规则表!$F$18)>0)*(MOD((COLUMN()-规则表!$F$18-COLUMN($I41:INDEX(41:41,COLUMN()-规则表!$F$18)))/规则表!$D$18,1)=0)*($I41:INDEX(41:41,COLUMN()-规则表!$F$18))),0)} -> 0 | W99: {=IF(W$109,SUMPRODUCT(IF(MOD((COLUMN()-规则表!$C$18-COLUMN($D9:INDEX(9:9,COLUMN()-规则表!$C$18)))/规则表!$D$18,1)=0,$D9:INDEX(9:9,COLUMN()-规则表!$C$18),0))-SUMPRODUCT(IF(MOD((COLUMN()-COLUMN($D25:INDEX(25:25,COLUMN())))/规则表!$D$18,1)=0,$D25:INDEX(25:25,COLUMN()),0))+SUMPRODUCT(($I41:INDEX(41:41,COLUMN())<0)*(MOD((COLUMN()-COLUMN($I41:INDEX(41:41,COLUMN())))/规则表!$D$18,1)=0)*($I41:INDEX(41:41,COLUMN())))+SUMPRODUCT(($I41:INDEX(41:41,COLUMN()-规则表!$F$18)>0)*(MOD((COLUMN()-规则表!$F$18-COLUMN($I41:INDEX(41:41,COLUMN()-规则表!$F$18)))/规则表!$D$18,1)=0)*($I41:INDEX(41:41,COLUMN()-规则表!$F$18))),0)} -> 0 | X99: {=IF(X$109,SUMPRODUCT(IF(MOD((COLUMN()-规则表!$C$18-COLUMN($D9:INDEX(9:9,COLUMN()-规则表!$C$18)))/规则表!$D$18,1)=0,$D9:INDEX(9:9,COLUMN()-规则表!$C$18),0))-SUMPRODUCT(IF(MOD((COLUMN()-COLUMN($D25:INDEX(25:25,COLUMN())))/规则表!$D$18,1)=0,$D25:INDEX(25:25,COLUMN()),0))+SUMPRODUCT(($I41:INDEX(41:41,COLUMN())<0)*(MOD((COLUMN()-COLUMN($I41:INDEX(41:41,COLUMN())))/规则表!$D$18,1)=0)*($I41:INDEX(41:41,COLUMN())))+SUMPRODUCT(($I41:INDEX(41:41,COLUMN()-规则表!$F$18)>0)*(MOD((COLUMN()-规则表!$F$18-COLUMN($I41:INDEX(41:41,COLUMN()-规则表!$F$18)))/规则表!$D$18,1)=0)*($I41:INDEX(41:41,COLUMN()-规则表!$F$18))),0)} -> 0
